Workbook
Name Appendix_1_Range: 'APPENDIX 1'!$B$3:$R$51
Name Appendix_10: 'APPENDIX 10'!$B$3:$K$37
Name Appendix_11: 'APPENDIX 11'!$B$3:$Q$37
Name Appendix_12: 'APPENDIX 12'!$B$3:$Q$37
Name Appendix_13: 'APPENDIX 13'!$B$3:$Q$37
Name Appendix_14: 'APPENDIX 14'!$B$3:$Q$37
Name Appendix_15: 'APPENDIX 15'!$B$3:$Q$37
Name Appendix_16: 'APPENDIX 16'!$B$3:$Q$37
Name Appendix_17: 'APPENDIX 17'!$B$3:$Q$37
Name Appendix_18: 'APPENDIX 18'!$B$3:$Q$37
Name Appendix_19: 'APPENDIX 19'!$B$3:$Q$37
Name Appendix_2: 'APPENDIX 2'!$B$3:$R$38
Name Appendix_20: 'APPENDIX 20'!$B$3:$I$38
Name Appendix_21: 'APPENDIX 21'!$B$3:$R$50
Name Appendix_22: 'APPENDIX 22'!$B$3:$Q$50
Name Appendix_23: 'APPENDIX 23'!$B$3:$Q$50
Name Appendix_24: 'APPENDIX 24'!$B$3:$Q$50
Name Appendix_25: 'APPENDIX 25'!$B$3:$Q$50
Name Appendix_26: 'APPENDIX 26'!$B$3:$Q$50
Name Appendix_27: 'APPENDIX 27'!$B$3:$Q$50
Name Appendix_28: 'APPENDIX 28'!$B$3:$Q$50
Name Appendix_29: 'APPENDIX 29'!$B$3:$Q$50
Name Appendix_3: 'APPENDIX 3'!$B$3:$R$9
Name Appendix_30: 'APPENDIX 30'!$B$3:$Q$50
Name Appendix_31: 'APPENDIX 31'!$B$3:$Q$50
Name Appendix_32: 'APPENDIX 32'!$B$3:$Q$50
Name Appendix_33: 'APPENDIX 33'!$B$3:$Q$50
Name Appendix_34: 'APPENDIX 34'!$B$3:$Q$50
Name Appendix_35: 'APPENDIX 35'!$B$3:$Q$50
Name Appendix_36: 'APPENDIX 36'!$B$3:$Q$50
Name Appendix_37: 'APPENDIX 37'!$B$3:$Q$50
Name Appendix_38: 'APPENDIX 38'!$B$3:$Q$50
Name Appendix_39: 'APPENDIX 39'!$B$3:$Q$50
Name Appendix_4: 'APPENDIX 4'!$B$3:$H$52
Name Appendix_40: 'APPENDIX 40'!$B$3:$Q$50
Name Appendix_41: 'APPENDIX 41'!$B$3:$Q$50
Name Appendix_42: 'APPENDIX 42'!$B$3:$Q$50
Name Appendix_43: 'APPENDIX 43'!$B$3:$Q$50
Name Appendix_44: 'APPENDIX 44'!$B$3:$Q$50
Name Appendix_45: 'APPENDIX 45'!$B$3:$Q$9
Name Appendix_46: 'APPENDIX 46'!$B$3:$L$33
Name Appendix_47: 'APPENDIX 47'!$B$3:$H$43
Name Appendix_48: 'APPENDIX 48'!$B$3:$H$32
Name Appendix_49: 'APPENDIX 49'!$B$3:$H$9
Name Appendix_50: 'APPENDIX 50'!$B$2:$P$28
Name Appendix_51: 'APPENDIX 51'!$B$3:$L$44
Name Appendix_52: 'APPENDIX 52'!$B$3:$L$44
Name Appendix_53: 'APPENDIX 53'!$B$3:$H$36
Name Appendix_54: 'APPENDIX 54'!$B$3:$H$63
Name Appendix_55I: #REF!
Name Appendix_55II: #REF!
Name Appendix_55III: #REF!
Name Appendix_55IV: #REF!
Name Appendix_55V: #REF!
Name Appendix_55VI: #REF!
Name Appendix_56: #REF!
Name Appendix_57: #REF!
Name Appendix_5I: 'APPENDIX 5 I'!$B$3:$L$43
Name Appendix_5II: 'APPENDIX 5 II'!$B$2:$L$43
Name Appendix_5III: 'APPENDIX 5 III'!$B$2:$K$43

Sheet Details
F7: INSURANCE REGULATORY AUTHORITY | M7: Quarterly | N7: 2010
M8: Annual | N8: 2011
N9: 2012
N10: 2013
N11: 2015
F12: TYPE OF INDUSTRY STATISTICS | G12: ANNUAL AUDITED | N12: 2016
N13: 2017
N14: 2019
F15: FOR THE YEAR | G15: 2024 | N15: 2020
N16: 2021
F18: PERIOD ENDED | G18: 31ST DECEMBER 2024 | N18: 2022
N19: 2024
F21: PREPARED BY | G21: INSURANCE REGULATORY AUTHORITY
G22: AUGUST, 2025
N23: 2024
N24: 2025
N25: 2026
N26: 2027
N27: 2028
N28: 2029
N29: 2030
N30: 2031
N31: 2032
N32: 2033
N33: 2034
N34: 2035
... N51: 2052

Sheet Reliance & Limitations
B3: RELIANCE AND LIMITATIONS
B4: The insurance information contained in this workbook has been extracted from the annual audited returns submitted to the Authority in line with Section 54 of the Insurance Act. No adjustments have been made to the returns’ data except where necessary in consultation with the affected insurer(s) or reinsurer(s). The publication of any summary of the returns in this report does not necessarily mean that the returns so summarized have satisfied all the requirements of the Insurance Act, or that the Commissioner of Insurance approves the accuracy or the contents of the returns Where necessary, figures have been adjusted to eliminate errors in totals due to rounding off, and are given in thousands Kenya shillings (‘000’ KES) except where otherwise stated. Also to note, the 2024 data is provisional. The report did not incorporate annual audited data for Trident Insurance Company Limited and KUSCCO Mutual Assurance Limited due to non-submission of the annual returns. However, unaudited Q4 2024 data for KUSCCO Mutual Assurance Limited was used in place of the audited figures. In addition, data for Invesco Assurance Company Limited was excluded as the company was placed under statutory management during the year under review.

Sheet Contents
E2: INSURANCE REGULATORY AUTHORITY
E4: 2024 DATA
E5: TABLE of CONTENTS
B6: Sheet Name | C6: Label | E6: Link | F6: Description
B8: T1 | C8: Trends 1 | E8: =HYPERLINK("#'" & B8 & "'!A1", C8) -> Trends 1 | F8: Economy and Insurance Industry Trends
B9: T2 | C9: Trends 2 | E9: =HYPERLINK("#'" & B9 & "'!A1", C9) -> Trends 2 | F9: Trends in Long-Term Insurance Business
B10: T3 | C10: Trends 3 | E10: =HYPERLINK("#'" & B10 & "'!A1", C10) -> Trends 3 | F10: Trends in General Insurance Business
B11: T4 | C11: Trends 4 | E11: =HYPERLINK("#'" & B11 & "'!A1", C11) -> Trends 4 | F11: Trends in Microinsurance Business
B12: T5 | C12: Trends 5 | E12: =HYPERLINK("#'" & B12 & "'!A1", C12) -> Trends 5 | F12: Trends in Re-insurance Business
B13: APPENDIX 1 | C13: APPENDIX 1 | E13: =HYPERLINK("#'" & B13 & "'!A1", C13) -> APPENDIX 1 | F13: Summary of Profit & Loss Accounts under General Insurance Business for the Year Ended 31.12.2024
B14: APPENDIX 2 | C14: APPENDIX 2 | E14: =HYPERLINK("#'" & B14 & "'!A1", C14) -> APPENDIX 2 | F14: Summary of Profit & Loss Accounts Long-Term Insurance Business for the Year Ended 31.12.2024
B15: APPENDIX 3 | C15: APPENDIX 3 | E15: =HYPERLINK("#'" & B15 & "'!A1", C15) -> APPENDIX 3 | F15: Summary of Profit & Loss Accounts Microinsurance Business for the Year Ended 31.12.2024
B16: APPENDIX 4 | C16: APPENDIX 4 | E16: =HYPERLINK("#'" & B16 & "'!A1", C16) -> APPENDIX 4 | F16: Summary of Net Commissions and Management Expenses for the Year Ended 31.12.2024
B17: APPENDIX 5 I | C17: APPENDIX 5 I | E17: =HYPERLINK("#'" & B17 & "'!A1", C17) -> APPENDIX 5 I | F17: Summary of Long Term Insurance Business Balance Sheets as at 31.12.2024
B18: APPENDIX 5 II | C18: APPENDIX 5 II | E18: =HYPERLINK("#'" & B18 & "'!A1", C18) -> APPENDIX 5 II | F18: Summary of Long Term Insurance Business Balance Sheets as at 31.12.2024
B19: APPENDIX 5 III | C19: APPENDIX 5 III | E19: =HYPERLINK("#'" & B19 & "'!A1", C19) -> APPENDIX 5 III | F19: Summary of Long Term Insurance Business Balance Sheets as at 31.12.2024
... B71: APPENDIX 54 | C71: APPENDIX 54 | E71: =HYPERLINK("#'" & B71 & "'!A1", C71) -> APPENDIX 54 | F71: Summary of Industry Livestock Agriculture Insurance for the Year Ended 31.12.2024

Sheet T1
C3: Table 1: Economy and Insurance Industry Trends
C6: a) Economy and Insurance Indicators
D7: Years
D8: 2013 | E8: 2014 | F8: 2015 | G8: 2016 | H8: 2017 | I8: 2018 | J8: 2019 | K8: 2020 | L8: 2021 | M8: =L8+1 -> 2022 | N8: 2023 | O8: 2024*
C9: Gross Direct Premium (KES Billion) | D9: 129.19 | E9: 155.8 | F9: 172.54012 | G9: 195.22965 | H9: 207.6 | I9: 214.9 | J9: 227.9 | K9: 233.1 | L9: 270.46828 | M9: 306.69307 | N9: 360.67855 | O9: =('APPENDIX 8'!K31+'APPENDIX 21'!Q42+'APPENDIX 46'!F10)/10^6 -> 397.06487
C10: Gross Direct Premium Growth Rate (%) | F10: 10.744623 | G10: 13.150289 | H10: =(H9/G9-1)*100 -> 6.3363086 | I10: =(I9/H9-1)*100 -> 3.5163776 | J10: =(J9/I9-1)*100 -> 6.0493253 | K10: =(K9/J9-1)*100 -> 2.2817025 | L10: 16.03101 | M10: 13.393358 | N10: 17.602447 | O10: =(O9/N9-1)*100 -> 10.088296
C11: GDP (Market Prices) KES Billion* | D11: 4745.1434 | E11: 5402.41 | F11: 6284.2 | G11: 7022.96 | H11: 8483.4 | I11: 9340.3 | J11: 10237.73 | K11: 10715.07 | L11: 12027.662 | M11: 13368.34 | N11: 15108.806 | O11: 16224.5
C12: GDP (%) growth rate (at market prices) | D12: 11.352532 | E12: 13.851354 | F12: 16.32216 | G12: 11.8 | H12: =(H11/G11-1)*100 -> 20.79522 | I12: =(I11/H11-1)*100 -> 10.100903 | J12: =(J11/I11-1)*100 -> 9.6081496 | K12: =(K11/J11-1)*100 -> 4.662557 | L12: =(L11/K11-1)*100 -> 12.249957 | M12: 11.146626 | N12: 13.019312 | O12: =(O11/N11-1)*100 -> 7.3843963
C13: Insurance Penetration ratio (%) (at current prices) | D13: 2.7225731 | E13: 2.8838981 | F13: 2.7456179 | G13: 2.78 | H13: 2.55 | I13: 2.43 | J13: 2.34 | K13: 2.1754408 | L13: 2.2487188 | M13: 2.2941747 | N13: 2.3872075 | O13: =(O9/O11)*100 -> 2.4473165
C14: Population (Million)* | D14: 41.8 | E14: 43 | F14: 44.2 | G14: 45.4 | H14: 45.3 | I14: 46.4 | J14: 47.6 | K14: 48.8 | L14: 49.7 | M14: 50.6 | N14: 51.5 | O14: 52.43
C15: Insurance Density (KES) | D15: 3090.6699 | E15: 3623.2558 | F15: 3903.6227 | G15: 4300.2125 | H15: 4455 | I15: 4525 | J15: 4788 | K15: 4776.6393 | L15: 5442.0178 | M15: 6061.1278 | N15: 7003.467 | O15: =(O9/O14)*1000 -> 7573.2381
C16: Lives Covered (Million) | D16: 2.058619 | E16: 2.470662 | F16: 4.390843 | G16: 3.82463 | H16: 4.26 | I16: 4.3 | J16: 11.65 | K16: 13.44 | L16: 13.478245 | M16: 14.22** | N16: 13.599477 | O16: ='APPENDIX 48'!G31/10^6 -> 13.530404
C17: Policies (LT,GB & Micro) (Million) | D17: 2.77243 | E17: 3.815534 | F17: 2.702272 | G17: 3.390335 | H17: 3.14 | I17: 3.43 | J17: 3.96 | L17: 4.07759 | M17: 8.713364 | N17: 12.104754 | O17: =('APPENDIX 47'!F42+'APPENDIX 48'!F31+'APPENDIX 49'!F8)/10^6 -> 14.308442
C18: Insurance cover (Lives/population) % | D18: 4.9249258 | E18: 5.7457256 | F18: 9.9340339 | G18: 8.4242952 | H18: 9.1 | I18: 9 | J18: 24.5 | K18: 27.540984 | L18: 27.119205 | M18: 28.110484 | N18: 26.406751 | O18: =(O16/O14)*100 -> 25.806608
C19: Insurance Cover (policies/population) % | D19: 6.6326077 | E19: 8.8733349 | F19: 6.1137376 | G19: 7.4676982 | H19: 6.7 | I19: 7.1 | J19: 8.3 | L19: 8.2044064 | M19: 17.220087 | N19: 23.504377 | O19: =(O17/O14)*100 -> 27.290563
C20: Rate of Inflation (%)* | D20: 5.7 | E20: 6.9 | F20: 6.6 | G20: 6.3 | H20: 8 | I20: 4.7 | J20: 5.2 | K20: 5.4 | L20: 5.62 | M20: 7.66 | N20: 7.67 | O20: 4.525
C21: Real Gross Direct Premium growth (%) | D21: 9.2156853 | E21: 12.813442 | F21: 3.8880137 | G21: 6.4442984 | H21: =(((100+H10)/(100+H20))-1)*100 -> -1.540455 | I21: =(((100+I10)/(100+I20))-1)*100 -> -1.1304894 | J21: =(((100+J10)/(100+J20))-1)*100 -> 0.80734341 | K21: =(((100+K10)/(100+K20))-1)*100 -> -2.9585365 | L21: =(((100+L10)/(100+L20))-1)*100 -> 9.857044 | M21: 5.3254299 | N21: 9.2248969 | O21: =(((100+O10)/(100+O20))-1)*100 -> 5.3224545
C22: Sources: KNBS, CBK and IRA Statistics Population in 2024 is based on 2019 projections done by KNBS *information has been updated to reflect the most updated information available **Revised
C25: b) Trend in some key insurance indicators
C26: Item | D26: Years | P26: Annual Change 2023/2024 %
D27: 2013 | E27: 2014 | F27: 2015 | G27: 2016 | H27: 2017 | I27: 2018 | J27: 2019 | K27: 2020 | L27: 2021 | M27: =L27+1 -> 2022 | N27: =M27+1 -> 2023 | O27: =O8 -> 2024*
C28: Gross Premium Income | D28: 135384923 | E28: 157732058 | F28: 174039164 | G28: 196635836 | H28: 209001296 | I28: 216261729 | J28: 229499718 | K28: 234775753 | L28: 273710831 | M28: 310273121 | N28: 3.6501795e+08 | O28: =('APPENDIX 8'!$K$31+'APPENDIX 39'!$C$42+'APPENDIX 39'!$D$42+'APPENDIX 46'!F10) -> 4.0059456e+08 | P28: =(O28-N28)/ABS(N28) *100 -> 9.7465392
C29: Net Premium Written | D29: 105013409 | E29: 126333481 | F29: 139377049 | G29: 158362431 | H29: 165852034 | I29: 172322202 | J29: 182658282 | K29: 187853004 | L29: 221133803 | M29: 249190282 | N29: 2.8749921e+08 | O29: =('APPENDIX 19'!$E$31+'APPENDIX 39'!$F$42) -> 3.2027453e+08 | P29: =(O29-N29)/ABS(N29) *100 -> 11.40014
C30: Claims Incurred (general business) | D30: 34170145 | E30: 42677696 | F30: 48811202 | G30: 54857495 | H30: 56151966 | I30: 56927996 | J30: 58961582 | K30: 58311459 | L30: 69835740 | M30: 77095546 | N30: 87688511 | O30: =SUM('APPENDIX 42'!C42:P42) -> 98762568 | P30: =(O30-N30)/ABS(N30) *100 -> 12.628857
C31: Net commissions | D31: 7204448 | E31: 14332657 | F31: 10833473 | G31: 12578735 | H31: 12495182 | I31: 11487628 | J31: 10957562 | K31: 11157093 | L31: 13521938 | M31: 15341053 | N31: 17528063 | O31: =('APPENDIX 19'!$L$31+'APPENDIX 39'!$M$42) -> 18414098 | P31: =(O31-N31)/ABS(N31) *100 -> 5.05495
C32: Expenses of Management | D32: 24808273 | E32: 49249464 | F32: 35991670 | G32: 39982771 | H32: 41197258 | I32: 44072857 | J32: 45702207 | K32: 44173611 | L32: 46513554 | M32: 50280745 | N32: 59386080 | O32: =('APPENDIX 19'!$M$31+'APPENDIX 39'!$N$42) -> 59851116 | P32: =(O32-N32)/ABS(N32) *100 -> 0.7830726
C33: Underwriting Results (general business) | D33: 3402770 | E33: 1604507 | F33: -274188 | G33: -2125731 | H33: -1027851 | I33: -2588861 | J33: -3165405 | K33: -1847726 | L33: -6333631 | M33: -3270383 | N33: -6039288.7 | O33: ='APPENDIX 39'!$O$42 -> -3678306.7 | P33: =(O33-N33)/ABS(N33) *100 -> 39.093709
C34: Investment Income(P&L) | D34: 9429214 | E34: 11095059 | F34: 6294523 | G34: 5338509 | H34: 6596592 | I34: 6967045 | J34: 9132215 | K34: 4879906 | L34: 7283075 | M34: 7041440 | N34: 72238709 | O34: ='APPENDIX 1'!$G$50+'APPENDIX 2'!$G$37 -> 1.4000145e+08 | P34: =(O34-N34)/ABS(N34) *100 -> 93.803927
C35: Operating profit/loss after taxation | D35: 20245881 | E35: 17232015 | F35: 13564434 | G35: 12835309 | H35: 13642972 | I35: 7269268 | J35: 15119928 | K35: 6388955 | L35: 8645622 | M35: 14715312 | N35: 23459372 | O35: ='APPENDIX 1'!$R$50+'APPENDIX 2'!$R$37 -> 30423137 | P35: =(O35-N35)/ABS(N35) *100 -> 29.684358
C36: Investments | D36: 296336802 | E36: 355009404 | F36: 390225346 | G36: 425304138 | H36: 483799656 | I36: 524237249 | J36: 596011648 | K36: 656460833 | L36: 733461323 | M36: 833722972 | N36: 7.1086498e+08 | O36: ='APPENDIX 5 III'!$N$46+'APPENDIX 5 III'!$O$46+'APPENDIX 6 IV'!$P$44+'APPENDIX 6 IV'!$Q$44 -> 8.6009332e+08 | P36: =(O36-N36)/ABS(N36) *100 -> 20.992501
C37: Assets | D37: 366252339 | E37: 430536097 | F37: 478752455 | G37: 528748193 | H37: 590953330 | I37: 635035110 | J37: 711247445 | K37: 765932477 | L37: 850506382 | M37: 956871079 | N37: 1.0768615e+09 | O37: ='APPENDIX 5 III'!K42+'APPENDIX 6 IV'!M40 -> 1.2520461e+09 | P37: =(O37-N37)/ABS(N37) *100 -> 16.268071
C38: Shareholder’s Funds | D38: 100958028 | E38: 114141212 | F38: 125830028 | G38: 134455222 | H38: 147255002 | I38: 149134602 | J38: 161835044 | K38: 166069303 | L38: 167914107 | M38: 184166513 | N38: 2.1043713e+08 | O38: ='APPENDIX 5 III'!$K$12+'APPENDIX 6 IV'!M11 -> 2.3206429e+08 | P38: =(O38-N38)/ABS(N38) *100 -> 10.277252
C39: Amounts in Thousands
C40: *Provisional

Sheet T2
C4: Table 2: Trends in Long-Term Insurance Business
C6: a) Summary of long term insurance business performance
C7: Indicators | D7: Years | P7: Annual Change 2023/2024 %
D8: 2013 | E8: 2014 | F8: 2015 | G8: 2016 | H8: 2017 | I8: 2018 | J8: 2019 | K8: 2020 | L8: 2021 | M8: =L8+1 -> 2022 | N8: =M8+1 -> 2023 | O8: 2024*
C9: Gross Direct Premium | D9: 44424411 | E9: 56581380 | F9: 62064805 | G9: 73519181 | H9: 82807826 | I9: 87408352 | J9: 97395510 | K9: 102078013 | L9: 123687148 | M9: 140953582 | N9: 1.7007501e+08 | O9: ='APPENDIX 19'!$D$31 -> 1.917987e+08 | P9: =(O9-N9)/ABS(N9) *100 -> 12.773001
C10: Outward Reinsurance | D10: 2731261 | E10: 3856486 | F10: 4983380 | G10: 5666993 | H10: 5860038 | I10: 7048742 | J10: 7529611 | K10: 6751093 | L10: 9081590 | M10: 12025131 | N10: 15517575 | O10: =(O9-O11) -> 14987211 | P10: =(O10-N10)/ABS(N10) *100 -> -3.4178243
C11: Net Premiums | D11: 41693150 | E11: 52718917 | F11: 57081418 | G11: 67852188 | H11: 76947788 | I11: 80359610 | J11: 89865899 | K11: 95326920 | L11: 114605558 | M11: 128928451 | N11: 1.5455744e+08 | O11: ='APPENDIX 19'!$E$31 -> 1.7681149e+08 | P11: =(O11-N11)/ABS(N11) *100 -> 14.39856
C12: Management expenses | D12: 7637766 | E12: 28460004 | F12: 11279207 | G12: 12364010 | H12: 12072033 | I12: 13928440 | J12: 15362328 | K12: 14381760 | L12: 15689550 | M12: 17456624 | N12: 20034446 | O12: ='APPENDIX 19'!$M$31 -> 22349821 | P12: =(O12-N12)/ABS(N12) *100 -> 11.556968
C13: Net Commissions | D13: 3432164 | E13: 9618165 | F13: 5152743 | G13: 5474094 | H13: 5448401 | I13: 4887507 | J13: 5277712 | K13: 5793085 | L13: 6493140 | M13: 7254217 | N13: 7727024 | O13: ='APPENDIX 19'!$L$31 -> 9157713.9 | P13: =(O13-N13)/ABS(N13) *100 -> 18.515407
C14: Life Fund C/F | D14: 137229500 | E14: 1.9329355e+08 | F14: 231885634 | G14: 255648171 | H14: 301571353 | I14: 333263364 | J14: 387780599 | K14: 426165838 | L14: 494301595 | M14: 574251284 | N14: 6.5734458e+08 | O14: ='APPENDIX 19'!$Q$31 -> 8.057781e+08 | P14: =(O14-N14)/ABS(N14) *100 -> 22.580778
C17: b) Summary of long term insurance business performance per class
C18: Indicators | E18: Years | H18: Years | P18: =P7 -> Annual Change 2023/2024 %
D19: 2013 | E19: 2014 | F19: 2015 | G19: 2016 | H19: 2017 | I19: 2018 | J19: 2019 | K19: 2020 | L19: 2021 | M19: =L19+1 -> 2022 | N19: =M19+1 -> 2023 | O19: =O8 -> 2024*
C20: Gross Direct Premium
C21: Life Assurances | D21: 13310197 | E21: 14363846 | F21: 16783137 | G21: 18880725 | H21: 21374928 | I21: 24331504 | J21: 28187025 | K21: 29549666 | L21: 34107231 | M21: 35547858 | N21: 38836382 | O21: ='APPENDIX 11'!$D$31 -> 42457066 | P21: =(O21-N21)/ABS(N21) *100 -> 9.3229177
C22: Annuities | D22: 1331213 | E22: 6358440 | F22: 4137425 | G22: 4698479 | H22: 9834902 | I22: 6880785 | J22: 7451904 | K22: 8208247 | L22: 9290658 | M22: 10036388 | N22: 12351081 | O22: ='APPENDIX 12'!$D$31 -> 12356888 | P22: =(O22-N22)/ABS(N22) *100 -> 0.047016521
C23: Personal Pensions | D23: 16089228 | E23: 14099531 | F23: 22002402 | G23: 28118598 | H23: 4497901 | I23: 4138741 | J23: 5486479 | K23: 5825247 | L23: 6804397 | M23: 8111970 | N23: 16207214 | O23: ='APPENDIX 14'!D31 -> 21729305 | P23: =(O23-N23)/ABS(N23) *100 -> 34.071809
C24: Deposit Administration | H24: 24588257 | I24: 29775545 | J24: 32237072 | K24: 34857836 | L24: 42355599 | M24: 50954518 | N24: 61704945 | O24: ='APPENDIX 15'!D31 -> 68244152 | P24: =(O24-N24)/ABS(N24) *100 -> 10.59754
C25: Group Life | D25: 3038834 | E25: 9331736 | F25: 9858591 | G25: 10600535 | H25: 12765171 | I25: 11031270 | J25: 10957689 | K25: 9665028 | L25: 14334101 | M25: 16785151 | N25: 21668737 | O25: ='APPENDIX 13'!$D$31 -> 24669467 | P25: =(O25-N25)/ABS(N25) *100 -> 13.848201
C26: Group Credit | D26: 1943 | E26: 4265352 | F26: 4816710 | G26: 6306075 | H26: 5208397 | I26: 7740166 | J26: 9516603 | K26: 10010766 | L26: 12978038 | M26: 15445861 | N26: 15748325 | O26: ='APPENDIX 16'!$D$31 -> 14560401 | P26: =IFERROR((O26-N26)/ABS(N26) *100,0) -> -7.5431748
C27: Permanent Health | D27: 6426533 | E27: 0 | F27: 0 | G27: 0 | H27: - | I27: - | J27: - | K27: - | L27: 0 | M27: 15757 | N27: 0 | O27: ='APPENDIX 17'!$D$31 -> 0 | P27: =IFERROR((O27-N27)/ABS(N27) *100,0) -> 0
C28: Investments | D28: 4226463 | E28: 8163684 | F28: 4422409 | G28: 4914770 | H28: 4538271 | I28: 3510341 | J28: 3558738 | K28: 3961223 | L28: 3817124 | M28: 4056079 | N28: 3558330.7 | O28: ='APPENDIX 18'!$D$31 -> 7781418.3 | P28: =(O28-N28)/ABS(N28) *100 -> 118.6817
C29: Total | D29: 44424411 | E29: 56582589 | F29: 62020674 | G29: 73519182 | H29: 82807826 | I29: 87408352 | J29: 97395510 | K29: 102078013 | L29: 123687148 | M29: 140953582 | N29: 1.7007501e+08 | O29: =SUM(O21:O28) -> 1.917987e+08 | P29: =(O29-N29)/ABS(N29) *100 -> 12.773001
C30: Net Premiums
C31: Life Assurances | D31: 13114458 | E31: 14163998 | F31: 16562968 | G31: 18669399 | H31: 21122113 | I31: 24106317 | J31: 27970560 | K31: 29313231 | L31: 33862799 | M31: 35267956 | N31: 38491286 | O31: ='APPENDIX 11'!$E$31 -> 41996916 | P31: =(O31-N31)/ABS(N31) *100 -> 9.1075958
C32: Annuities | D32: 1331213 | E32: 6358440 | F32: 4137425 | G32: 4698479 | H32: 9834897 | I32: 6880785 | J32: 7451904 | K32: 8208247 | L32: 9272486 | M32: 10018249 | N32: 12332971 | O32: ='APPENDIX 12'!$E$31 -> 12338795 | P32: =(O32-N32)/ABS(N32) *100 -> 0.047221195
C33: Personal Pensions | D33: 16089228 | E33: 14099531 | F33: 22002402 | G33: 28118598 | H33: 4497901 | I33: 4138741 | J33: 5486479 | K33: 5825247 | L33: 6804397 | M33: 8111970 | N33: 16207214 | O33: ='APPENDIX 14'!E31 -> 21729305 | P33: =(O33-N33)/ABS(N33) *100 -> 34.071809
C34: Deposit Administration | H34: 24588257 | I34: 29775545 | J34: 32237072 | K34: 34857836 | L34: 42355599 | M34: 50954518 | N34: 61704945 | O34: ='APPENDIX 15'!E31 -> 68244152 | P34: =(O34-N34)/ABS(N34) *100 -> 10.59754
C35: Group Life | D35: 3020246 | E35: 6020998 | F35: 5805185 | G35: 6412173 | H35: 8666923 | I35: 5633076 | J35: 5561462 | K35: 5450274 | L35: 8154809 | M35: 9020611 | N35: 9061642.1 | O35: ='APPENDIX 13'!$E$31 -> 12198302 | P35: =IFERROR((O35-N35)/ABS(N35) *100,0) -> 34.614695
C36: Group Credit | D36: 1943 | E36: 3913711 | F36: 4106976 | G36: 5038769 | H36: 3699427 | I36: 6314805 | J36: 7599816 | K36: 7711080 | L36: 10339239 | M36: 11485915 | N36: 13201198 | O36: ='APPENDIX 16'!$E$31 -> 12522648 | P36: =IFERROR((O36-N36)/ABS(N36) *100,0) -> -5.1400607
C37: Permanent Health | D37: 4127806 | E37: 0 | F37: 0 | G37: 0 | H37: - | I37: - | J37: - | K37: - | L37: 0 | M37: 13185 | N37: 0 | O37: ='APPENDIX 17'!$E$31 -> 0 | P37: =IFERROR((O37-N37)/ABS(N37) *100,0) -> 0
C38: Investments | D38: 4008265 | E38: 8163451 | F38: 4422331 | G38: 4914770 | H38: 4538271 | I38: 3510341 | J38: 3558606 | K38: 3961005 | L38: 3816229 | M38: 4056047 | N38: 3558184.2 | O38: ='APPENDIX 18'!$E$31 -> 7781368.2 | P38: =(O38-N38)/ABS(N38) *100 -> 118.6893
C39: Total | D39: 41693149 | E39: 52720129 | F39: 57037287 | G39: 67852188 | H39: 76947788 | I39: 80359610 | J39: 89865899 | K39: 95326920 | L39: 114605558 | M39: 128928451 | N39: 1.5455744e+08 | O39: =SUM(O31:O38) -> 1.7681149e+08 | P39: =(O39-N39)/ABS(N39) *100 -> 14.39856
C40: Net Commissions
C41: Life Assurances | D41: 2930874 | E41: 3184836 | F41: 3760565 | G41: 4314129 | H41: 4089626 | I41: 3841617 | J41: 4178191 | K41: 4406912 | L41: 4344451 | M41: 4709382 | N41: 5554528.5 | O41: ='APPENDIX 11'!$L$31 -> 5927242.1 | P41: =IFERROR((O41-N41)/ABS(N41) *100,0) -> 6.7100854
C42: Annuities | D42: 18430 | E42: 137180 | F42: 103094 | G42: 71677 | H42: 174395 | I42: 111012 | J42: 156043 | K42: 164128 | L42: 174330 | M42: 194641 | N42: 215563.3 | O42: ='APPENDIX 12'!$L$31 -> 250142.9 | P42: =IFERROR((O42-N42)/ABS(N42) *100,0) -> 16.041504
C43: Personal Pensions | D43: 134547 | E43: 161911 | F43: 191723 | G43: 350075 | H43: 55033 | I43: 39355 | J43: 61199 | K43: 68987 | L43: 86775 | M43: 97312 | N43: 130552.5 | O43: ='APPENDIX 14'!L31 -> 198223.95 | P43: =IFERROR((O43-N43)/ABS(N43) *100,0) -> 51.834656
C44: Deposit Administration | H44: 265098 | I44: 283451 | J44: 332644 | K44: 333964 | L44: 445466 | M44: 628537 | N44: 709036.13 | O44: ='APPENDIX 15'!L31 -> 953381.9 | P44: =IFERROR((O44-N44)/ABS(N44) *100,0) -> 34.461682
C45: Group Life | D45: 128988 | E45: 92494 | F45: 222082 | G45: 89220 | H45: 351110 | I45: -56828 | J45: -338650 | K45: -64499 | L45: 598376 | M45: 308784 | N45: 326283.4 | O45: ='APPENDIX 13'!$L$31 -> 120575.49 | P45: =IFERROR((O45-N45)/ABS(N45) *100,0) -> -63.04578
C46: Group Credit | D46: 13 | E46: 189041 | F46: 441028 | G46: 427617 | H46: 319000 | I46: 479268 | J46: 511910 | K46: 757675 | L46: 735799 | M46: 1246815 | N46: 711495.43 | O46: ='APPENDIX 16'!$L$31 -> 1601621.5 | P46: =IFERROR((O46-N46)/ABS(N46) *100,0) -> 125.10637
C47: Permanent Health | D47: -26090 | E47: 0 | F47: 0 | G47: 0 | H47: - | I47: - | J47: - | K47: - | L47: 0 | M47: 514 | N47: 0 | O47: ='APPENDIX 17'!$L$31 -> 0 | P47: =IFERROR((O47-N47)/ABS(N47) *100,0) -> 0
C48: Investments | D48: 245399 | E48: 448182 | F48: 434248 | G48: 221377 | H48: 194139 | I48: 189631 | J48: 376375 | K48: 125918 | L48: 107943 | M48: 68232 | N48: 79564.722 | O48: ='APPENDIX 18'!$L$31 -> 106526.05 | P48: =(O48-N48)/ABS(N48) *100 -> 33.886034
C49: Total | D49: 3432161 | E49: 4213644 | F49: 5152740 | G49: 5474095 | H49: 5448401 | I49: 4887507 | J49: 5277712 | K49: 5793085 | L49: 6493140 | M49: 7254217 | N49: 7727024 | O49: =SUM(O41:O48) -> 9157713.9 | P49: =(O49-N49)/ABS(N49) *100 -> 18.515407
C50: Management Expenses
C51: Life Assurances | D51: 4061029 | E51: 5216983 | F51: 5978723 | G51: 6864778 | H51: 6046834 | I51: 6968920 | J51: 7995319 | K51: 7633138 | L51: 7364010 | M51: 7747091 | N51: 8380874.2 | O51: ='APPENDIX 11'!$M$31 -> 9645730.6 | P51: =IFERROR((O51-N51)/ABS(N51) *100,0) -> 15.092178
C52: Annuities | D52: 73522 | E52: 190496 | F52: 269555 | G52: 216835 | H52: 230153 | I52: 221561 | J52: 249092 | K52: 224184 | L52: 235090 | M52: 216492 | N52: 270406.7 | O52: ='APPENDIX 12'!$M$31 -> 388959.45 | P52: =IFERROR((O52-N52)/ABS(N52) *100,0) -> 43.842385
C53: Personal Pensions | D53: 955924 | E53: 1059753 | F53: 1283823 | G53: 1239403 | H53: 159799 | I53: 220130 | J53: 255376 | K53: 234889 | L53: 284364 | M53: 320309 | N53: 852581.61 | O53: ='APPENDIX 14'!M31 -> 1168290.2 | P53: =IFERROR((O53-N53)/ABS(N53) *100,0) -> 37.029726
C54: Deposit Administration | H54: 1302405 | I54: 1728708 | J54: 1693233 | K54: 1813835 | L54: 1964306 | M54: 2302079 | N54: 2360278.2 | O54: ='APPENDIX 15'!M31 -> 2775368.4 | P54: =IFERROR((O54-N54)/ABS(N54) *100,0) -> 17.586495
C55: Group Life | D55: 678354 | E55: 1486792 | F55: 1578524 | G55: 1573914 | H55: 1830361 | I55: 2114840 | J55: 1827250 | K55: 1749964 | L55: 2591938 | M55: 3398806 | N55: 4055487.7 | O55: ='APPENDIX 13'!$M$31 -> 3989712.6 | P55: =IFERROR((O55-N55)/ABS(N55) *100,0) -> -1.6218781
C56: Group Credit | D56: 0 | E56: 937610 | F56: 1290586 | G56: 1586621 | H56: 1609944 | I56: 1709742 | J56: 2519063 | K56: 1877442 | L56: 2635282 | M56: 3029677 | N56: 3260955.9 | O56: ='APPENDIX 16'!$M$31 -> 3403632.3 | P56: =IFERROR((O56-N56)/ABS(N56) *100,0) -> 4.3752939
C57: Permanent Health | D57: 1037683 | E57: 0 | F57: 0 | G57: 0 | H57: - | I57: - | J57: - | K57: - | L57: 0 | M57: 2786 | N57: 0 | O57: ='APPENDIX 17'!$M$31 -> 0 | P57: =IFERROR((O57-N57)/ABS(N57) *100,0) -> 0
C58: Investments | D58: 831259 | E58: 740921 | F58: 877989 | G58: 882462 | H58: 892539 | I58: 964539 | J58: 822995 | K58: 848308 | L58: 614560 | M58: 439384 | N58: 853862.1 | O58: ='APPENDIX 18'!$M$31 -> 978127.26 | P58: =(O58-N58)/ABS(N58) *100 -> 14.553306
C59: Total | D59: 7637771 | E59: 9632555 | F59: 11279200 | G59: 12364013 | H59: 12072033 | I59: 13928440 | J59: 15362328 | K59: 14381760 | L59: 15689550 | M59: 17456624 | N59: 20034446 | O59: =SUM(O51:O58) -> 22349821 | P59: =(O59-N59)/ABS(N59) *100 -> 11.556968
C60: Amounts in '000' KES
C61: *Provisional

Sheet T3
C4: Table 3: Trends in General Insurance Business
C7: a) Classwise GDP under general insurance business
C8: Class of business | D8: Years | P8: Annual Change 2023/2024 %
D9: 2013 | E9: 2014 | F9: 2015 | G9: 2016 | H9: 2017 | I9: 2018 | J9: 2019 | K9: 2020 | L9: 2021 | M9: =L9+1 -> 2022 | N9: =M9+1 -> 2023 | O9: 2024*
C10: Aviation | D10: 1127429 | E10: 1200632 | F10: 1484892 | G10: 1476801 | H10: 1726496 | I10: 2134254 | J10: 2109320 | K10: 2963413 | L10: 3094410 | M10: 3564550 | N10: 4558254.5 | O10: ='[1]APPENDIX 21'!C$42 -> 4879911.3 | P10: =(O10-N10)/ABS(N10) *100 -> 7.0565769
C11: Engineering | D11: 2776577 | E11: 3547973 | F11: 3794202 | G11: 3473125 | H11: 4190323 | I11: 3691508 | J11: 3502268 | K11: 3249381 | L11: 4283167 | M11: 5064942 | N11: 4418421.4 | O11: ='[1]APPENDIX 21'!D$42 -> 4992920.1 | P11: =(O11-N11)/ABS(N11) *100 -> 13.002351
C12: Fire Domestic | D12: 1272835 | E12: 1347967 | F12: 1388204 | G12: 1482865 | H12: 1570425 | I12: 1595804 | J12: 1672639 | K12: 1795320 | L12: 1770893 | M12: 1815381 | N12: 2033724.9 | O12: ='[1]APPENDIX 21'!E$42 -> 2081468.1 | P12: =(O12-N12)/ABS(N12) *100 -> 2.3475777
C13: Fire industrial | D13: 7637802 | E13: 8757929 | F13: 9547284 | G13: 10062935 | H13: 11130626 | I13: 10824386 | J13: 10870577 | K13: 10776438 | L13: 12949770 | M13: 16828541 | N13: 19599395 | O13: ='[1]APPENDIX 21'!F$42 -> 21870299 | P13: =(O13-N13)/ABS(N13) *100 -> 11.586599
C14: Liability | D14: 1560128 | E14: 1891331 | F14: 2191880 | G14: 2520106 | H14: 2817584 | I14: 2728902 | J14: 3124267 | K14: 3124468 | L14: 3358022 | M14: 3723336 | N14: 4657601.9 | O14: ='[1]APPENDIX 21'!G$42 -> 5224758.4 | P14: =(O14-N14)/ABS(N14) *100 -> 12.177008
C15: Marine | D15: 2775148 | E15: 2726463 | F15: 2852402 | G15: 2604270 | H15: 3555639 | I15: 3370608 | J15: 3188714 | K15: 3063641 | L15: 3637910 | M15: 4054753 | N15: 4350308.1 | O15: ='[1]APPENDIX 21'!H$42 -> 4739988.1 | P15: =(O15-N15)/ABS(N15) *100 -> 8.9575253
C16: Motor Private | D16: 13909445 | E16: 16382944 | F16: 18430997 | G16: 20460256 | H16: 21484964 | I16: 22495605 | J16: 23431002 | K16: 23449022 | L16: 24626670 | M16: 27855160 | N16: 30182712 | O16: ='[1]APPENDIX 21'!I$42 -> 30668659 | P16: =(O16-N16)/ABS(N16) *100 -> 1.6100179
C17: Motor Commercial | D17: 19536285 | E17: 22553021 | F17: 24091465 | G17: 24025770 | H17: 23226291 | I17: 23593081 | J17: 23049684 | K17: 21279353 | L17: 24279823 | M17: 26132363 | N17: 26508100 | O17: =('[1]APPENDIX 21'!J$42+'[1]APPENDIX 21'!K$42) -> 27120958 | P17: =(O17-N17)/ABS(N17) *100 -> 2.3119667
C18: Personal Accident | D18: 3250304 | E18: 3604559 | F18: 3882018 | G18: 3997282 | H18: 3516204 | I18: 3157233 | J18: 3283857 | K18: 2362292 | L18: 2400674 | M18: 2331266 | N18: 2911861.4 | O18: ='[1]APPENDIX 21'!L$42 -> 2995600.5 | P18: =(O18-N18)/ABS(N18) *100 -> 2.8757937
C19: Theft | D19: 3289650 | E19: 3553715 | F19: 3786845 | G19: 3774820 | H19: 3784701 | I19: 3863654 | J19: 3835945 | K19: 3851366 | L19: 3992205 | M19: 4119725 | N19: 4804844.9 | O19: ='[1]APPENDIX 21'!M$42 -> 5479902.4 | P19: =(O19-N19)/ABS(N19) *100 -> 14.049517
C20: Workmen's Compensation | D20: 4666576 | E20: 5174648 | F20: 5346077 | G20: 5601571 | H20: 5675906 | I20: 6225354 | J20: 6358473 | K20: 6233992 | L20: 10659325 | M20: 11712076 | N20: 12583481 | O20: ='[1]APPENDIX 21'!N$42 -> 12644257 | P20: =(O20-N20)/ABS(N20) *100 -> 0.48298231
C21: Medical | D21: 20507131 | E21: 25315035 | F21: 29516467 | G21: 38520439 | H21: 38337371 | I21: 40195984 | J21: 42348102 | K21: 45061539 | L21: 47586164 | M21: 54839172 | N21: 66227984 | O21: ='[1]APPENDIX 21'!O$42 -> 76203263 | P21: =(O21-N21)/ABS(N21) *100 -> 15.06203
C22: Miscellaneous | D22: 2456310 | E22: 3120075 | F22: 3487951 | G22: 3710221 | H22: 3763080 | I22: 3635343 | J22: 3741207 | K22: 3847235 | L22: 4142108 | M22: 3698214 | N22: 6865120.8 | O22: ='[1]APPENDIX 21'!P$42 -> 6129963.2 | P22: =(O22-N22)/ABS(N22) *100 -> -10.70859
C23: Total | D23: 84765620 | E23: 99176292 | F23: 109800684 | G23: 121710461 | H23: 124779610 | I23: 127511716 | J23: 130516055 | K23: 131057460 | L23: 146781141 | M23: 165739479 | N23: 1.8970181e+08 | O23: =SUM(O10:O22) -> 2.0503195e+08 | P23: =(O23-N23)/ABS(N23) *100 -> 8.0811764
C24: Amounts in '000' KES
C27: b) Incurred claims under general insurance business
C28: Class of business | D28: Years | P28: =P8 -> Annual Change 2023/2024 %
D29: 2013 | E29: 2014 | F29: 2015 | G29: 2016 | H29: 2017 | I29: 2018 | J29: 2019 | K29: 2020 | L29: 2021 | M29: =L29+1 -> 2022 | N29: =M29+1 -> 2023 | O29: =O9 -> 2024*
C30: Aviation | D30: 15144 | E30: 5915 | F30: 12888 | G30: 69815 | H30: -48571 | I30: 28336 | J30: 9285 | K30: 43775 | L30: -3515 | M30: 5880 | N30: 12740.992 | O30: ='[1]APPENDIX 42'!C$42 -> 32901.149 | P30: =(O30-N30)/ABS(N30) *100 -> 158.23067
C31: Engineering | D31: 301706 | E31: 366679 | F31: 468625 | G31: 448796 | H31: 431756 | I31: 411244 | J31: 597785 | K31: 697881 | L31: 592670 | M31: 708591 | N31: 637053.5 | O31: ='[1]APPENDIX 42'!D$42 -> 857092.66 | P31: =(O31-N31)/ABS(N31) *100 -> 34.540137
C32: Fire Domestic | D32: 337000 | E32: 289864 | F32: 483004 | G32: 523792 | H32: 309981 | I32: 477500 | J32: 414559 | K32: 394133 | L32: 421323 | M32: 205136 | N32: 378506.01 | O32: ='[1]APPENDIX 42'!E$42 -> 908594.61 | P32: =(O32-N32)/ABS(N32) *100 -> 140.04761
C33: Fire industrial | D33: 803448 | E33: 801192 | F33: 1177669 | G33: 988870 | H33: 1100373 | I33: 1141362 | J33: 825219 | K33: 1149283 | L33: 979632 | M33: 1486378 | N33: 1164292.3 | O33: ='[1]APPENDIX 42'!F$42 -> 2754740.2 | P33: =(O33-N33)/ABS(N33) *100 -> 136.60212
C34: Liability | D34: 253807 | E34: 316224 | F34: 430841 | G34: 661618 | H34: 340822 | I34: 597548 | J34: 399152 | K34: 462135 | L34: 636608 | M34: 513688 | N34: 1052329.4 | O34: ='[1]APPENDIX 42'!G$42 -> 489318.87 | P34: =(O34-N34)/ABS(N34) *100 -> -53.501358
C35: Marine | D35: 560436 | E35: 566269 | F35: 631426 | G35: 503037 | H35: 725376 | I35: 669398 | J35: 669464 | K35: 598869 | L35: 1043536 | M35: 748793 | N35: 624592.88 | O35: ='[1]APPENDIX 42'!H$42 -> 628714.52 | P35: =(O35-N35)/ABS(N35) *100 -> 0.65989199
C36: Motor Private | D36: 8784204 | E36: 10957919 | F36: 12723572 | G36: 14968463 | H36: 14181895 | I36: 14301162 | J36: 16635527 | K36: 15418425 | L36: 18015197 | M36: 19585676 | N36: 19800801 | O36: ='[1]APPENDIX 42'!I$42 -> 20554433 | P36: =(O36-N36)/ABS(N36) *100 -> 3.8060716
C37: Motor Commercial | D37: 9271908 | E37: 10746378 | F37: 12858229 | G37: 12750248 | H37: 12646816 | I37: 13618583 | J37: 15304543 | K37: 14705102 | L37: 17884591 | M37: 17686508 | N37: 19386931 | O37: =('[1]APPENDIX 42'!J$42+'[1]APPENDIX 42'!K$42) -> 20440523 | P37: =(O37-N37)/ABS(N37) *100 -> 5.4345455
C38: Personal Accident | D38: 884041 | E38: 1296968 | F38: 672415 | G38: 1237073 | H38: 1081310 | I38: 747352 | J38: 464566 | K38: 481601 | L38: 1063712 | M38: -294008 | N38: 266099.71 | O38: ='[1]APPENDIX 42'!L$42 -> 255250.56 | P38: =(O38-N38)/ABS(N38) *100 -> -4.0770961
C39: Theft | D39: 1143607 | E39: 1238056 | F39: 770640 | G39: 1192206 | H39: 969900 | I39: 1304641 | J39: 887812 | K39: 722603 | L39: 860395 | M39: 694374 | N39: 979561.85 | O39: ='[1]APPENDIX 42'!M$42 -> 1352820.5 | P39: =(O39-N39)/ABS(N39) *100 -> 38.10465
C40: Workmen's Compensation | D40: 2024589 | E40: 2649305 | F40: 2666925 | G40: 2987368 | H40: 3126587 | I40: 2374487 | J40: 1548271 | K40: 1910300 | L40: 1752873 | M40: 2291780 | N40: 2846599.2 | O40: ='[1]APPENDIX 42'!N$42 -> 3056513.2 | P40: =(O40-N40)/ABS(N40) *100 -> 7.3742048
C41: Medical | D41: 9260252 | E41: 12774064 | F41: 15063107 | G41: 18095577 | H41: 20632162 | I41: 20515402 | J41: 20424313 | K41: 20975226 | L41: 25941119 | M41: 32583822 | N41: 39104741 | O41: ='[1]APPENDIX 42'!O$42 -> 46113366 | P41: =(O41-N41)/ABS(N41) *100 -> 17.922696
C42: Miscellaneous | D42: 529996 | E42: 668871 | F42: 851856 | G42: 430629 | H42: 653554 | I42: 740981 | J42: 781086 | K42: 752126 | L42: 647599 | M42: 878928 | N42: 1434261.9 | O42: ='[1]APPENDIX 42'!P$42 -> 1318299.7 | P42: =(O42-N42)/ABS(N42) *100 -> -8.085146
C43: Total | D43: 34170138 | E43: 42677704 | F43: 48811197 | G43: 54857492 | H43: 56151961 | I43: 56927996 | J43: 58961582 | K43: 58311459 | L43: 69835740 | M43: 77095546 | N43: 87688511 | O43: =SUM(O30:O42) -> 98762568 | P43: =(O43-N43)/ABS(N43) *100 -> 12.628857
C44: Amounts in '000' KES
C47: c) Classwise underwriting results- General
C48: Class of business | D48: Years | P48: =P8 -> Annual Change 2023/2024 %
D49: 2013 | E49: 2014 | F49: 2015 | G49: 2016 | H49: 2017 | I49: 2018 | J49: 2019 | K49: 2020 | L49: 2021 | M49: =L49+1 -> 2022 | N49: =M49+1 -> 2023 | O49: =O9 -> 2024*
C50: Aviation | D50: 4944 | E50: -20306 | F50: -59485 | G50: -90552 | H50: -253123 | I50: -159479 | J50: -79233 | K50: -253828 | L50: -23730 | M50: -44626 | N50: -143547.55 | O50: ='[1]APPENDIX 44'!C$42 -> -68157.82 | P50: =(O50-N50)/ABS(N50) *100 -> 52.518993
C51: Engineering | D51: 80353 | E51: -121414 | F51: 75372 | G51: -58087 | H51: 70708 | I51: 25627 | J51: -130356 | K51: -196231 | L51: -102927 | M51: -164954 | N51: -138163.47 | O51: ='[1]APPENDIX 44'!D$42 -> -206504.93 | P51: =(O51-N51)/ABS(N51) *100 -> -49.464203
C52: Fire Domestic | D52: 145523 | E52: 258437 | F52: -19648 | G52: 44379 | H52: 238670 | I52: -275853 | J52: 171455 | K52: 208960 | L52: 153611 | M52: 402307 | N52: 134967.59 | O52: ='[1]APPENDIX 44'!E$42 -> -340681.44 | P52: =(O52-N52)/ABS(N52) *100 -> -352.41723
C53: Fire industrial | D53: 337267 | E53: -24125 | F53: 16134 | G53: 37031 | H53: -116886 | I53: 367656 | J53: 380424 | K53: -124730 | L53: 325500 | M53: -27105 | N53: 157350.45 | O53: ='[1]APPENDIX 44'!F$42 -> -490064.66 | P53: =(O53-N53)/ABS(N53) *100 -> -411.44789
C54: Liability | D54: 161704 | E54: 520157 | F54: 92095 | G54: 139993 | H54: 469143 | I54: 131790 | J54: -62178 | K54: 290997 | L54: 75221 | M54: 225887 | N54: -87690.779 | O54: ='[1]APPENDIX 44'!G$42 -> 490047.37 | P54: =(O54-N54)/ABS(N54) *100 -> 658.83569
C55: Marine | D55: 412861 | E55: 870568 | F55: 148713 | G55: 312675 | H55: 322049 | I55: 450260 | J55: 501522 | K55: 276702 | L55: 96685 | M55: 639103 | N55: 4251.1282 | O55: ='[1]APPENDIX 44'!H$42 -> 655692.31 | P55: =(O55-N55)/ABS(N55) *100 -> 15323.96
C56: Motor Private | D56: -693880 | E56: -1732887 | F56: -3101547 | G56: -3291827 | H56: -2930081 | I56: -2578206 | J56: -4182589 | K56: -2924093 | L56: -5525904 | M56: -4803423 | N56: -2694927.5 | O56: ='[1]APPENDIX 44'!I$42 -> -1376281.3 | P56: =(O56-N56)/ABS(N56) *100 -> 48.930673
C57: Motor Commercial | D57: 1403051 | E57: 1408890 | F57: 725825 | G57: 820734 | H57: 933287 | I57: -873562 | J57: -2656785 | K57: -2623740 | L57: -3998359 | M57: -2471334 | N57: -3437763.5 | O57: =('[1]APPENDIX 44'!J$42+'[1]APPENDIX 44'!K$42) -> -3321558.1 | P57: =(O57-N57)/ABS(N57) *100 -> 3.3802608
C58: Personal Accident | D58: 192881 | E58: 91968 | F58: 832092 | G58: -341214 | H58: -178485 | I58: 235783 | J58: 518298 | K58: 195586 | L58: -1339169 | M58: -178226 | N58: 346840.07 | O58: ='[1]APPENDIX 44'!L$42 -> 417512.16 | P58: =(O58-N58)/ABS(N58) *100 -> 20.375986
C59: Theft | D59: 185391 | E59: 396536 | F59: 617293 | G59: 180312 | H59: 473312 | I59: 216899 | J59: 398438 | K59: 459958 | L59: 262379 | M59: -396121 | N59: 224385.98 | O59: ='[1]APPENDIX 44'!M$42 -> -159078.31 | P59: =(O59-N59)/ABS(N59) *100 -> -170.89494
C60: Workmen's Compensation | D60: 424801 | E60: 84434 | F60: 56231 | G60: -100665 | H60: -223460 | I60: 619342 | J60: 1679536 | K60: 1450202 | L60: 2968958 | M60: 2972204 | N60: 1694350.9 | O60: ='[1]APPENDIX 44'!N$42 -> 1846178.7 | P60: =(O60-N60)/ABS(N60) *100 -> 8.9608252
C61: Medical | D61: 282523 | E61: -396895 | F61: -118033 | G61: -621635 | H61: 82523 | I61: -1008230 | J61: 139634 | K61: 1329826 | L61: 243530 | M61: 123125 | N61: -1943800 | O61: ='[1]APPENDIX 44'!O$42 -> -1859373.5 | P61: =(O61-N61)/ABS(N61) *100 -> 4.343375
C62: Miscellaneous | D62: 465349 | E62: 269146 | F62: 508677 | G62: 843122 | H62: 84499 | I62: 259106 | J62: 156433 | K62: 62663 | L62: 530569 | M62: 452785 | N62: -155542.95 | O62: ='[1]APPENDIX 44'!P$42 -> 733962.87 | P62: =(O62-N62)/ABS(N62) *100 -> 571.87151
C63: Total | D63: 3402768 | E63: 1604509 | F63: -226281 | G63: -2125734 | H63: -1027844 | I63: -2588867 | J63: -3165401 | K63: -1847728 | L63: -6333636 | M63: -3270378 | N63: -6039289.7 | O63: =SUM(O50:O62) -> -3678306.7 | P63: =(O63-N63)/ABS(N63) *100 -> 39.09372
C64: Amounts in '000' KES
C65: *Provisional
C66: c) Claims paid under general insurance business
C67: Class of business | D67: Years | P67: =P28 -> Annual Change 2023/2024 %
D68: 2013 | E68: 2014 | F68: 2015 | G68: 2016 | H68: 2017 | I68: 2018 | J68: 2019 | K68: 2020 | L68: 2021 | M68: =L68+1 -> 2022 | N68: =M68+1 -> 2023 | O68: =O29 -> 2024*
C69: Aviation | G69: 3954 | H69: 17227 | I69: 28326 | J69: 13896 | K69: 31473 | L69: 4917 | M69: 481 | N69: 16603.563 | O69: {=TRANSPOSE('APPENDIX 41'!C42:I42)} -> 23175.062 | P69: =(O69-N69)/ABS(N69) *100 -> 39.578852
C70: Engineering | G70: 474786 | H70: 420142 | I70: 404207 | J70: 480487 | K70: 488550 | L70: 196128 | M70: 441535 | N70: 974822.44 | O70: 619878.85 | P70: =(O70-N70)/ABS(N70) *100 -> -36.411101
C71: Fire Domestic | G71: 482889 | H71: 388295 | I71: 465487 | J71: 412050 | K71: 343471 | L71: 422190 | M71: 294726 | N71: 335180.71 | O71: 810458.41 | P71: =(O71-N71)/ABS(N71) *100 -> 141.79745
C72: Fire industrial | G72: 1062102 | H72: 839432 | I72: 1150510 | J72: 725293 | K72: 1152263 | L72: 1019715 | M72: 964804 | N72: 1222094 | O72: 2176010.2 | P72: =(O72-N72)/ABS(N72) *100 -> 78.055871
C73: Liability | G73: -31009 | H73: 428903 | I73: 479916 | J73: 652332 | K73: 522066 | L73: 527442 | M73: 582474 | N73: 678668.04 | O73: 686395.78 | P73: =(O73-N73)/ABS(N73) *100 -> 1.1386631
C74: Marine | G74: 601667 | H74: 671686 | I74: 696801 | J74: 615633 | K74: 615359 | L74: 768393 | M74: 556487 | N74: 716443.35 | O74: 712798.85 | P74: =(O74-N74)/ABS(N74) *100 -> -0.50869311
C75: Motor Private | G75: 13199636 | H75: 13284812 | I75: 13999436 | J75: 15042499 | K75: 14321052 | L75: 15798656 | M75: 17888773 | N75: 19110848 | O75: 19319578 | P75: =(O75-N75)/ABS(N75) *100 -> 1.0922095
C76: Motor Commercial | G76: 11976725 | H76: 12194156 | I76: 12847537 | J76: 13555318 | K76: 12680018 | L76: 14635565 | M76: 15688563 | N76: 17496799 | O76: ='APPENDIX 41'!J42+'APPENDIX 41'!K42 -> 16608824 | P76: =(O76-N76)/ABS(N76) *100 -> -5.0750712
C77: Personal Accident | G77: 1106139 | H77: 937071 | I77: 890480 | J77: 596099 | K77: 574984 | L77: 346776 | M77: 418816 | N77: 521187.3 | O77: {=TRANSPOSE('APPENDIX 41'!L42:Q42)} -> 428132.8 | P77: =(O77-N77)/ABS(N77) *100 -> -17.854328
C78: Theft | G78: 1051544 | H78: 1015916 | I78: 1186695 | J78: 990421 | K78: 922779 | L78: 785518 | M78: 724694 | N78: 999101.65 | O78: 1188189 | P78: =(O78-N78)/ABS(N78) *100 -> 18.925736
C79: Workmen's Compensation | G79: 2068823 | H79: 2442082 | I79: 2394545 | J79: 1707426 | K79: 2021022 | L79: 1950319 | M79: 1864269 | N79: 2276009.7 | O79: 2803720.7 | P79: =(O79-N79)/ABS(N79) *100 -> 23.185796
C80: Medical | G80: 17744012 | H80: 19323478 | I80: 20689826 | J80: 20833719 | K80: 20114975 | L80: 25603549 | M80: 31379497 | N80: 37624516 | O80: 44812938 | P80: =(O80-N80)/ABS(N80) *100 -> 19.105688
C81: Miscellaneous | G81: 580122 | H81: 584304 | I81: 638076 | J81: 848374 | K81: 786181 | L81: 732620 | M81: 814739 | N81: 1099024.2 | O81: 1168656.2 | P81: =(O81-N81)/ABS(N81) *100 -> 6.3357982
C82: Total | G82: 50321390 | H82: 52547504 | I82: 55871842 | J82: 56473547 | K82: 54574193 | L82: 62791788 | M82: 71619858 | N82: 83071298 | O82: 91358756 | P82: =(O82-N82)/ABS(N82) *100 -> 9.9763203
C83: Amounts in '000' KES

Sheet T4
C4: Table 3: Trends in Microinsurance Business
C7: a) Classwise GDP under microinsurance business
C8: Class of business | E8: Distribution 2024 %
D9: 2024*
C10: Life | D10: {=TRANSPOSE('[1]APPENDIX 46'!C10:E10)} -> 2573.596 | E10: =($D10/$D$13)*100 -> 1.0987666
C11: General | D11: 224030.32 | E11: =($D11/$D$13)*100 -> 95.64711
C12: Bundled | D12: 7622 | E12: =($D12/$D$13)*100 -> 3.2541233
C13: Total | D13: =SUM(D10:D12) -> 234225.91 | E13: =($D13/$D$13)*100 -> 100
C14: Amounts in '000' KES
C17: b) Incurred claims under microinsurance business
C18: Class of business | E18: =E8 -> Distribution 2024 %
D19: =D9 -> 2024*
C20: Life | D20: {=TRANSPOSE('[1]APPENDIX 46'!I17:K17)} -> 470.147 | E20: =($D20/$D$23)*100 -> 1.5829063
C21: General | D21: 27954.209 | E21: =($D21/$D$23)*100 -> 94.117147
C22: Bundled | D22: 1277.149 | E22: =($D22/$D$23)*100 -> 4.2999471
C23: Total | D23: =SUM(D20:D22) -> 29701.505 | E23: =($D23/$D$23)*100 -> 100
C24: Amounts in '000' KES
C27: c) Classwise claims paid under Microinsurance business
C28: Class of business | E28: =E8 -> Distribution 2024 %
D29: =D9 -> 2024*
C30: Life | D30: {=TRANSPOSE('[1]APPENDIX 46'!I10:K10)} -> 247.396 | E30: =($D30/$D$33) *100 -> 0.72990965
C31: General | D31: 32741.462 | E31: =($D31/$D$33) *100 -> 96.599416
C32: Bundled | D32: 905.2 | E32: =($D32/$D$33) *100 -> 2.6706746
C33: Total | D33: =SUM(D30:D32) -> 33894.058 | E33: =($D33/$D$33) *100 -> 100
C34: Amounts in '000' KES
C35: *Provisional

Sheet T5
C5: Table 4: Trends in Re-Insurance Business
C7: a) Performance for long term reinsurers
C8: Item | D8: Years | P8: Annual Change 2023/2024 %
D9: 2013 | E9: 2014 | F9: 2015 | G9: 2016 | H9: 2017 | I9: 2018 | J9: 2019 | K9: 2020 | L9: 2021 | M9: =L9+1 -> 2022 | N9: =M9+1 -> 2023 | O9: 2024*
C10: Life Assurances
C11: Inward reinsurance premium | D11: 174580 | E11: 134022 | F11: 114245 | G11: 152658 | H11: 179830 | I11: 239839 | J11: 246317 | K11: 239008 | L11: 96544 | M11: 294833 | N11: 163636.36 | O11: ='[1]APPENDIX 11'!D36 -> 216341.66 | P11: =(O11-N11)/ABS(N11) *100 -> 32.208793
C12: Outward reinsurance premium | D12: 18743 | E12: 1971 | F12: 4689 | G12: 17602 | H12: 22747 | I12: 10701 | J12: 10826 | K12: 60950 | L12: 12676 | M12: 9734 | N12: -8370.834 | O12: =O11-O13 -> 27316.379 | P12: =(O12-N12)/ABS(N12) *100 -> 426.32804
C13: Net premium income | D13: 155837 | E13: 119828 | F13: 119828 | G13: 135056 | H13: 157083 | I13: 229138 | J13: 235491 | K13: 178058 | L13: 83868 | M13: 285099 | N13: 172007.2 | O13: ='[1]APPENDIX 11'!$E$36 -> 189025.28 | P13: =(O13-N13)/ABS(N13) *100 -> 9.8938213
C14: Management expenses | D14: 29506 | E14: 71834 | F14: 54739 | G14: 18330 | H14: 26601 | I14: 25995 | J14: 27293 | K14: 38231 | L14: 42152 | M14: 19968 | N14: 7237.4876 | O14: ='[1]APPENDIX 11'!$M$36 -> 20872.755 | P14: =(O14-N14)/ABS(N14) *100 -> 188.3978
C15: Net commissions | D15: 50521 | E15: 21550 | F15: 21550 | G15: 59375 | H15: 47993 | I15: 29873 | J15: 62932 | K15: 57205 | L15: 18673 | M15: 69592 | N15: 45172.838 | O15: ='[1]APPENDIX 11'!$L$36 -> 60180.861 | P15: =(O15-N15)/ABS(N15) *100 -> 33.223556
C16: Life fund c/f | D16: 1033636 | E16: 1171464 | F16: 1177990 | G16: 1203305 | H16: 1241040 | I16: 1386391 | J16: 1496517 | K16: 1534174 | L16: 1617766 | M16: 1773012 | N16: 514261.87 | O16: ='[1]APPENDIX 11'!Q36 -> 570243.66 | P16: =(O16-N16)/ABS(N16) *100 -> 10.885854
C17: Group Life
C18: Inward reinsurance premium | D18: 1318142 | E18: 1485325 | F18: 1971822 | G18: 2247254 | H18: 2591325 | I18: 3014166 | J18: 3545208 | K18: 2906584 | L18: 3033758 | M18: 2783551 | N18: 3545454.1 | O18: ='[1]APPENDIX 13'!$D$36 -> 4024420 | P18: =(O18-N18)/ABS(N18) *100 -> 13.509295
C19: outward reinsurance premium | D19: 146482 | E19: 32671 | F19: 48362 | G19: 305800 | H19: 303096 | I19: 324320 | J19: 387934 | K19: 267328 | L19: 334085 | M19: 313071 | N19: 2953229.3 | O19: =O18-O20 -> 409398.08 | P19: =(O19-N19)/ABS(N19) *100 -> -86.137274
C20: Net premium income | D20: 1171660 | E20: 1301827 | F20: 1718421 | G20: 1941454 | H20: 2288229 | I20: 2689846 | J20: 3157274 | K20: 2639256 | L20: 2699673 | M20: 2470480 | N20: 592224.78 | O20: ='[1]APPENDIX 13'!$E$36 -> 3615021.9 | P20: =(O20-N20)/ABS(N20) *100 -> 510.41382
C21: Management expenses | D21: 218806 | E21: 558274 | F21: 699719 | G21: 249450 | H21: 325124 | I21: 302888 | J21: 353897 | K21: 220382 | L21: 372816 | M21: 190833 | N21: -8482.7292 | O21: ='[1]APPENDIX 13'!$M$36 -> 253100.04 | P21: =(O21-N21)/ABS(N21) *100 -> 3083.71
C22: Net commissions | D22: 283922 | E22: 224720 | F22: 287252 | G22: 546986 | H22: 624144 | I22: 751119 | J22: 896634 | K22: 766785 | L22: 680777 | M22: 661340 | N22: 704866.39 | O22: ='[1]APPENDIX 13'!$L$36 -> 1090700.3 | P22: =(O22-N22)/ABS(N22) *100 -> 54.738583
C23: Life fund | D23: 4491195 | E23: 5121829 | F23: 5748174 | G23: 5445849 | H23: 5975024 | I23: 6315119 | J23: 7372750 | K23: 8132130 | L23: 8872267 | M23: 10979707 | N23: 7353568.3 | O23: ='[1]APPENDIX 13'!Q36 -> 9023495.5 | P23: =(O23-N23)/ABS(N23) *100 -> 22.709072
C24: Amounts in '000' KES
C27: b) Underwriting results under general reinsurance business
C28: Class of business | D28: Years | P28: =P8 -> Annual Change 2023/2024 %
D29: 2013 | E29: 2014 | F29: 2015 | G29: 2016 | H29: 2017 | I29: 2018 | J29: 2019 | K29: 2020 | L29: 2021 | M29: =L29+1 -> 2022 | N29: =M29+1 -> 2023 | O29: =O9 -> 2024*
C30: Aviation | D30: 3331 | E30: -22366 | F30: 74718 | G30: -19756 | H30: -12834 | I30: 4542 | J30: -18729 | K30: -1077 | L30: 12288 | M30: -7566 | N30: 86421.122 | O30: ='[1]APPENDIX 44'!C$49 -> 7991.4753 | P30: =(O30-N30)/ABS(N30) *100 -> -90.752868
C31: Engineering | D31: 280151 | E31: 110074 | F31: 228806 | G31: 205944 | H31: 172210 | I31: 223258 | J31: 275016 | K31: -480240 | L31: -228919 | M31: 242981 | N31: 634761.44 | O31: ='[1]APPENDIX 44'!D$49 -> 718617.22 | P31: =(O31-N31)/ABS(N31) *100 -> 13.210598
C32: Fire Domestic | D32: -9183 | E32: 1862 | F32: 329788 | G32: -19084 | H32: 8328 | I32: 6529 | J32: 528720 | K32: 688589 | L32: 7543 | M32: 77166 | N32: -258786.17 | O32: ='[1]APPENDIX 44'!E$49 -> -410525.79 | P32: =(O32-N32)/ABS(N32) *100 -> -58.635132
C33: Fire industrial | D33: 560765 | E33: 629912 | F33: -691401 | G33: -671791 | H33: -612432 | I33: -38213 | J33: -245061 | K33: -358002 | L33: 737729 | M33: 1043748 | N33: -635116.85 | O33: ='[1]APPENDIX 44'!F$49 -> 670535 | P33: =(O33-N33)/ABS(N33) *100 -> 205.57664
C34: Liability | D34: 39519 | E34: 85149 | F34: 46463 | G34: 63275 | H34: 51506 | I34: 109221 | J34: 82632 | K34: 86751 | L34: 128529 | M34: 63606 | N34: 164119.31 | O34: ='[1]APPENDIX 44'!G$49 -> -1046906 | P34: =(O34-N34)/ABS(N34) *100 -> -737.89327
C35: Marine | D35: 140630 | E35: 286894 | F35: 80212 | G35: 47746 | H35: 152505 | I35: -88587 | J35: -2835 | K35: 272698 | L35: 37675 | M35: -161572 | N35: 104092.73 | O35: ='[1]APPENDIX 44'!H$49 -> 333210.11 | P35: =(O35-N35)/ABS(N35) *100 -> 220.10893
C36: Motor Private | D36: 3145 | E36: 8360 | F36: 7999 | G36: 18107 | H36: 48544 | I36: 27724 | J36: 29459 | K36: -581735 | L36: 72407 | M36: 321433 | N36: 52289.865 | O36: ='[1]APPENDIX 44'!I$49 -> -62706.766 | P36: =(O36-N36)/ABS(N36) *100 -> -219.92145
C37: Motor Commercial | D37: 91193 | E37: 102325 | F37: 644 | G37: 120356 | H37: 269786 | I37: -122896 | J37: -828633 | K37: -1043466 | L37: -31434 | M37: 8677 | N37: -80579.038 | O37: =('[1]APPENDIX 44'!J$49+'[1]APPENDIX 44'!K49) -> 295163.42 | P37: =(O37-N37)/ABS(N37) *100 -> 466.30299
C38: Personal Accident | D38: -109200 | E38: -379110 | F38: -93734 | G38: 583453 | H38: 38268 | I38: -189387 | J38: -2583962 | K38: 2132340 | L38: 68492 | M38: 295464 | N38: 751834.8 | O38: ='[1]APPENDIX 44'!L$49 -> 1393776.3 | P38: =(O38-N38)/ABS(N38) *100 -> 85.383319
C39: Theft | D39: -205259 | E39: -150893 | F39: 106261 | G39: 142121 | H39: 264811 | I39: 101026 | J39: 255472 | K39: 8109 | L39: 108588 | M39: 24356 | N39: -154875.58 | O39: ='[1]APPENDIX 44'!M$49 -> 117080.71 | P39: =(O39-N39)/ABS(N39) *100 -> 175.59663
C40: Workmen's Compensation | D40: -4749 | E40: 9437 | F40: 234983 | G40: 3264 | H40: 9140 | I40: 3768 | J40: -7463 | K40: -18506 | L40: 169666 | M40: 140034 | N40: 642024.69 | O40: ='[1]APPENDIX 44'!N$49 -> 28493.74 | P40: =(O40-N40)/ABS(N40) *100 -> -95.561893
C41: Medical | D41: -672213 | E41: -369149 | F41: -525036 | G41: -650108 | H41: -236752 | I41: -1191497 | J41: 1144582 | K41: -1388992 | L41: -897875 | M41: -708115 | N41: 813644.99 | O41: ='[1]APPENDIX 44'!O$49 -> -63595.435 | P41: =(O41-N41)/ABS(N41) *100 -> -107.81612
C42: Miscellaneous | D42: 115441 | E42: 96243 | F42: 373455 | G42: 464570 | H42: 230594 | I42: 658724 | J42: -1090774 | K42: 959588 | L42: 254690 | M42: -143925 | N42: -247198.5 | O42: ='[1]APPENDIX 44'!P$49 -> 353698.27 | P42: =(O42-N42)/ABS(N42) *100 -> 243.08269
C43: Total | D43: 233571 | E43: 408738 | F43: 173158 | G43: 288097 | H43: 383674 | I43: -495788 | J43: -2461576 | K43: 276057 | L43: 439379 | M43: 1196287 | N43: =SUM(N30:N42) -> 1872632.8 | O43: =SUM(O30:O42) -> 2334832.2 | P43: =(O43-N43)/ABS(N43) *100 -> 24.681797
C44: Amounts in '000' KES
C45: *Provisional
C46: a) Performance for general reinsurers
C47: Item | D47: Years | P47: Annual Change 2023/2024 %
D48: 2013 | E48: 2014 | F48: 2015 | G48: 2016 | H48: 2017 | I48: 2018 | J48: 2019 | K48: 2020 | L48: 2021 | M48: =L48+1 -> 2022 | N48: =M48+1 -> 2023 | O48: 2024*
C49: Inward reinsurance premium | D49: 11941515 | E49: 14767189 | F49: 15801462 | G49: 15266497 | H49: 17494109 | I49: 17691725 | J49: 21606301 | K49: 23366089 | L49: 28088864 | M49: 40076864 | N49: 29637764 | O49: ='APPENDIX 22'!Q49 -> 34529188 | P49: =(O49-N49)/ABS(N49) *100 -> 16.504025
C50: Outward reinsurance premium | D50: 473602 | E50: 591965 | F50: 627793 | G50: 769279 | H50: 718956 | I50: 1523352 | J50: 1501140 | K50: 1819079 | L50: 2162357 | M50: 4732429 | N50: 3506247.8 | O50: ='APPENDIX 24'!Q49 -> 4812670.5 | P50: =(O50-N50)/ABS(N50) *100 -> 37.259852
C51: Net earned premium income | D51: 10510255 | E51: 13220316 | F51: 14689144 | G51: 14845284 | H51: 15929002 | I51: 16380642 | J51: 18688661 | K51: 24255147 | L51: 24749953 | M51: 32358707 | N51: 27157882 | O51: ='APPENDIX 40'!Q49 -> 29626594 | P51: =(O51-N51)/ABS(N51) *100 -> 9.0902203
C52: Net incurred claims | D52: 5839213 | E52: 7736192 | F52: 8890225 | G52: 8199875 | H52: 8725365 | I52: 10263532 | J52: 12743839 | K52: 15134936 | L52: 14494495 | M52: 18565424 | N52: 16688280 | O52: ='APPENDIX 42'!Q49 -> 15641525 | P52: =(O52-N52)/ABS(N52) *100 -> -6.2723963
C53: Management expenses | D53: 29506 | E53: 71834 | F53: 54739 | G53: 18330 | H53: 26601 | I53: 25995 | J53: 27293 | K53: 2571251 | L53: 3060743 | M53: 3195699 | N53: 3030223 | O53: ='APPENDIX 4'!D50 -> 2651805.3 | P53: =(O53-N53)/ABS(N53) *100 -> -12.488114
C54: Net commissions | D54: 50521 | E54: 21550 | F54: 21550 | G54: 59375 | H54: 47993 | I54: 29873 | J54: 62932 | K54: 6272905 | L54: 6755333 | M54: 9401296 | N54: 8674539.1 | O54: ='APPENDIX 4'!C50 -> 8998431.2 | P54: =(O54-N54)/ABS(N54) *100 -> 3.7338247
C55: Amounts in '000' KES

Sheet APPENDIX 1
B3: =_xlfn.CONCAT(Contents!E13,": ", UPPER(Contents!F13)) -> APPENDIX 1: SUMMARY OF PROFIT & LOSS ACCOUNTS UNDER GENERAL INSURANCE BUSINESS FOR THE YEAR ENDED 31.12.2024
B4: Company | C4: Insurance Revenue | D4: Insurance Service Expense | E4: Net expenses from reinsurance contracts held | F4: Insurance Service Result | G4: Net Investment Income | H4: Finance expenses from insurance contracts | I4: Finance income from reinsurance contracts | J4: Net Financial Result | K4: Asset management services revenue | L4: Other Income | M4: Other finance costs | N4: Other operating expenses | O4: Share of profit of associates and joint ventures accounted for using the equity method | P4: Profit before income tax | Q4: Income tax expense | R4: Profit for the year
B5: INSURERS
B6: AAR INSURANCE KENYA | C6: {='[1]APPENDIX 1'!$C6:$R6} -> 10696270 | D6: 9983608 | E6: 125557.97 | F6: 587104.41 | G6: 647371.18 | H6: 0 | I6: 0 | J6: 647371.18 | K6: 0 | L6: 5413.7566 | M6: 14759.758 | N6: 689274.94 | O6: 0 | P6: 535854.64 | Q6: 152386.02 | R6: 383468.63
B7: AFRICA MERCHANT ASSURANCE | C7: {='[1]APPENDIX 1'!$C7:$R7} -> 3226047.5 | D7: 2060274.8 | E7: 313195.52 | F7: 852577.18 | G7: 128612.09 | H7: 461615.43 | I7: 77095.661 | J7: -255907.68 | K7: 0 | L7: 0 | M7: 0 | N7: 456086.41 | O7: 0 | P7: 140583.09 | Q7: 38611.511 | R7: 101971.57
B8: APA INSURANCE LIMITED | C8: {='[1]APPENDIX 1'!$C8:$R8} -> 17460597 | D8: 14418179 | E8: 2360727.3 | F8: 681690.01 | G8: 1546494 | H8: 1493994.3 | I8: 582463.29 | J8: 634963.01 | K8: 0 | L8: 0 | M8: 28516.615 | N8: 394977.1 | O8: 39425.079 | P8: 932584.38 | Q8: -116196.02 | R8: 1048780.4
B9: BRITAM GENERAL INSURANCE | C9: {='[1]APPENDIX 1'!$C9:$R9} -> 16975459 | D9: 12306514 | E9: 3527521.7 | F9: 1141423.3 | G9: 1835535.8 | H9: 1436494.4 | I9: 634898.77 | J9: 1033940.2 | K9: 0 | L9: 58068.088 | M9: 40850.592 | N9: 564376 | O9: 0 | P9: 1628205 | Q9: 376427.17 | R9: 1251777.8
B10: CANNON GENERAL INSURANCE (K) LIMITED | C10: {='[1]APPENDIX 1'!$C10:$R10} -> 1807225.3 | D10: 2344306.5 | E10: -27028.26 | F10: -510052.93 | G10: 722005.51 | H10: 84537.928 | I10: 66941.464 | J10: 704409.04 | K10: 0 | L10: 0 | M10: 0 | N10: 226084.85 | O10: 0 | P10: -31728.742 | Q10: 90445.995 | R10: -122174.74
B11: CIC GENERAL INSURANCE COMPANY | C11: {='[1]APPENDIX 1'!$C11:$R11} -> 15967867 | D11: 15151627 | E11: 483965.2 | F11: 332275.47 | G11: 1323008 | H11: 615744.7 | I11: 183574.69 | J11: 890838 | K11: 0 | L11: 350844.45 | M11: 0 | N11: 355159.82 | O11: 0 | P11: 1218798.1 | Q11: 363651.69 | R11: 855146.41
B12: CORPORATE INSURANCE COMPANY | C12: {='[1]APPENDIX 1'!$C12:$R12} -> 218819.36 | D12: 134569.95 | E12: 5376.985 | F12: 78872.428 | G12: 2059.9852 | H12: 115165.35 | I12: 39392.553 | J12: -73712.807 | K12: 0 | L12: 0 | M12: 0 | N12: 113725.59 | O12: 0 | P12: -108565.97 | Q12: 0 | R12: -108565.97
B13: DIRECTLINE ASSURANCE COMPANY | C13: {='[1]APPENDIX 1'!$C13:$R13} -> 4250992.4 | D13: 5127752.7 | E13: 64869.75 | F13: -941630.07 | G13: 270924.45 | H13: 928143.89 | I13: 0 | J13: -657219.44 | K13: 0 | L13: 0 | M13: 0 | N13: 88323.379 | O13: 0 | P13: -1687172.9 | Q13: -488004.96 | R13: -1199167.9
B14: EQUITY GENERAL INSURANCE | C14: {='[1]APPENDIX 1'!$C14:$R14} -> 0 | D14: 0 | E14: 0 | F14: 0 | G14: 0 | H14: 0 | I14: 0 | J14: 0 | K14: 0 | L14: 0 | M14: 0 | N14: 0 | O14: 0 | P14: 0 | Q14: 0 | R14: 0
B15: FIDELITY SHIELD INSURANCE | C15: {='[1]APPENDIX 1'!$C15:$R15} -> 3771950.7 | D15: 2970623 | E15: 808337 | F15: -7009.3174 | G15: 394700.92 | H15: 171658.49 | I15: 20230.312 | J15: 243272.75 | K15: 0 | L15: 68369.225 | M15: 0 | N15: 91491.797 | O15: 0 | P15: 213140.86 | Q15: 32491.857 | R15: 180649
B16: FIRST ASSURANCE COMPANY | C16: {='[1]APPENDIX 1'!$C16:$R16} -> 5598965.4 | D16: 5294626.5 | E16: 257459.14 | F16: 46879.793 | G16: 459530 | H16: -27362.902 | I16: -46602.614 | J16: 440290.29 | K16: 0 | L16: 0 | M16: 22847 | N16: 342330.84 | O16: 0 | P16: 121992.24 | Q16: 50305 | R16: 71687.245
B17: GA INSURANCE COMPANY | C17: {='[1]APPENDIX 1'!$C17:$R17} -> 16260156 | D17: 14445384 | E17: 1301189.8 | F17: 513582.42 | G17: 1737168 | H17: 0 | I17: 0 | J17: 1737168 | K17: 0 | L17: 118866.35 | M17: 0 | N17: 116580.33 | O17: 0 | P17: 2253036.5 | Q17: 466599.02 | R17: 1786437.4
... B41: TRIDENT INSURANCE COMPANY | C41: {='[1]APPENDIX 1'!$C41:$R41} -> 0 | D41: 0 | E41: 0 | F41: 0 | G41: 0 | H41: 0 | I41: 0 | J41: 0 | K41: 0 | L41: 0 | M41: 0 | N41: 0 | O41: 0 | P41: 0 | Q41: 0 | R41: 0
B42: TOTAL | C42: =SUM(C6:C41) -> 2.0142171e+08 | D42: =SUM(D6:D41) -> 1.7207282e+08 | E42: =SUM(E6:E41) -> 21472574 | F42: =SUM(F6:F41) -> 7876317.5 | G42: =SUM(G6:G41) -> 20159476 | H42: =SUM(H6:H41) -> 9638229.6 | I42: =SUM(I6:I41) -> 3044746 | J42: =SUM(J6:J41) -> 13565993 | ... R42: =SUM(R6:R41) -> 10031308
B43: REINSURERS
B44: CONTINENTAL REINSURANCE | C44: {='[1]APPENDIX 1'!$C44:$R44} -> 6496640.2 | D44: 5666061.3 | E44: 203565 | F44: 627013.93 | G44: 298336.92 | H44: 980360.44 | I44: 345664.94 | J44: -336358.59 | K44: 0 | L44: 8063.056 | M44: 839255.76 | N44: 39711.576 | O44: 0 | P44: -580248.94 | Q44: -164703.76 | R44: -415545.18
B45: EAST AFRICA REINSURANCE | C45: {='[1]APPENDIX 1'!$C45:$R45} -> 4310410.9 | D45: 3965772.7 | E45: 173737.09 | F45: 170901.08 | G45: 757836.45 | H45: 179602.36 | I45: 30317.516 | J45: 608551.61 | K45: 0 | L45: 0 | M45: 0 | N45: 253357.52 | O45: 0 | P45: 526095.17 | Q45: 24142.463 | R45: 501952.7
B46: GHANA REINSURANCE COMPANY | C46: {='[1]APPENDIX 1'!$C46:$R46} -> 3269656.1 | D46: 2722278.8 | E46: 55468.276 | F46: 491909.07 | G46: 267600.1 | H46: 271874.24 | I46: 60526.736 | J46: 56252.594 | K46: 0 | L46: 134.492 | M46: 238345.3 | N46: 35989.766 | O46: 0 | P46: 273961.09 | Q46: 87727.3 | R46: 186233.79
B47: KENYA REINSURANCE CORPORATION | C47: {='[1]APPENDIX 1'!$C47:$R47} -> 13125734 | D47: 9628984.6 | E47: 593204.7 | F47: 2903544.6 | G47: 4375802.1 | H47: 705255.71 | I47: -79251.863 | J47: 3591294.5 | K47: 0 | L47: 456526.95 | M47: 1947629.2 | N47: 1040377.3 | O47: 610185.62 | P47: 4573545.2 | Q47: 1823653 | R47: 2749892.2
B48: WAICA REINSURANCE KENYA LIMITED | C48: {='[1]APPENDIX 1'!$C48:$R48} -> 5514193.8 | D48: 4390883.9 | E48: -68840.898 | F48: 1192150.8 | G48: 316435.52 | H48: 354566.63 | I48: 21452.774 | J48: -16678.343 | K48: 0 | L48: 14284.854 | M48: 264167.4 | N48: 411852.48 | O48: 0 | P48: 513737.45 | Q48: 182620.51 | R48: 331116.94
B49: TOTAL | C49: =SUM(C44:C48) -> 32716635 | D49: =SUM(D44:D48) -> 26373981 | E49: =SUM(E44:E48) -> 957134.17 | F49: =SUM(F44:F48) -> 5385519.5 | G49: =SUM(G44:G48) -> 6016011.1 | H49: =SUM(H44:H48) -> 2491659.4 | I49: =SUM(I44:I48) -> 378710.1 | J49: =SUM(J44:J48) -> 3903061.8 | ... R49: =SUM(R44:R48) -> 3353650.4
B50: GRAND TOTAL | C50: =SUM(C49+C42) -> 2.3413835e+08 | D50: =SUM(D49+D42) -> 1.984468e+08 | E50: =SUM(E49+E42) -> 22429708 | F50: =SUM(F49+F42) -> 13261837 | G50: =SUM(G49+G42) -> 26175487 | H50: =SUM(H49+H42) -> 12129889 | I50: =SUM(I49+I42) -> 3423456 | J50: =SUM(J49+J42) -> 17469054 | ... R50: =SUM(R49+R42) -> 13384959
B51: Amounts in Thousand Shillings

Sheet APPENDIX 2
B3: =_xlfn.CONCAT(Contents!E14,": ",UPPER(Contents!F14)) -> APPENDIX 2: SUMMARY OF PROFIT & LOSS ACCOUNTS LONG-TERM INSURANCE BUSINESS FOR THE YEAR ENDED 31.12.2024
B4: Company | C4: Insurance Revenue | D4: Insurance Service Expense | E4: Net expenses from reinsurance contracts held | F4: Insurance Service Result | G4: Net Investment Income | H4: Finance expenses from insurance contracts | I4: Finance income from reinsurance contracts | J4: Net Financial Result | K4: Asset management services revenue | L4: Other Income | M4: Other finance costs | N4: Other operating expenses | O4: Share of profit of associates and joint ventures accounted for using the equity method | P4: Profit before income tax | Q4: Income tax expense | R4: Profit for the year
B5: INSURERS
B6: ABSA LIFE ASSURANCE | C6: {='[1]APPENDIX 2'!$C6:$R6} -> 7599467.3 | D6: 6475342.4 | E6: 317024.9 | F6: 807099.99 | G6: 1730323.1 | H6: 2237019.7 | I6: 55529.75 | J6: -451166.8 | K6: 0 | L6: 14347.04 | M6: 0 | N6: 213005.63 | O6: 0 | P6: 157274.6 | Q6: 5880.329 | R6: 151394.27
B7: APA LIFE ASSURANCE COMPANY | C7: {='[1]APPENDIX 2'!$C7:$R7} -> 2909083.8 | D7: 2439244.2 | E7: 65906.347 | F7: 403933.29 | G7: 1899444.7 | H7: 1939087.9 | I7: 13051.334 | J7: -26591.832 | K7: 0 | L7: 0 | M7: 33035.342 | N7: 84983.106 | O7: 0 | P7: 259323.01 | Q7: 58752.379 | R7: 200570.63
B8: BRITAM LIFE ASSURANCE | C8: {='[1]APPENDIX 2'!$C8:$R8} -> 13682024 | D8: 8910682.2 | E8: 1024789.7 | F8: 3746551.5 | G8: 27906944 | H8: 25312837 | I8: 149953.74 | J8: 2744060.5 | K8: 0 | L8: -26087.151 | M8: 37173.904 | N8: 1053955.9 | O8: 241950.45 | P8: 5615345.5 | Q8: 1684603.7 | R8: 3930741.9
B9: CANNON LIFE ASSURANCE (K) LIMITED | C9: {='[1]APPENDIX 2'!$C9:$R9} -> 355750.99 | D9: 476521.84 | E9: 74567.21 | F9: -195338.06 | G9: 102280.74 | H9: -44757.899 | I9: 1691.2806 | J9: 148729.92 | K9: 0 | L9: 16320 | M9: 0 | N9: 11272.251 | O9: 0 | P9: -41560.394 | Q9: 10777.369 | R9: -52337.764
B10: CAPEX LIFE ASSURANCE COMPANY | C10: {='[1]APPENDIX 2'!$C10:$R10} -> 1634045.1 | D10: 1277652 | E10: 243771.56 | F10: 112621.47 | G10: 41398.236 | H10: 17403.521 | I10: 9803.5779 | J10: 33798.293 | K10: 0 | L10: 0 | M10: 0 | N10: 20146.871 | O10: 0 | P10: 126272.89 | Q10: 0 | R10: 126272.89
B11: CIC LIFE ASSURANCE COMPANY | C11: {='[1]APPENDIX 2'!$C11:$R11} -> 6847228.7 | D11: 5140777.8 | E11: 553238.35 | F11: 1153212.5 | G11: 1978918 | H11: 4510951.3 | I11: 91380.734 | J11: -2440652.7 | K11: 0 | L11: 2650197.9 | M11: 0 | N11: 201507.98 | O11: 0 | P11: 1161249.9 | Q11: 348374.96 | R11: 812874.9
B12: CORPORATE INSURANCE COMPANY | C12: {='[1]APPENDIX 2'!$C12:$R12} -> 61268.936 | D12: 64915.463 | E12: 1091.6464 | F12: -4738.1734 | G12: 11172.979 | H12: 36967.91 | I12: 0 | J12: -25794.931 | K12: 0 | L12: 0 | M12: 0 | N12: 6254.073 | O12: 0 | P12: -36787.177 | Q12: 0 | R12: -36787.177
B13: EQUITY LIFE ASSURANCE | C13: {='[1]APPENDIX 2'!$C13:$R13} -> 1428825.5 | D13: 921101.11 | E13: 111447.7 | F13: 396276.73 | G13: 3018261.1 | H13: 1965893.5 | I13: 27880.719 | J13: 1080248.3 | K13: 0 | L13: 170193.35 | M13: 0 | N13: 254546 | O13: 0 | P13: 1392172.4 | Q13: 324581.36 | R13: 1067591
B14: GA LIFE ASSURANCE COMPANY | C14: {='[1]APPENDIX 2'!$C14:$R14} -> 95946.173 | D14: 63627.093 | E14: 29474.986 | F14: 2844.094 | G14: 5475893.4 | H14: 0 | I14: 0 | J14: 5475893.4 | K14: 0 | L14: 1091592.4 | M14: 138.053 | N14: 5109253.5 | O14: 0 | P14: 1460938.3 | Q14: 415935.89 | R14: 1045002.4
B15: GEMINIA LIFE INSURANCE COMPANY | C15: {='[1]APPENDIX 2'!$C15:$R15} -> 1096880.7 | D15: 936739.1 | E15: 45287.074 | F15: 114854.49 | G15: 277316.4 | H15: 70281.707 | I15: 0 | J15: 207034.69 | K15: 0 | L15: 0 | M15: 1427 | N15: 248994.09 | O15: 0 | P15: 71468.081 | Q15: 0 | R15: 71468.081
B16: ICEA LION LIFE ASSURANCE | C16: {='[1]APPENDIX 2'!$C16:$R16} -> 6980321.3 | D16: 4036521.2 | E16: 166682.77 | F16: 2777117.3 | G16: 26569662 | H16: 24650641 | I16: 0 | J16: 1919021 | K16: 0 | L16: 85278 | M16: 0 | N16: 953957 | O16: 0 | P16: 3827459.3 | Q16: 1001857 | R16: 2825602.3
B17: JUBILEE LIFE INSURANCE | C17: {='[1]APPENDIX 2'!$C17:$R17} -> 4833085 | D17: 4495827.5 | E17: 153272.26 | F17: 183985.2 | G17: 17069315 | H17: 13744158 | I17: 0 | J17: 3325157.1 | K17: 0 | L17: 0 | M17: 0 | N17: 680385.54 | O17: 73678 | P17: 2902434.7 | Q17: 822642.8 | R17: 2079791.9
... B30: THE MONARCH INSURANCE | C30: {='[1]APPENDIX 2'!$C30:$R30} -> 42454.027 | D30: 198249.67 | E30: -93898.978 | F30: -61896.667 | G30: 27272.32 | H30: 4584.831 | I30: 0 | J30: 22687.489 | K30: 0 | L30: 34349.652 | M30: 0 | N30: 0 | O30: 0 | P30: -4859.526 | Q30: 1658.195 | R30: -6517.721
B31: TOTAL | C31: =SUM(C6:C30) -> 70092155 | D31: =SUM(D6:D30) -> 56214894 | E31: =SUM(E6:E30) -> 3709662.9 | F31: =SUM(F6:F30) -> 10167598 | G31: =SUM(G6:G30) -> 1.1258956e+08 | H31: =SUM(H6:H30) -> 77824391 | I31: =SUM(I6:I30) -> 333038.45 | J31: =SUM(J6:J30) -> 15881465 | ... R31: =SUM(R6:R30) -> 15082705
B32: REINSURERS
B33: CONTINENTAL REINSURANCE | C33: {='[1]APPENDIX 2'!$C33:$R33} -> 17385.979 | D33: 30548.035 | E33: -2775.18 | F33: -10386.876 | G33: 51161.547 | H33: 6804.561 | I33: 60.403 | J33: 44417.389 | K33: 0 | L33: 0 | M33: 43339.828 | N33: 545.266 | O33: 0 | P33: -9854.581 | Q33: -45526.339 | R33: -55380.92
B34: EAST AFRICA REINSURANCE | C34: {='[1]APPENDIX 2'!$C34:$R34} -> 1220774.1 | D34: 985777.14 | E34: 124612.65 | F34: 110384.26 | G34: 283518.22 | H34: 26506.135 | I34: 6919.391 | J34: 263931.48 | K34: 0 | L34: 0 | M34: 0 | N34: 51111.801 | O34: 0 | P34: 323203.94 | Q34: -100303.91 | R34: 222900.03
B35: KENYA REINSURANCE CORPORATION | C35: {='[1]APPENDIX 2'!$C35:$R35} -> 2940422.8 | D35: 2575405.1 | E35: 113507.12 | F35: 251510.6 | G35: 901723.31 | H35: -82325.851 | I35: 472.115 | J35: 984521.27 | K35: 0 | L35: 0 | M35: 2.526 | N35: 66377.709 | O35: 0 | P35: 1169651.6 | Q35: 618302 | R35: 1787953.6
B36: TOTAL | C36: =SUM(C33:C35) -> 4178582.8 | D36: =SUM(D33:D35) -> 3591730.2 | E36: =SUM(E33:E35) -> 235344.59 | F36: =SUM(F33:F35) -> 351507.98 | G36: =SUM(G33:G35) -> 1236403.1 | H36: =SUM(H33:H35) -> -49015.155 | I36: =SUM(I33:I35) -> 7451.909 | J36: =SUM(J33:J35) -> 1292870.1 | ... R36: =SUM(R33:R35) -> 1955472.7
B37: GRAND TOTAL | C37: =C36+C31 -> 74270738 | D37: =D36+D31 -> 59806624 | E37: =E36+E31 -> 3945007.5 | F37: =F36+F31 -> 10519106 | G37: =G36+G31 -> 1.1382597e+08 | H37: =H36+H31 -> 77775376 | I37: =I36+I31 -> 340490.36 | J37: =J36+J31 -> 17174335 | ... R37: =R36+R31 -> 17038178
B38: Amounts in Thousand Shillings

Sheet APPENDIX 3
B3: =_xlfn.CONCAT(Contents!E15,": ",UPPER(Contents!F15)) -> APPENDIX 3: SUMMARY OF PROFIT & LOSS ACCOUNTS MICROINSURANCE BUSINESS FOR THE YEAR ENDED 31.12.2024
B4: Company | C4: Insurance Revenue | D4: Insurance Service Expense | E4: Net expenses from reinsurance contracts held | F4: Insurance Service Result | G4: Net Investment Income | H4: Finance expenses from insurance contracts | I4: Finance income from reinsurance contracts | J4: Net Financial Result | K4: Asset management services revenue | L4: Other Income | M4: Other finance costs | N4: Other operating expenses | O4: Share of profit of associates and joint ventures accounted for using the equity method | P4: Profit before income tax | Q4: Income tax expense | R4: Profit for the year
B5: INSURERS
B6: STAR DISCOVER MICRO INSURANCE | C6: {='[1]APPENDIX 3'!$C6:$R6} -> 102415.22 | D6: 80380.466 | E6: 53285.465 | F6: -31250.714 | G6: 0 | H6: 1045.1028 | I6: 895.91834 | J6: -149.18447 | K6: 0 | L6: 2423.583 | M6: 0 | N6: 252.84097 | O6: 0 | P6: -29229.157 | Q6: -8534.6161 | R6: -20694.541
B7: TURACO MICROINSURANCE | C7: {='[1]APPENDIX 3'!$C7:$R7} -> 112763.59 | D7: 94865.577 | E7: 13855.854 | F7: 4042.1546 | G7: 6535.155 | H7: 0 | I7: 0 | J7: 6535.155 | K7: 0 | L7: 0 | M7: 447.312 | N7: 5323.657 | O7: 0 | P7: 4806.3406 | Q7: 464.51431 | R7: 4341.8263
B8: TOTAL | C8: =SUM(C6:C7) -> 215178.8 | D8: =SUM(D6:D7) -> 175246.04 | E8: =SUM(E6:E7) -> 67141.319 | F8: =SUM(F6:F7) -> -27208.56 | G8: =SUM(G6:G7) -> 6535.155 | H8: =SUM(H6:H7) -> 1045.1028 | I8: =SUM(I6:I7) -> 895.91834 | J8: =SUM(J6:J7) -> 6385.9705 | ... R8: =SUM(R6:R7) -> -16352.714
B9: Amounts in Thousand Shillings

Sheet APPENDIX 4
B3: =_xlfn.CONCAT(Contents!E16,": ",UPPER(Contents!F16)) -> APPENDIX 4: SUMMARY OF NET COMMISSIONS AND MANAGEMENT EXPENSES FOR THE YEAR ENDED 31.12.2024
B5: GENERAL INSURANCE BUSINESS | F5: LONG TERM INSURANCE BUSINESS
B6: Company | C6: Commissions | D6: Management Expenses | F6: Company | G6: Commissions | H6: Management Expenses
B7: AAR INSURANCE KENYA | C7: {='[1]APPENDIX 4'!$C7:$D7} -> 661101.01 | D7: 1473817.7 | F7: ABSA LIFE ASSURANCE | G7: {='[1]APPENDIX 4'!$G7:$H7} -> 897210.76 | H7: 1039424.3
B8: AFRICA MERCHANT ASSURANCE | C8: {='[1]APPENDIX 4'!$C8:$D8} -> 320263.18 | D8: 1040963.2 | F8: APA LIFE ASSURANCE COMPANY | G8: {='[1]APPENDIX 4'!$G8:$H8} -> 541994.82 | H8: 477253.47
B9: APA INSURANCE LIMITED | C9: {='[1]APPENDIX 4'!$C9:$D9} -> 797500.83 | D9: 2492443.4 | F9: BRITAM LIFE ASSURANCE | G9: {='[1]APPENDIX 4'!$G9:$H9} -> 1536509.7 | H9: 4544020.8
B10: BRITAM GENERAL INSURANCE | C10: {='[1]APPENDIX 4'!$C10:$D10} -> 384227.53 | D10: 2795524.5 | F10: CANNON LIFE ASSURANCE (K) LIMITED | G10: {='[1]APPENDIX 4'!$G10:$H10} -> 4490.4837 | H10: 208425.3
B11: CANNON GENERAL INSURANCE (K) LIMITED | C11: {='[1]APPENDIX 4'!$C11:$D11} -> 135453.67 | D11: 567087.34 | F11: CAPEX LIFE ASSURANCE COMPANY | G11: {='[1]APPENDIX 4'!$G11:$H11} -> 100616.91 | H11: 402937.43
B12: CIC GENERAL INSURANCE COMPANY | C12: {='[1]APPENDIX 4'!$C12:$D12} -> 1307351.8 | D12: 3086692.8 | F12: CIC LIFE ASSURANCE COMPANY | G12: {='[1]APPENDIX 4'!$G12:$H12} -> 716042.15 | H12: 1872117.1
B13: CORPORATE INSURANCE COMPANY | C13: {='[1]APPENDIX 4'!$C13:$D13} -> -1326.5509 | D13: 191145.52 | F13: CORPORATE INSURANCE COMPANY | G13: {='[1]APPENDIX 4'!$G13:$H13} -> 0 | H13: 12856.517
B14: DIRECTLINE ASSURANCE COMPANY | C14: {='[1]APPENDIX 4'!$C14:$D14} -> 480946.96 | D14: 911067.82 | F14: EQUITY LIFE ASSURANCE | G14: {='[1]APPENDIX 4'!$G14:$H14} -> -11901.403 | H14: 558982.43
B15: EQUITY GENERAL INSURANCE | C15: {='[1]APPENDIX 4'!$C15:$D15} -> 0 | D15: 0 | F15: GA LIFE ASSURANCE COMPANY | G15: {='[1]APPENDIX 4'!$G15:$H15} -> 42997.084 | H15: 137387
B16: FIDELITY SHIELD INSURANCE | C16: {='[1]APPENDIX 4'!$C16:$D16} -> 212045.2 | D16: 474144.97 | F16: GEMINIA LIFE INSURANCE COMPANY | G16: {='[1]APPENDIX 4'!$G16:$H16} -> 182632.45 | H16: 138469.05
B17: FIRST ASSURANCE COMPANY | C17: {='[1]APPENDIX 4'!$C17:$D17} -> 174781.52 | D17: 1257826.5 | F17: ICEA LION LIFE ASSURANCE | G17: {='[1]APPENDIX 4'!$G17:$H17} -> 1568935.5 | H17: 2317307.4
B18: GA INSURANCE COMPANY | C18: {='[1]APPENDIX 4'!$C18:$D18} -> -170541.1 | D18: 1559423 | F18: JUBILEE LIFE INSURANCE | G18: {='[1]APPENDIX 4'!$G18:$H18} -> 1189191.6 | H18: 1469750.5
... B31: OCCIDENTAL INSURANCE COMPANY | C31: {='[1]APPENDIX 4'!$C31:$D31} -> -347214.62 | D31: 584137.62 | F31: THE MONARCH INSURANCE | G31: {='[1]APPENDIX 4'!$G31:$H31} -> -114.048 | H31: 23868.073
B32: OLD MUTUAL GENERAL INSURANCE | C32: {='[1]APPENDIX 4'!$C32:$D32} -> 1419041.7 | D32: 3261554.1 | F32: TOTAL | G32: =SUM(G7:G31) -> 9157713.9 | H32: =SUM(H7:H31) -> 22349821
B33: PACIS INSURANCE COMPANY | C33: {='[1]APPENDIX 4'!$C33:$D33} -> 252752.71 | D33: 729926.48 | F33: REINSURERS
B34: PIONEER INSURANCE COMPANY | C34: {='[1]APPENDIX 4'!$C34:$D34} -> 160751.92 | D34: 457527.06 | F34: CONTINENTAL REINSURANCE | G34: {='[1]APPENDIX 4'!$G34:$H34} -> 5479.831 | H34: 8610.053
B35: SANLAM INSURANCE COMPANY | C35: {='[1]APPENDIX 4'!$C35:$D35} -> 131623.41 | D35: 744363.01 | F35: EAST AFRICA REINSURANCE | G35: {='[1]APPENDIX 4'!$G35:$H35} -> 247715.05 | H35: 198985.03
B36: STAR DISCOVER INSURANCE | C36: {='[1]APPENDIX 4'!$C36:$D36} -> 142371.65 | D36: 284210.3 | F36: KENYA REINSURANCE CORPORATION | G36: {='[1]APPENDIX 4'!$G36:$H36} -> 897686.25 | H36: 66377.71
B37: TAKAFUL INSURANCE OF AFRICA | C37: {='[1]APPENDIX 4'!$C37:$D37} -> 73193.048 | D37: 420863.96 | F37: TOTAL | G37: =SUM(G34:G36) -> 1150881.1 | H37: =SUM(H34:H36) -> 273972.79
B38: TAUSI ASSURANCE COMPANY | C38: {='[1]APPENDIX 4'!$C38:$D38} -> 132890.29 | D38: 590081 | F38: GRAND TOTAL | G38: =G37+G32 -> 10308595 | H38: =H37+H32 -> 22623794
B39: THE HERITAGE INSURANCE COMPANY | C39: {='[1]APPENDIX 4'!$C39:$D39} -> 205554.52 | D39: 1979483.1 | F39: Amounts in Thousand shillings
B40: THE KENYAN ALLIANCE INSURANCE | C40: {='[1]APPENDIX 4'!$C40:$D40} -> 59150.207 | D40: 875603.46
B41: THE MONARCH INSURANCE | C41: {='[1]APPENDIX 4'!$C41:$D41} -> 107318.06 | D41: 466187.25
B42: TRIDENT INSURANCE COMPANY | C42: {='[1]APPENDIX 4'!$C42:$D42} -> 0 | D42: 0 | F42: MICROINSURANCE BUSINESS
B43: TOTAL | C43: =SUM(C7:C42) -> 9256384 | D43: =SUM(D7:D42) -> 37501295 | F43: STAR DISCOVER MICRO INSURANCE | G43: {='[1]APPENDIX 4'!$G43:$H43} -> -1740.9745 | H43: 61517.61
B44: REINSURERS | F44: TURACO MICROINSURANCE | G44: {='[1]APPENDIX 4'!$G44:$H44} -> -14214.314 | H44: 58645.663
B45: CONTINENTAL REINSURANCE | C45: {='[1]APPENDIX 4'!$C45:$D45} -> 1445374.9 | D45: 628065.56 | F45: TOTAL | G45: =SUM(G43:G44) -> -15955.289 | H45: =SUM(H43:H44) -> 120163.27
B46: EAST AFRICA REINSURANCE | C46: {='[1]APPENDIX 4'!$C46:$D46} -> 977673.2 | D46: 394586.48 | F46: Amounts in Thousand shillings
B47: GHANA REINSURANCE COMPANY | C47: {='[1]APPENDIX 4'!$C47:$D47} -> 1068087.1 | D47: 176923.45
B48: KENYA REINSURANCE CORPORATION | C48: {='[1]APPENDIX 4'!$C48:$D48} -> 4151588.7 | D48: 1040377.3
B49: WAICA REINSURANCE KENYA LIMITED | C49: {='[1]APPENDIX 4'!$C49:$D49} -> 1355707.3 | D49: 411852.48
B50: TOTAL | C50: =SUM(C45:C49) -> 8998431.2 | D50: =SUM(D45:D49) -> 2651805.3
B51: GRAND TOTAL | C51: =C50+C43 -> 18254815 | D51: =D50+D43 -> 40153101
B52: Amounts in Thousand shillings

Sheet APPENDIX 5 I
B3: =_xlfn.CONCAT(INDEX(_xlfn.TEXTSPLIT(Contents!E17," I"),1),": ",UPPER(Contents!F17)) -> APPENDIX 5: SUMMARY OF LONG TERM INSURANCE BUSINESS BALANCE SHEETS AS AT 31.12.2024
B4: Company | C4: ABSA LIFE ASSURANCE | D4: APA LIFE ASSURANCE COMPANY | E4: BRITAM LIFE ASSURANCE | F4: CANNON LIFE ASSURANCE (K) LIMITED | G4: CAPEX LIFE ASSURANCE COMPANY | H4: CIC LIFE ASSURANCE COMPANY | I4: CONTINENTAL REINSURANCE | J4: CORPORATE INSURANCE COMPANY | K4: EAST AFRICA REINSURANCE | L4: EQUITY LIFE ASSURANCE
B5: Share Capital | C5: {='[1]APPENDIX 5 I'!$C5:$L5} -> 699000 | D5: 1100000 | E5: 1200000 | F5: 416725.77 | G5: 400000 | H5: 800000 | I5: 500000 | J5: 200000 | K5: 500000 | L5: 420000
B6: Share Premium_x000D_ | C6: {='[1]APPENDIX 5 I'!$C6:$L6} -> 0 | D6: 0 | E6: 0 | F6: 491067.65 | G6: 0 | H6: 0 | I6: 0 | J6: 0 | K6: 0 | L6: 180000
B7: Revaluation Reserves | C7: {='[1]APPENDIX 5 I'!$C7:$L7} -> 0 | D7: 0 | E7: 0 | F7: 2500 | G7: 2072.909 | H7: 0 | I7: 0 | J7: -8100 | K7: 0 | L7: 0
B8: Statutory Reserves | C8: {='[1]APPENDIX 5 I'!$C8:$L8} -> -40382.649 | D8: -113765.05 | E8: 14900507 | F8: 0 | G8: 0 | H8: 1566091.1 | I8: 21056.733 | J8: -334199.16 | K8: 0 | L8: 0
B9: Other Equity | C9: {='[1]APPENDIX 5 I'!$C9:$L9} -> 0 | D9: 0 | E9: 0 | F9: 399360.94 | G9: 0 | H9: -24517.332 | I9: -15.88 | J9: 0 | K9: 0 | L9: 0
B10: Retained Earnings | C10: {='[1]APPENDIX 5 I'!$C10:$L10} -> 818602.86 | D10: 244790.81 | E10: 75000 | F10: -1221978.8 | G10: 227574.35 | H10: 812874.9 | I10: 56739.326 | J10: -36787.178 | K10: 1056274.1 | L10: 3762566.8
B11: Other Reserves | C11: {='[1]APPENDIX 5 I'!$C11:$L11} -> 0 | D11: 0 | E11: 0 | F11: 518154.63 | G11: 1120.164 | H11: 0 | I11: 0 | J11: 0 | K11: 0 | L11: 0
B12: Total Equity_x000D_ | C12: 1477220.2 | D12: 1231025.8 | E12: 16175507 | F12: 605830.19 | G12: 630767.43 | H12: 3154448.7 | I12: 577780.18 | J12: -179086.33 | K12: 1556274.1 | L12: 4362566.8
B13: Investment Contract Liabilites | C13: {='[1]APPENDIX 5 I'!$C13:$L13} -> 0 | D13: 293063.44 | E13: 0 | F13: 0 | G13: 13011.007 | H13: 98924.319 | I13: 0 | J13: 0 | K13: 0 | L13: 0
B14: Insurance Contract Liabilites | C14: {='[1]APPENDIX 5 I'!$C14:$L14} -> 12547614 | D14: 15164514 | E14: 1.4485248e+08 | F14: 751940.44 | G14: 1502517.5 | H14: 27877089 | I14: 53212.265 | J14: 795174.07 | K14: 893928.65 | L14: 19894172
B15: Reinsurance Contract Liabilites | C15: {='[1]APPENDIX 5 I'!$C15:$L15} -> 0 | D15: 8063.7861 | E15: 9761.9287 | F15: 0 | G15: 74519.79 | H15: 0 | I15: 7462.789 | J15: 0 | K15: 114117.81 | L15: 0
B16: Long-Term Liabilites | C16: {='[1]APPENDIX 5 I'!$C16:$L16} -> 223609.27 | D16: 104297.82 | E16: 6385931.4 | F16: 0 | G16: 0 | H16: 1014886 | I16: 70315.084 | J16: 0 | K16: 452688.82 | L16: 795587.96
B17: Short-Term Liabilites | C17: {='[1]APPENDIX 5 I'!$C17:$L17} -> 130173.07 | D17: 0 | E17: 960993.27 | F17: 99625.866 | G17: 52080.633 | H17: 0 | I17: 25753.554 | J17: 128456.43 | K17: 0 | L17: 72666.679
B18: Other Liabilites | C18: {='[1]APPENDIX 5 I'!$C18:$L18} -> 198194.85 | D18: 172530.98 | E18: 1056267.9 | F18: 236770.49 | G18: 26155.142 | H18: 710479.02 | I18: 47784.763 | J18: 22467.175 | K18: 0 | L18: 671018.16
B19: Total Equity And Liabilities | C19: 14576812 | D19: 16973496 | E19: 1.6944095e+08 | F19: 1694167 | G19: 2299051.5 | H19: 32855827 | I19: 782308.63 | J19: 767011.34 | K19: 3017009.4 | L19: 25796011
B20: Intangible Assets | C20: {='[1]APPENDIX 5 I'!$C20:$L20} -> 46032.978 | D20: 13448.22 | E20: 289887.76 | F20: 1210.9356 | G20: 8158.282 | H20: 56184.183 | I20: 0 | J20: 633.33062 | K20: 0.1 | L20: 215190.17
B21: Land and Buildings | C21: {='[1]APPENDIX 5 I'!$C21:$L21} -> 0 | D21: 0 | E21: 330482 | F21: 92500 | G21: 0 | H21: 0 | I21: 0 | J21: 0 | K21: 0 | L21: 0
B22: Investment Property | C22: {='[1]APPENDIX 5 I'!$C22:$L22} -> 0 | D22: 155000 | E22: 16341555 | F22: 944050 | G22: 540000 | H22: 2181875 | I22: 0 | J22: 713255.4 | K22: 0 | L22: 0
B23: Fixed Assets | C23: {='[1]APPENDIX 5 I'!$C23:$L23} -> 22268.06 | D23: 9397.0962 | E23: 98163.747 | F23: 1759.1695 | G23: 12302.169 | H23: 56442.473 | I23: 0 | J23: 619.0801 | K23: 0 | L23: 6295.6521
B24: Government Securites | C24: {='[1]APPENDIX 5 I'!$C24:$L24} -> 12085697 | D24: 14610403 | E24: 1.2536561e+08 | F24: 467855.4 | G24: 260434.65 | H24: 20568810 | I24: 649517.13 | J24: 26758.399 | K24: 1289032.3 | L24: 19729628
B25: Other Securites | C25: {='[1]APPENDIX 5 I'!$C25:$L25} -> 0 | D25: 82660.269 | E25: 11177964 | F25: 0 | G25: 0 | H25: 334445.49 | I25: 0 | J25: 0 | K25: 0 | L25: 0
B26: Investment in Related Parties | C26: {='[1]APPENDIX 5 I'!$C26:$L26} -> 0 | D26: 0 | E26: 7610993.4 | F26: 0 | G26: 0 | H26: 0 | I26: 0 | J26: 0 | K26: 0 | L26: 0
B27: Corporate Bonds | C27: {='[1]APPENDIX 5 I'!$C27:$L27} -> 0 | D27: 112326.88 | E27: 4245.8902 | F27: 0 | G27: 0 | H27: 64753.362 | I27: 0 | J27: 0 | K27: 0 | L27: 51524.046
B28: Commercial Papers | C28: {='[1]APPENDIX 5 I'!$C28:$L28} -> 0 | D28: 75198.08 | E28: 0 | F28: 0 | G28: 0 | H28: 0 | I28: 0 | J28: 0 | K28: 0 | L28: 0
B29: Debentures | C29: {='[1]APPENDIX 5 I'!$C29:$L29} -> 0 | D29: 0 | E29: 0 | F29: 0 | G29: 0 | H29: 0 | I29: 0 | J29: 0 | K29: 0 | L29: 0
B30: Ordinary Shares Quoted | C30: {='[1]APPENDIX 5 I'!$C30:$L30} -> 0 | D30: 274550.75 | E30: 2023547.7 | F30: 0 | G30: 1.56 | H30: 631691.08 | I30: 0 | J30: 0 | K30: 9151.8786 | L30: 1962590.9
B31: Ordinary Shares Unquoted | C31: {='[1]APPENDIX 5 I'!$C31:$L31} -> 0 | D31: 10119.475 | E31: 847305.79 | F31: 211.64 | G31: 0 | H31: 0 | I31: 0 | J31: 1770.231 | K31: 0 | L31: 0
... B41: Other Assets | C41: {='[1]APPENDIX 5 I'!$C41:$L41} -> 835469.35 | D41: 14939.335 | E41: 375805.29 | F41: 59972.837 | G41: 309083.28 | H41: 129686.51 | I41: 0 | J41: 0 | K41: 0 | L41: 654986.19
B42: Total Assets | C42: 14576812 | D42: 16973496 | E42: 1.6944095e+08 | F42: 1694167 | G42: 2299051.5 | H42: 32855827 | I42: 782308.63 | J42: 767011.34 | K42: 3017009.4 | L42: 25796011
B43: Amounts in thousand Shillings | K43: Continued next page

Sheet APPENDIX 5 II
B2: Continued from previous page
B3: =_xlfn.CONCAT(INDEX(_xlfn.TEXTSPLIT(Contents!E18," II"),1),": ",UPPER(Contents!F18)) -> APPENDIX 5: SUMMARY OF LONG TERM INSURANCE BUSINESS BALANCE SHEETS AS AT 31.12.2024
B4: Company | C4: GA LIFE ASSURANCE COMPANY | D4: GEMINIA LIFE INSURANCE COMPANY | E4: ICEA LION LIFE ASSURANCE | F4: JUBILEE LIFE INSURANCE | G4: KENINDIA ASSURANCE COMPANY | H4: KENYA ORIENT LIFE ASSURANCE | I4: KENYA REINSURANCE CORPORATION | J4: KUSCCO MUTUAL ASSURANCE LIMITED | K4: LIBERTY LIFE ASSURANCE COMPANY | L4: MADISON INSURANCE COMPANY
B5: Share Capital | C5: {='[1]APPENDIX 5 II'!$C5:$L5} -> 400000 | D5: 458093.68 | E5: 1125000 | F5: 500000 | G5: 400000 | H5: 313000 | I5: 500000 | J5: 400100 | K5: 742340 | L5: 450000
B6: Share Premium_x000D_ | C6: {='[1]APPENDIX 5 II'!$C6:$L6} -> 0 | D6: 0 | E6: 1125000 | F6: 0 | G6: 0 | H6: 0 | I6: 0 | J6: 0 | K6: 0 | L6: 0
B7: Revaluation Reserves | C7: {='[1]APPENDIX 5 II'!$C7:$L7} -> 0 | D7: 0 | E7: 0 | F7: 0 | G7: -536.59 | H7: 0 | I7: 0 | J7: 0 | K7: 384946.36 | L7: 19341.205
B8: Statutory Reserves | C8: {='[1]APPENDIX 5 II'!$C8:$L8} -> 1802623.5 | D8: 316903 | E8: 15133712 | F8: 3067746.2 | G8: 1831973.6 | H8: 131877.46 | I8: 0 | J8: 0 | K8: 1965372.3 | L8: -2834562.3
B9: Other Equity | C9: {='[1]APPENDIX 5 II'!$C9:$L9} -> 0 | D9: 0 | E9: 1050000 | F9: 0 | G9: 0 | H9: 0 | I9: 0 | J9: 0 | K9: 0 | L9: 1550000
B10: Retained Earnings | C10: {='[1]APPENDIX 5 II'!$C10:$L10} -> 252089.01 | D10: 122801.14 | E10: 3766632.3 | F10: 6116849.5 | G10: 2176266.8 | H10: 112660.9 | I10: 10357519 | J10: -13304.768 | K10: -304169.9 | L10: 62000
B11: Other Reserves | C11: {='[1]APPENDIX 5 II'!$C11:$L11} -> 0 | D11: 0 | E11: 0 | F11: 0 | G11: 156085.9 | H11: 0 | I11: 0 | J11: 0 | K11: 0 | L11: 0
B12: Total Equity_x000D_ | C12: 2454712.5 | D12: 897797.82 | E12: 22200344 | F12: 9684595.7 | G12: 4563789.8 | H12: 557538.37 | I12: 10857519 | J12: 386795.23 | K12: 2788488.7 | L12: -753221.1
B13: Investment Contract Liabilites | C13: {='[1]APPENDIX 5 II'!$C13:$L13} -> 40179526 | D13: 834143.48 | E13: 0 | F13: 0 | G13: 0 | H13: 1748186.7 | I13: 0 | J13: 0 | K13: 11020491 | L13: 0
B14: Insurance Contract Liabilites | C14: {='[1]APPENDIX 5 II'!$C14:$L14} -> 23882.403 | D14: 1678057.4 | E14: 1.5376187e+08 | F14: 1.358502e+08 | G14: 86799114 | H14: 2557958.4 | I14: 2889454.9 | J14: 741095.06 | K14: 12952000 | L14: 19282912
B15: Reinsurance Contract Liabilites | C15: {='[1]APPENDIX 5 II'!$C15:$L15} -> 0 | D15: 0 | E15: 0 | F15: 0 | G15: 31747.755 | H15: 0 | I15: 0 | J15: 0 | K15: 0 | L15: 193322
B16: Long-Term Liabilites | C16: {='[1]APPENDIX 5 II'!$C16:$L16} -> 0 | D16: 58439.677 | E16: 3989542 | F16: 1378255.8 | G16: 785025.97 | H16: 101328.53 | I16: 0 | J16: 94639.014 | K16: 1007274.4 | L16: 0
B17: Short-Term Liabilites | C17: {='[1]APPENDIX 5 II'!$C17:$L17} -> 65491.323 | D17: 72102.83 | E17: 0 | F17: 1894389.4 | G17: 405946.96 | H17: 0 | I17: 0 | J17: 24939.42 | K17: 603572.8 | L17: 173015.38
B18: Other Liabilites | C18: {='[1]APPENDIX 5 II'!$C18:$L18} -> 3669101 | D18: 21383 | E18: 2132999.9 | F18: 261621.5 | G18: 61387.735 | H18: 43458.493 | I18: 0 | J18: 98252.605 | K18: 307071.67 | L18: 334605.58
B19: Total Equity And Liabilities | C19: 46392713 | D19: 3561924.2 | E19: 1.8208476e+08 | F19: 1.4906906e+08 | G19: 92647012 | H19: 5008470.5 | I19: 13746974 | J19: 1345721.3 | K19: 28678899 | L19: 19230634
B20: Intangible Assets | C20: {='[1]APPENDIX 5 II'!$C20:$L20} -> 15.272 | D20: 3861.87 | E20: 54763.281 | F20: 22934.014 | G20: 2276.655 | H20: 6649.8412 | I20: 0 | J20: 17340.215 | K20: 117174.11 | L20: 42718.265
B21: Land and Buildings | C21: {='[1]APPENDIX 5 II'!$C21:$L21} -> 0 | D21: 0 | E21: 0 | F21: 0 | G21: 854038.77 | H21: 0 | I21: 0 | J21: 0 | K21: 770786.86 | L21: 263398.36
B22: Investment Property | C22: {='[1]APPENDIX 5 II'!$C22:$L22} -> 1443598.5 | D22: 74000 | E22: 10288000 | F22: 3496391.8 | G22: 2060400 | H22: 560000 | I22: 1889175 | J22: 0 | K22: 445213.14 | L22: 7091924.5
B23: Fixed Assets | C23: {='[1]APPENDIX 5 II'!$C23:$L23} -> 543.15348 | D23: 13954.678 | E23: 265013.75 | F23: 171010.2 | G23: 18772.043 | H23: 2834.4098 | I23: 0 | J23: 81017.927 | K23: 78772.488 | L23: 31032.051
B24: Government Securites | C24: {='[1]APPENDIX 5 II'!$C24:$L24} -> 44576014 | D24: 1561057.5 | E24: 1.0816038e+08 | F24: 1.2530407e+08 | G24: 88294194 | H24: 3597237.2 | I24: 6920992 | J24: 0 | K24: 18562350 | L24: 4509445
B25: Other Securites | C25: {='[1]APPENDIX 5 II'!$C25:$L25} -> 1548.433 | D25: 0 | E25: 1763212.6 | F25: 0 | G25: 0 | H25: 127418.09 | I25: 0 | J25: 0 | K25: 1003736.1 | L25: 19388.02
B26: Investment in Related Parties | C26: {='[1]APPENDIX 5 II'!$C26:$L26} -> 0 | D26: 0 | E26: 747113.95 | F26: 2539945.3 | G26: 0 | H26: 0 | I26: 0 | J26: 0 | K26: 0 | L26: 0
B27: Corporate Bonds | C27: {='[1]APPENDIX 5 II'!$C27:$L27} -> 0 | D27: 3250.4994 | E27: 224792.5 | F27: 7099.451 | G27: 6616.6376 | H27: 123490.19 | I27: 0 | J27: 0 | K27: 0 | L27: 0
B28: Commercial Papers | C28: {='[1]APPENDIX 5 II'!$C28:$L28} -> 0 | D28: 0 | E28: 0 | F28: 0 | G28: 0 | H28: 0 | I28: 0 | J28: 0 | K28: 0 | L28: 0
B29: Debentures | C29: {='[1]APPENDIX 5 II'!$C29:$L29} -> 0 | D29: 0 | E29: 0 | F29: 0 | G29: 0 | H29: 0 | I29: 0 | J29: 0 | K29: 0 | L29: 0
B30: Ordinary Shares Quoted | C30: {='[1]APPENDIX 5 II'!$C30:$L30} -> 73739.631 | D30: 34499.452 | E30: 7639497.4 | F30: 5042888.9 | G30: 776729.86 | H30: 0 | I30: 215732 | J30: 0 | K30: 1380941.3 | L30: 122973.12
B31: Ordinary Shares Unquoted | C31: {='[1]APPENDIX 5 II'!$C31:$L31} -> 0 | D31: 0 | E31: 15724.8 | F31: 5133019.7 | G31: 31.89872 | H31: 283929.8 | I31: 0 | J31: 0 | K31: 196597.8 | L31: 2043847.4
... B41: Other Assets | C41: {='[1]APPENDIX 5 II'!$C41:$L41} -> 30941.601 | D41: 447515.53 | E41: 1326980.7 | F41: 901336.45 | G41: 18296.047 | H41: 16485.514 | I41: -51125.055 | J41: 425268.07 | K41: 203330.84 | L41: 1390779.5
B42: Total Assets | C42: 46392713 | D42: 3561924.2 | E42: 1.8208476e+08 | F42: 1.4906906e+08 | G42: 92647012 | H42: 5008470.5 | I42: 13746974 | J42: 1345721.3 | K42: 28678899 | L42: 19230634
B43: Amounts in thousand Shillings | L43: Continued next page

Sheet APPENDIX 5 III
B2: Continued from previous page
B3: =_xlfn.CONCAT(INDEX(_xlfn.TEXTSPLIT(Contents!E19," III"),1),": ",UPPER(Contents!F19)) -> APPENDIX 5: SUMMARY OF LONG TERM INSURANCE BUSINESS BALANCE SHEETS AS AT 31.12.2024 | N3: Life | P3: Industry
B4: Company | C4: OLD MUTUAL ASSURANCE COMPANY | D4: OLD MUTUAL LIFE ASSURANCE KENYA | E4: PIONEER ASSURANCE COMPANY | F4: PRUDENTIAL LIFE ASSURANCE | G4: SANLAM LIFE ASSURANCE | H4: STAR DISCOVER LIFE INSURANCE | I4: THE KENYAN ALLIANCE INSURANCE | J4: THE MONARCH INSURANCE | K4: TOTAL | N4: Insurers | O4: Reinsurers | P4: Insurers | Q4: Reinsurers | R4: Industry
B5: Share Capital | C5: {='[1]APPENDIX 5 III'!$C5:$J5} -> 2174870.5 | D5: 2946667.4 | E5: 400000 | F5: 425698.08 | G5: 843138.54 | H5: 400000 | I5: 500000 | J5: 154975.83 | K5: =SUM(_xlfn.ANCHORARRAY($C5),_xlfn.ANCHORARRAY('APPENDIX 5 II'!$C5),_xlfn.ANCHORARRAY('APPENDIX 5 I'!$C5)) -> 19369610 | M5: =B5 -> Share Capital | N5: =K5-O5 -> 17869610 | O5: ='APPENDIX 5 I'!I5+'APPENDIX 5 I'!K5+'APPENDIX 5 II'!I5 -> 1500000 | P5: =$N5+'APPENDIX 6 IV'!$P5+'APPENDIX 7'!$E5 -> 50910475 | Q5: =$O5+'APPENDIX 6 IV'!$Q5 -> 19101531 | R5: =SUM(P5:Q5) -> 70012006
B6: Share Premium_x000D_ | C6: {='[1]APPENDIX 5 III'!$C6:$J6} -> 1884956.8 | D6: 1160475.7 | E6: 0 | F6: 3768621.6 | G6: 30260 | H6: 0 | I6: 0 | J6: 0 | K6: =SUM(_xlfn.ANCHORARRAY($C6),_xlfn.ANCHORARRAY('APPENDIX 5 II'!$C6),_xlfn.ANCHORARRAY('APPENDIX 5 I'!$C6)) -> 8640381.8 | M6: =B6 -> Share Premium_x000D_ | N6: =K6-O6 -> 8640381.8 | O6: ='APPENDIX 5 I'!I6+'APPENDIX 5 I'!K6+'APPENDIX 5 II'!I6 -> 0 | P6: =$N6+'APPENDIX 6 IV'!$P6+'APPENDIX 7'!$E6 -> 11949731 | Q6: =$O6+'APPENDIX 6 IV'!$Q6 -> 10871.242 | R6: =SUM(P6:Q6) -> 11960603
B7: Revaluation Reserves | C7: {='[1]APPENDIX 5 III'!$C7:$J7} -> 0 | D7: 0 | E7: 0 | F7: 0 | G7: 0 | H7: 0 | I7: 0 | J7: 0 | K7: =SUM(_xlfn.ANCHORARRAY($C7),_xlfn.ANCHORARRAY('APPENDIX 5 II'!$C7),_xlfn.ANCHORARRAY('APPENDIX 5 I'!$C7)) -> 400223.89 | M7: =B7 -> Revaluation Reserves | N7: =K7-O7 -> 400223.89 | O7: ='APPENDIX 5 I'!I7+'APPENDIX 5 I'!K7+'APPENDIX 5 II'!I7 -> 0 | P7: =$N7+'APPENDIX 6 IV'!$P7+'APPENDIX 7'!$E7 -> 2866332.9 | Q7: =$O7+'APPENDIX 6 IV'!$Q7 -> 258456.3 | R7: =SUM(P7:Q7) -> 3124789.2
B8: Statutory Reserves | C8: {='[1]APPENDIX 5 III'!$C8:$J8} -> 0 | D8: -243794.7 | E8: 232406.33 | F8: 0 | G8: 3371580.5 | H8: 0 | I8: -142526.83 | J8: 49787.343 | K8: =SUM(_xlfn.ANCHORARRAY($C8),_xlfn.ANCHORARRAY('APPENDIX 5 II'!$C8),_xlfn.ANCHORARRAY('APPENDIX 5 I'!$C8)) -> 40682406 | M8: =B8 -> Statutory Reserves | N8: =K8-O8 -> 40661350 | O8: ='APPENDIX 5 I'!I8+'APPENDIX 5 I'!K8+'APPENDIX 5 II'!I8 -> 21056.733 | P8: =$N8 -> 40661350 | Q8: =$O8 -> 21056.733 | R8: =SUM(P8:Q8) -> 40682406
B9: Other Equity | C9: {='[1]APPENDIX 5 III'!$C9:$J9} -> 0 | D9: 0 | E9: 35000 | F9: 0 | G9: 0 | H9: 0 | I9: 0 | J9: 0 | K9: =SUM(_xlfn.ANCHORARRAY($C9),_xlfn.ANCHORARRAY('APPENDIX 5 II'!$C9),_xlfn.ANCHORARRAY('APPENDIX 5 I'!$C9)) -> 3009827.7 | M9: =B9 -> Other Equity | N9: =K9-O9 -> 3009843.6 | O9: ='APPENDIX 5 I'!I9+'APPENDIX 5 I'!K9+'APPENDIX 5 II'!I9 -> -15.88 | P9: =$N9+'APPENDIX 6 IV'!$P8+'APPENDIX 7'!$E8 -> 6729810.2 | Q9: =$O9+'APPENDIX 6 IV'!$Q8 -> -108854.05 | R9: =SUM(P9:Q9) -> 6620956.1
B10: Retained Earnings | C10: {='[1]APPENDIX 5 III'!$C10:$J10} -> -1932091.2 | D10: -648605.14 | E10: 248225.2 | F10: -2970308.4 | G10: 23593.194 | H10: 256186.03 | I10: 41677.369 | J10: -63841.241 | K10: =SUM(_xlfn.ANCHORARRAY($C10),_xlfn.ANCHORARRAY('APPENDIX 5 II'!$C10),_xlfn.ANCHORARRAY('APPENDIX 5 I'!$C10)) -> 23399837 | M10: =B10 -> Retained Earnings | N10: =K10-O10 -> 11929305 | O10: ='APPENDIX 5 I'!I10+'APPENDIX 5 I'!K10+'APPENDIX 5 II'!I10 -> 11470532 | P10: =$N10+'APPENDIX 6 IV'!$P9+'APPENDIX 7'!$E9 -> 48904329 | Q10: =$O10+'APPENDIX 6 IV'!$Q9 -> 43397976 | R10: =SUM(P10:Q10) -> 92302305
B11: Other Reserves | C11: {='[1]APPENDIX 5 III'!$C11:$J11} -> 0 | D11: 27533.634 | E11: 0 | F11: 0 | G11: 0 | H11: 0 | I11: 0 | J11: 1113.588 | K11: =SUM(_xlfn.ANCHORARRAY($C11),_xlfn.ANCHORARRAY('APPENDIX 5 II'!$C11),_xlfn.ANCHORARRAY('APPENDIX 5 I'!$C11)) -> 704007.92 | M11: =B11 -> Other Reserves | N11: =K11-O11 -> 704007.92 | O11: ='APPENDIX 5 I'!I11+'APPENDIX 5 I'!K11+'APPENDIX 5 II'!I11 -> 0 | P11: =$N11+'APPENDIX 6 IV'!$P10+'APPENDIX 7'!$E10 -> 6029057.5 | Q11: =O11+'APPENDIX 6 IV'!Q10 -> 1447472.7 | R11: =SUM(P11:Q11) -> 7476530.2
B12: Total Equity_x000D_ | C12: =SUM(C5:C11) -> 2127736.2 | D12: =SUM(D5:D11) -> 3242276.9 | E12: =SUM(E5:E11) -> 915631.53 | F12: =SUM(F5:F11) -> 1224011.3 | G12: =SUM(G5:G11) -> 4268572.3 | H12: =SUM(H5:H11) -> 656186.03 | I12: =SUM(I5:I11) -> 399150.54 | J12: =SUM(J5:J11) -> 142035.52 | K12: =SUM(K5:K11) -> 96206295 | M12: =B12 -> Total Equity_x000D_ | N12: =K12-O12 -> 83214721 | O12: ='APPENDIX 5 I'!I12+'APPENDIX 5 I'!K12+'APPENDIX 5 II'!I12 -> 12991573 | P12: =$N12+'APPENDIX 6 IV'!$P11+'APPENDIX 7'!$E11 -> 1.6805108e+08 | Q12: =O12+'APPENDIX 6 IV'!Q11 -> 64128510 | R12: =SUM(P12:Q12) -> 2.321796e+08
B13: Investment Contract Liabilites | C13: {='[1]APPENDIX 5 III'!$C13:$J13} -> 896243.72 | D13: 36798.965 | E13: 142326.44 | F13: 0 | G13: 0 | H13: 0 | I13: 4495886.7 | J13: 0 | K13: =SUM(_xlfn.ANCHORARRAY($C13),_xlfn.ANCHORARRAY('APPENDIX 5 II'!$C13),_xlfn.ANCHORARRAY('APPENDIX 5 I'!$C13)) -> 59758602 | M13: =B13 -> Investment Contract Liabilites | N13: =K13-O13 -> 59758602 | O13: ='APPENDIX 5 I'!I13+'APPENDIX 5 I'!K13+'APPENDIX 5 II'!I13 -> 0 | P13: =$N13 -> 59758602 | Q13: =O13 -> 0 | R13: =SUM(P13:Q13) -> 59758602
B14: Insurance Contract Liabilites | C14: {='[1]APPENDIX 5 III'!$C14:$J14} -> 9060933.5 | D14: 13221608 | E14: 11097933 | F14: 4299273.5 | G14: 27535254 | H14: 9080.7995 | I14: 1022318.6 | J14: 1185811.6 | K14: =SUM(_xlfn.ANCHORARRAY($C14),_xlfn.ANCHORARRAY('APPENDIX 5 II'!$C14),_xlfn.ANCHORARRAY('APPENDIX 5 I'!$C14)) -> 7.0830141e+08 | M14: =B14 -> Insurance Contract Liabilites | N14: =K14-O14 -> 7.0446481e+08 | O14: ='APPENDIX 5 I'!I14+'APPENDIX 5 I'!K14+'APPENDIX 5 II'!I14 -> 3836595.8 | P14: =$N14+'APPENDIX 6 IV'!$P12+'APPENDIX 7'!$E12 -> 8.6505625e+08 | Q14: =O14+'APPENDIX 6 IV'!Q12 -> 24568657 | R14: =SUM(P14:Q14) -> 8.8962491e+08
B15: Reinsurance Contract Liabilites | C15: {='[1]APPENDIX 5 III'!$C15:$J15} -> 0 | D15: 0 | E15: 0 | F15: 0 | G15: 0 | H15: 0 | I15: 0 | J15: 0 | K15: =SUM(_xlfn.ANCHORARRAY($C15),_xlfn.ANCHORARRAY('APPENDIX 5 II'!$C15),_xlfn.ANCHORARRAY('APPENDIX 5 I'!$C15)) -> 438995.86 | M15: =B15 -> Reinsurance Contract Liabilites | N15: =K15-O15 -> 317415.26 | O15: ='APPENDIX 5 I'!I15+'APPENDIX 5 I'!K15+'APPENDIX 5 II'!I15 -> 121580.6 | P15: =$N15+'APPENDIX 6 IV'!$P13+'APPENDIX 7'!$E13 -> 3761954.9 | Q15: =O15+'APPENDIX 6 IV'!Q13 -> 2022365.3 | R15: =SUM(P15:Q15) -> 5784320.2
B16: Long-Term Liabilites | C16: {='[1]APPENDIX 5 III'!$C16:$J16} -> 0 | D16: 0 | E16: 0 | F16: 0 | G16: 1445374.9 | H16: 0 | I16: 0 | J16: 14935.603 | K16: =SUM(_xlfn.ANCHORARRAY($C16),_xlfn.ANCHORARRAY('APPENDIX 5 II'!$C16),_xlfn.ANCHORARRAY('APPENDIX 5 I'!$C16)) -> 17922132 | M16: =B16 -> Long-Term Liabilites | N16: =K16-O16 -> 17399128 | O16: ='APPENDIX 5 I'!I16+'APPENDIX 5 I'!K16+'APPENDIX 5 II'!I16 -> 523003.9 | P16: =$N16+'APPENDIX 6 IV'!$P14+'APPENDIX 7'!$E14 -> 19408180 | Q16: =O16+'APPENDIX 6 IV'!Q14 -> 2002249.9 | R16: =SUM(P16:Q16) -> 21410430
B17: Short-Term Liabilites | C17: {='[1]APPENDIX 5 III'!$C17:$J17} -> 438130.54 | D17: 616169.59 | E17: 534660.44 | F17: 56113.338 | G17: 782949.46 | H17: 34225.682 | I17: 32668.976 | J17: 2831.948 | K17: =SUM(_xlfn.ANCHORARRAY($C17),_xlfn.ANCHORARRAY('APPENDIX 5 II'!$C17),_xlfn.ANCHORARRAY('APPENDIX 5 I'!$C17)) -> 7206957.5 | M17: =B17 -> Short-Term Liabilites | N17: =K17-O17 -> 7181204 | O17: ='APPENDIX 5 I'!I17+'APPENDIX 5 I'!K17+'APPENDIX 5 II'!I17 -> 25753.554 | P17: =$N17+'APPENDIX 6 IV'!$P15+'APPENDIX 7'!$E15 -> 22546342 | Q17: =O17+'APPENDIX 6 IV'!Q15 -> 1004352.5 | R17: =SUM(P17:Q17) -> 23550695
B18: Other Liabilites | C18: {='[1]APPENDIX 5 III'!$C18:$J18} -> 398997.01 | D18: 215921.82 | E18: 229662.98 | F18: 333145.94 | G18: 158306.71 | H18: 9631.521 | I18: 0 | J18: 20990.284 | K18: =SUM(_xlfn.ANCHORARRAY($C18),_xlfn.ANCHORARRAY('APPENDIX 5 II'!$C18),_xlfn.ANCHORARRAY('APPENDIX 5 I'!$C18)) -> 11438206 | M18: =B18 -> Other Liabilites | N18: =K18-O18 -> 11390422 | O18: ='APPENDIX 5 I'!I18+'APPENDIX 5 I'!K18+'APPENDIX 5 II'!I18 -> 47784.763 | P18: =$N18+'APPENDIX 6 IV'!$P16+'APPENDIX 7'!$E16 -> 19017858 | Q18: =O18+'APPENDIX 6 IV'!Q16 -> 1068957.9 | R18: =SUM(P18:Q18) -> 20086816
B19: Total Equity And Liabilities | C19: =SUM(C12:C18) -> 12922041 | D19: =SUM(D12:D18) -> 17332775 | E19: =SUM(E12:E18) -> 12920214 | F19: =SUM(F12:F18) -> 5912544.1 | G19: =SUM(G12:G18) -> 34190458 | H19: =SUM(H12:H18) -> 709124.03 | I19: =SUM(I12:I18) -> 5950024.8 | J19: =SUM(J12:J18) -> 1366604.9 | K19: =SUM(K12:K18) -> 9.012726e+08 | M19: =B19 -> Total Equity And Liabilities | N19: =K19-O19 -> 8.8372631e+08 | O19: ='APPENDIX 5 I'!I19+'APPENDIX 5 I'!K19+'APPENDIX 5 II'!I19 -> 17546292 | P19: =$N19+'APPENDIX 6 IV'!$P17+'APPENDIX 7'!$E17 -> 1.1576003e+09 | Q19: =O19+'APPENDIX 6 IV'!Q17 -> 94795093 | R19: =SUM(P19:Q19) -> 1.2523954e+09
B20: Intangible Assets | C20: {='[1]APPENDIX 5 III'!$C20:$J20} -> 8251.1735 | D20: 12825.775 | E20: 7696.601 | F20: 17106.704 | G20: 0 | H20: 6861.729 | I20: 0 | J20: 133.63221 | K20: =SUM(_xlfn.ANCHORARRAY($C20),_xlfn.ANCHORARRAY('APPENDIX 5 II'!$C20),_xlfn.ANCHORARRAY('APPENDIX 5 I'!$C20)) -> 951355.09 | M20: =B20 -> Intangible Assets | N20: =K20-O20 -> 951354.99 | O20: ='APPENDIX 5 I'!I20+'APPENDIX 5 I'!K20+'APPENDIX 5 II'!I20 -> 0.1 | P20: =$N20+'APPENDIX 6 IV'!$P18+'APPENDIX 7'!$E18 -> 2308503.5 | Q20: =O20+'APPENDIX 6 IV'!Q18 -> 49119.667 | R20: =SUM(P20:Q20) -> 2357623.2
B21: Land and Buildings | C21: {='[1]APPENDIX 5 III'!$C21:$J21} -> 0 | D21: 0 | E21: 0 | F21: 0 | G21: 0 | H21: 0 | I21: 0 | J21: 0 | K21: =SUM(_xlfn.ANCHORARRAY($C21),_xlfn.ANCHORARRAY('APPENDIX 5 II'!$C21),_xlfn.ANCHORARRAY('APPENDIX 5 I'!$C21)) -> 2311206 | M21: =B21 -> Land and Buildings | N21: =K21-O21 -> 2311206 | O21: ='APPENDIX 5 I'!I21+'APPENDIX 5 I'!K21+'APPENDIX 5 II'!I21 -> 0 | P21: =$N21+'APPENDIX 6 IV'!$P19+'APPENDIX 7'!$E19 -> 7539079.1 | Q21: =O21+'APPENDIX 6 IV'!Q19 -> 415753.62 | R21: =SUM(P21:Q21) -> 7954832.7
B22: Investment Property | C22: {='[1]APPENDIX 5 III'!$C22:$J22} -> 2344000 | D22: 0 | E22: 1706200 | F22: 0 | G22: 2799000 | H22: 0 | I22: 3184650 | J22: 317720.52 | K22: =SUM(_xlfn.ANCHORARRAY($C22),_xlfn.ANCHORARRAY('APPENDIX 5 II'!$C22),_xlfn.ANCHORARRAY('APPENDIX 5 I'!$C22)) -> 58576009 | M22: =B22 -> Investment Property | N22: =K22-O22 -> 56686834 | O22: ='APPENDIX 5 I'!I22+'APPENDIX 5 I'!K22+'APPENDIX 5 II'!I22 -> 1889175 | P22: =$N22+'APPENDIX 6 IV'!$P20+'APPENDIX 7'!$E20 -> 80725496 | Q22: =O22+'APPENDIX 6 IV'!Q20 -> 13795800 | R22: =SUM(P22:Q22) -> 94521296
B23: Fixed Assets | C23: {='[1]APPENDIX 5 III'!$C23:$J23} -> 2534.4375 | D23: 104755.53 | E23: 29483.627 | F23: 21898.611 | G23: 93270.668 | H23: 2820.1315 | I23: 7658.424 | J23: 10478.761 | K23: =SUM(_xlfn.ANCHORARRAY($C23),_xlfn.ANCHORARRAY('APPENDIX 5 II'!$C23),_xlfn.ANCHORARRAY('APPENDIX 5 I'!$C23)) -> 1143098.3 | M23: =B23 -> Fixed Assets | N23: =K23-O23 -> 1143098.3 | O23: ='APPENDIX 5 I'!I23+'APPENDIX 5 I'!K23+'APPENDIX 5 II'!I23 -> 0 | P23: =$N23+'APPENDIX 6 IV'!$P21+'APPENDIX 7'!$E21 -> 2921353.5 | Q23: =O23+'APPENDIX 6 IV'!Q21 -> 143396.76 | R23: =SUM(P23:Q23) -> 3064750.3
B24: Government Securites | C24: {='[1]APPENDIX 5 III'!$C24:$J24} -> 7058900.6 | D24: 10406006 | E24: 5470237.1 | F24: 4355048.8 | G24: 28864568 | H24: 21920.863 | I24: 614604.15 | J24: 56044.244 | K24: =SUM(_xlfn.ANCHORARRAY($C24),_xlfn.ANCHORARRAY('APPENDIX 5 II'!$C24),_xlfn.ANCHORARRAY('APPENDIX 5 I'!$C24)) -> 6.5338681e+08 | M24: =B24 -> Government Securites | N24: =K24-O24 -> 6.4452727e+08 | O24: ='APPENDIX 5 I'!I24+'APPENDIX 5 I'!K24+'APPENDIX 5 II'!I24 -> 8859541.5 | P24: =$N24+'APPENDIX 6 IV'!$P22+'APPENDIX 7'!$E22 -> 7.4415549e+08 | Q24: =O24+'APPENDIX 6 IV'!Q22 -> 35552322 | R24: =SUM(P24:Q24) -> 7.7970781e+08
B25: Other Securites | C25: {='[1]APPENDIX 5 III'!$C25:$J25} -> 9984.7448 | D25: 206014.34 | E25: 0 | F25: 0 | G25: 0 | H25: 0 | I25: 0 | J25: 0 | K25: =SUM(_xlfn.ANCHORARRAY($C25),_xlfn.ANCHORARRAY('APPENDIX 5 II'!$C25),_xlfn.ANCHORARRAY('APPENDIX 5 I'!$C25)) -> 14726372 | M25: =B25 -> Other Securites | N25: =K25-O25 -> 14726372 | O25: ='APPENDIX 5 I'!I25+'APPENDIX 5 I'!K25+'APPENDIX 5 II'!I25 -> 0 | P25: =$N25+'APPENDIX 6 IV'!$P23+'APPENDIX 7'!$E23 -> 15319788 | Q25: =O25+'APPENDIX 6 IV'!Q23 -> 702854.02 | R25: =SUM(P25:Q25) -> 16022642
B26: Investment in Related Parties | C26: {='[1]APPENDIX 5 III'!$C26:$J26} -> 0 | D26: 2127736.2 | E26: 0 | F26: 0 | G26: 0 | H26: 0 | I26: 0 | J26: 0 | K26: =SUM(_xlfn.ANCHORARRAY($C26),_xlfn.ANCHORARRAY('APPENDIX 5 II'!$C26),_xlfn.ANCHORARRAY('APPENDIX 5 I'!$C26)) -> 13025789 | M26: =B26 -> Investment in Related Parties | N26: =K26-O26 -> 13025789 | O26: ='APPENDIX 5 I'!I26+'APPENDIX 5 I'!K26+'APPENDIX 5 II'!I26 -> 0 | P26: =$N26+'APPENDIX 6 IV'!$P24+'APPENDIX 7'!$E24 -> 19651027 | Q26: =O26+'APPENDIX 6 IV'!Q24 -> 12567784 | R26: =SUM(P26:Q26) -> 32218811
B27: Corporate Bonds | C27: {='[1]APPENDIX 5 III'!$C27:$J27} -> 0 | D27: 51144.022 | E27: 0 | F27: 0 | G27: 0 | H27: 0 | I27: 0 | J27: 0 | K27: =SUM(_xlfn.ANCHORARRAY($C27),_xlfn.ANCHORARRAY('APPENDIX 5 II'!$C27),_xlfn.ANCHORARRAY('APPENDIX 5 I'!$C27)) -> 649243.49 | M27: =B27 -> Corporate Bonds | N27: =K27-O27 -> 649243.49 | O27: ='APPENDIX 5 I'!I27+'APPENDIX 5 I'!K27+'APPENDIX 5 II'!I27 -> 0 | P27: =$N27+'APPENDIX 6 IV'!$P25+'APPENDIX 7'!$E25 -> 818104.68 | Q27: =O27+'APPENDIX 6 IV'!Q25 -> 44819.627 | R27: =SUM(P27:Q27) -> 862924.3
B28: Commercial Papers | C28: {='[1]APPENDIX 5 III'!$C28:$J28} -> 0 | D28: 0 | E28: 0 | F28: 0 | G28: 0 | H28: 0 | I28: 0 | J28: 0 | K28: =SUM(_xlfn.ANCHORARRAY($C28),_xlfn.ANCHORARRAY('APPENDIX 5 II'!$C28),_xlfn.ANCHORARRAY('APPENDIX 5 I'!$C28)) -> 75198.08 | M28: =B28 -> Commercial Papers | N28: =K28-O28 -> 75198.08 | O28: ='APPENDIX 5 I'!I28+'APPENDIX 5 I'!K28+'APPENDIX 5 II'!I28 -> 0 | P28: =$N28+'APPENDIX 6 IV'!$P26+'APPENDIX 7'!$E26 -> 83313.779 | Q28: =O28+'APPENDIX 6 IV'!Q26 -> 0 | R28: =SUM(P28:Q28) -> 83313.779
B29: Debentures | C29: {='[1]APPENDIX 5 III'!$C29:$J29} -> 0 | D29: 0 | E29: 0 | F29: 0 | G29: 0 | H29: 0 | I29: 0 | J29: 0 | K29: =SUM(_xlfn.ANCHORARRAY($C29),_xlfn.ANCHORARRAY('APPENDIX 5 II'!$C29),_xlfn.ANCHORARRAY('APPENDIX 5 I'!$C29)) -> 0 | M29: =B29 -> Debentures | N29: =K29-O29 -> 0 | O29: ='APPENDIX 5 I'!I29+'APPENDIX 5 I'!K29+'APPENDIX 5 II'!I29 -> 0 | P29: =$N29+'APPENDIX 6 IV'!$P27+'APPENDIX 7'!$E27 -> 357021.47 | Q29: =O29+'APPENDIX 6 IV'!Q27 -> 0 | R29: =SUM(P29:Q29) -> 357021.47
B30: Ordinary Shares Quoted | C30: {='[1]APPENDIX 5 III'!$C30:$J30} -> 440862.47 | D30: 232589.83 | E30: 744186.39 | F30: 0 | G30: 0 | H30: 0 | I30: 0 | J30: 0 | K30: =SUM(_xlfn.ANCHORARRAY($C30),_xlfn.ANCHORARRAY('APPENDIX 5 II'!$C30),_xlfn.ANCHORARRAY('APPENDIX 5 I'!$C30)) -> 21606174 | M30: =B30 -> Ordinary Shares Quoted | N30: =K30-O30 -> 21381290 | O30: ='APPENDIX 5 I'!I30+'APPENDIX 5 I'!K30+'APPENDIX 5 II'!I30 -> 224883.88 | P30: =$N30+'APPENDIX 6 IV'!$P28+'APPENDIX 7'!$E28 -> 24584631 | Q30: =O30+'APPENDIX 6 IV'!Q28 -> 1437374.9 | R30: =SUM(P30:Q30) -> 26022006
B31: Ordinary Shares Unquoted | C31: {='[1]APPENDIX 5 III'!$C31:$J31} -> 442611.09 | D31: 113721.32 | E31: 0 | F31: 0 | G31: 0 | H31: 0 | I31: 0 | J31: 0 | K31: =SUM(_xlfn.ANCHORARRAY($C31),_xlfn.ANCHORARRAY('APPENDIX 5 II'!$C31),_xlfn.ANCHORARRAY('APPENDIX 5 I'!$C31)) -> 9088891 | M31: =B31 -> Ordinary Shares Unquoted | N31: =K31-O31 -> 9088891 | O31: ='APPENDIX 5 I'!I31+'APPENDIX 5 I'!K31+'APPENDIX 5 II'!I31 -> 0 | P31: =$N31+'APPENDIX 6 IV'!$P29+'APPENDIX 7'!$E29 -> 13509212 | Q31: =O31+'APPENDIX 6 IV'!Q29 -> 603113.15 | R31: =SUM(P31:Q31) -> 14112325
... B41: Other Assets | C41: {='[1]APPENDIX 5 III'!$C41:$J41} -> 160117.55 | D41: 1318834.5 | E41: 2937270.8 | F41: 132550.42 | G41: 73167.446 | H41: 3327.345 | I41: 74158.13 | J41: 0 | K41: =SUM(_xlfn.ANCHORARRAY($C41),_xlfn.ANCHORARRAY('APPENDIX 5 II'!$C41),_xlfn.ANCHORARRAY('APPENDIX 5 I'!$C41)) -> 11789178 | M41: =B41 -> Other Assets | N41: =K41-O41 -> 11840303 | O41: ='APPENDIX 5 I'!I41+'APPENDIX 5 I'!K41+'APPENDIX 5 II'!I41 -> -51125.055 | P41: =$N41+'APPENDIX 6 IV'!$P39+'APPENDIX 7'!$E39 -> 30957453 | Q41: =O41+'APPENDIX 6 IV'!Q39 -> 1655078.5 | R41: =SUM(P41:Q41) -> 32612531
B42: Total Assets | C42: =SUM(C20:C41) -> 12922041 | D42: =SUM(D20:D41) -> 17332775 | E42: =SUM(E20:E41) -> 12920214 | F42: =SUM(F20:F41) -> 5912544.1 | G42: =SUM(G20:G41) -> 34190458 | H42: =SUM(H20:H41) -> 709124.03 | I42: =SUM(I20:I41) -> 5950024.8 | J42: =SUM(J20:J41) -> 1366605 | K42: =SUM(K20:K41) -> 9.012726e+08 | M42: =B42 -> Total Assets | N42: =K42-O42 -> 8.8372631e+08 | O42: ='APPENDIX 5 I'!I42+'APPENDIX 5 I'!K42+'APPENDIX 5 II'!I42 -> 17546292 | P42: =$N42+'APPENDIX 6 IV'!$P40+'APPENDIX 7'!$E40 -> 1.1576003e+09 | Q42: =O42+'APPENDIX 6 IV'!Q40 -> 94795093 | R42: =SUM(P42:Q42) -> 1.2523954e+09
B43: Amounts in Thousand Shillings
M45: Total Assets | N45: =N42 -> 8.8372631e+08 | O45: =O42 -> 17546292
M46: Investments | N46: =SUM(N22,N24:N36) -> 8.4322733e+08 | O46: =SUM(O22,O24:O36) -> 16865990

Sheet APPENDIX 6 I
B3: =_xlfn.CONCAT(INDEX(_xlfn.TEXTSPLIT(Contents!E20," I"),1),": ",UPPER(Contents!F20)) -> APPENDIX 6: SUMMARY OF GENERAL INSURANCE BUSINESS BALANCE SHEETS AS AT 31.12.2024
B4: Company | C4: AAR INSURANCE KENYA | D4: AFRICA MERCHANT ASSURANCE | E4: APA INSURANCE LIMITED | F4: BRITAM GENERAL INSURANCE | G4: CANNON GENERAL INSURANCE (K) LIMITED | H4: CIC GENERAL INSURANCE COMPANY | I4: CONTINENTAL REINSURANCE | J4: CORPORATE INSURANCE COMPANY | K4: DIRECTLINE ASSURANCE COMPANY | L4: EAST AFRICA REINSURANCE
B5: Share Captial | C5: {='[1]APPENDIX 6 I'!$C5:$L5} -> 1017626.6 | D5: 987386 | E5: 1250000 | F5: 2668000 | G5: 453960.46 | H5: 1700000 | I5: 1000000 | J5: 484386.36 | K5: 300000 | L5: 1000000
B6: Share Premium | C6: {='[1]APPENDIX 6 I'!$C6:$L6} -> 460523 | D6: 0 | E6: 0 | F6: 0 | G6: 583039.52 | H6: 0 | I6: 0 | J6: 0 | K6: 0 | L6: 0
B7: Revaluation Reserve | C7: {='[1]APPENDIX 6 I'!$C7:$L7} -> 0 | D7: 26469.279 | E7: 234618.57 | F7: 0 | G7: 74345 | H7: 0 | I7: 0 | J7: 0 | K7: -19998.74 | L7: 221544.99
B8: Other Equity | C8: {='[1]APPENDIX 6 I'!$C8:$L8} -> 0 | D8: 0 | E8: 0 | F8: 0 | G8: -86582 | H8: -63031.003 | I8: 664.738 | J8: 0 | K8: 0 | L8: 0
B9: Retained Earnings | C9: {='[1]APPENDIX 6 I'!$C9:$L9} -> 730157.61 | D9: 171548.47 | E9: 4895288.5 | F9: 4193214.8 | G9: -152379.93 | H9: 3691780.7 | I9: 1755224.7 | J9: 378124.47 | K9: -1809742 | L9: 4640307.3
B10: Other Reserves | C10: {='[1]APPENDIX 6 I'!$C10:$L10} -> 0 | D10: 0 | E10: 0 | F10: 0 | G10: 0 | H10: 0 | I10: -76192.105 | J10: 32245.5 | K10: 0 | L10: 0
B11: Total Equity_x000D_ | C11: 2208307.2 | D11: 1185403.8 | E11: 6379907.1 | F11: 6861214.8 | G11: 872383.05 | H11: 5328749.7 | I11: 2679697.3 | J11: 894756.33 | K11: -1529740.7 | L11: 5861852.3
B12: Insurance Contract Liabilites | C12: {='[1]APPENDIX 6 I'!$C12:$L12} -> 3947147.7 | D12: 2411276.4 | E12: 10655276 | F12: 11369265 | G12: 2187018.4 | H12: 10866677 | I12: 5730133.7 | J12: 397559.99 | K12: 9247188.5 | L12: 3160037.5
B13: Reinsurance Contract Liabilites | C13: {='[1]APPENDIX 6 I'!$C13:$L13} -> 0 | D13: 166.61725 | E13: 0 | F13: 392919.22 | G13: 0 | H13: 0 | I13: 163203.55 | J13: 0 | K13: 0 | L13: 0
B14: Long-Term Liabilites | C14: {='[1]APPENDIX 6 I'!$C14:$L14} -> 0 | D14: 0 | E14: 0 | F14: 0 | G14: 90445.995 | H14: 0 | I14: 59711.597 | J14: 0 | K14: 0 | L14: 0
B15: Short-Term Liabilites | C15: {='[1]APPENDIX 6 I'!$C15:$L15} -> 770042.82 | D15: 156482.77 | E15: 926374.37 | F15: 493807.74 | G15: 373502.39 | H15: 863723.62 | I15: 0 | J15: 116519.69 | K15: 196620.64 | L15: 0
B16: Other Liabilites | C16: {='[1]APPENDIX 6 I'!$C16:$L16} -> 176024 | D16: 131330.61 | E16: 225841.39 | F16: 976724.34 | G16: 30741.775 | H16: 78761.002 | I16: 116393.95 | J16: 15594.489 | K16: 112804.27 | L16: 426645.67
B17: Total Equity And Liabilities | C17: 7101521.7 | D17: 3884660.2 | E17: 18187399 | F17: 20093931 | G17: 3554091.6 | H17: 17137912 | I17: 8749140 | J17: 1424430.5 | K17: 8026872.7 | L17: 9448535.5
B18: Intangible Assets | C18: {='[1]APPENDIX 6 I'!$C18:$L18} -> 11730.745 | D18: 31341.946 | E18: 31369.049 | F18: 121591.33 | G18: 6935.918 | H18: 45984.727 | I18: 0 | J18: 1245.7851 | K18: 0 | L18: 124.457
B19: Land and Buildings | C19: {='[1]APPENDIX 6 I'!$C19:$L19} -> 0 | D19: 902063.82 | E19: 0 | F19: 0 | G19: 92500 | H19: 234000 | I19: 0 | J19: 0 | K19: 0 | L19: 386875.53
B20: Investment Property | C20: {='[1]APPENDIX 6 I'!$C20:$L20} -> 0 | D20: 563000 | E20: 1070000 | F20: 0 | G20: 637973.3 | H20: 1602000 | I20: 0 | J20: 698735.74 | K20: 2505000 | L20: 735000
B21: Fixed Assets | C21: {='[1]APPENDIX 6 I'!$C21:$L21} -> 43611.303 | D21: 69144.231 | E21: 35960.049 | F21: 115082.17 | G21: 6128.549 | H21: 114140.3 | I21: 45600.469 | J21: 3700.6845 | K21: 41370.032 | L21: 8593.2919
B22: Government Securites | C22: {='[1]APPENDIX 6 I'!$C22:$L22} -> 3345811.9 | D22: 1103053.8 | E22: 8944561 | F22: 13136316 | G22: 281784.65 | H22: 7548545.7 | I22: 2898931.2 | J22: 85351.522 | K22: 918884.63 | L22: 3654040.6
B23: Other Securites | C23: {='[1]APPENDIX 6 I'!$C23:$L23} -> 0 | D23: 0 | E23: 94072.702 | F23: 0 | G23: 0 | H23: 307545.7 | I23: 0 | J23: 0 | K23: 0 | L23: 181408.8
B24: Investment in Related Parties | C24: {='[1]APPENDIX 6 I'!$C24:$L24} -> 442626.57 | D24: 0 | E24: 383072.24 | F24: 100000 | G24: 17359.102 | H24: 0 | I24: 0 | J24: 0 | K24: 0 | L24: 644852.22
B25: Corporate Bonds | C25: {='[1]APPENDIX 6 I'!$C25:$L25} -> 0 | D25: 0 | E25: 0 | F25: 0 | G25: 0 | H25: 5013.8428 | I25: 0 | J25: 0 | K25: 0 | L25: 0
B26: Commercial Papers | C26: {='[1]APPENDIX 6 I'!$C26:$L26} -> 0 | D26: 0 | E26: 0 | F26: 0 | G26: 0 | H26: 0 | I26: 0 | J26: 0 | K26: 0 | L26: 0
B27: Debentures | C27: {='[1]APPENDIX 6 I'!$C27:$L27} -> 0 | D27: 0 | E27: 0 | F27: 0 | G27: 0 | H27: 0 | I27: 0 | J27: 0 | K27: 0 | L27: 0
B28: Ordinary Shares Quoted | C28: {='[1]APPENDIX 6 I'!$C28:$L28} -> 0 | D28: 937.951 | E28: 716130.18 | F28: 0 | G28: 0 | H28: 287868 | I28: 0 | J28: 0 | K28: 132034.23 | L28: 18305.04
B29: Ordinary Shares Unquoted | C29: {='[1]APPENDIX 6 I'!$C29:$L29} -> 0 | D29: 0 | E29: 17689.758 | F29: 0 | G29: 1437.932 | H29: 18957.819 | I29: 0 | J29: 1784.9716 | K29: 0 | L29: 0
... B39: Other Assets | C39: {='[1]APPENDIX 6 I'!$C39:$L39} -> 483335.84 | D39: 350012.8 | E39: 657803.6 | F39: 1167705.4 | G39: 675302.38 | H39: 599332.56 | I39: 807110.31 | J39: 89013.525 | K39: 2129980.6 | L39: 36400.812
B40: Total Assets | C40: 7101521.7 | D40: 3884660.2 | E40: 18187399 | F40: 20093931 | G40: 3554091.6 | H40: 17137912 | I40: 8749140 | J40: 1424430.5 | K40: 8026872.7 | L40: 9448535.5
B41: Amounts in thousand Shillings | J41: Continued next page

Sheet APPENDIX 6 II
B2: Continued from previous page
B3: =_xlfn.CONCAT(INDEX(_xlfn.TEXTSPLIT(Contents!E21," II"),1),": ",UPPER(Contents!F21)) -> APPENDIX 6: SUMMARY OF GENERAL INSURANCE BUSINESS BALANCE SHEETS AS AT 31.12.2024
B4: Company | C4: EQUITY GENERAL INSURANCE | D4: FIDELITY SHIELD INSURANCE | E4: FIRST ASSURANCE COMPANY | F4: GA INSURANCE COMPANY | G4: GEMINIA INSURANCE COMPANY | H4: GHANA REINSURANCE COMPANY | I4: ICEA LION GENERAL INSURANCE | J4: INTRA AFRICA ASSURANCE | K4: INVESCO ASSURANCE COMPANY | L4: JUBILEE ALLIANZ GENERAL INSURANCE
B5: Share Captial | C5: {='[1]APPENDIX 6 II'!$C5:$L5} -> 600000 | D5: 600000 | E5: 810000 | F5: 1500000 | G5: 1006250 | H5: 1000000 | I5: 1000000 | J5: 700000 | K5: 0 | L5: 2307103
B6: Share Premium | C6: {='[1]APPENDIX 6 II'!$C6:$L6} -> 0 | D6: 0 | E6: 512138.51 | F6: 0 | G6: 0 | H6: 10871.242 | I6: 0 | J6: 0 | K6: 0 | L6: 1399897
B7: Revaluation Reserve | C7: {='[1]APPENDIX 6 II'!$C7:$L7} -> 0 | D7: 102296.5 | E7: 268057.86 | F7: 904878.74 | G7: 0 | H7: 0 | I7: -116541.79 | J7: 342209.34 | K7: 0 | L7: 0
B8: Other Equity | C8: {='[1]APPENDIX 6 II'!$C8:$L8} -> 0 | D8: 0 | E8: 0 | F8: 0 | G8: 3925.879 | H8: 0 | I8: 400000 | J8: 22000 | K8: 0 | L8: 0
B9: Retained Earnings | C9: {='[1]APPENDIX 6 II'!$C9:$L9} -> 56126.094 | D9: 522137.34 | E9: 200933 | F9: 6206255.5 | G9: 761356.11 | H9: 990387.66 | I9: 7059120.5 | J9: 218831.13 | K9: 0 | L9: -3467561
B10: Other Reserves | C10: {='[1]APPENDIX 6 II'!$C10:$L10} -> 0 | D10: 0 | E10: 0 | F10: 941057.58 | G10: 32216.243 | H10: 0 | I10: 0 | J10: 0 | K10: 0 | L10: 0
B11: Total Equity_x000D_ | C11: =SUM(C5:C10) -> 656126.09 | D11: =SUM(D5:D10) -> 1224433.8 | E11: =SUM(E5:E10) -> 1791129.4 | F11: =SUM(F5:F10) -> 9552191.8 | G11: =SUM(G5:G10) -> 1803748.2 | H11: =SUM(H5:H10) -> 2001258.9 | I11: =SUM(I5:I10) -> 8342578.7 | J11: =SUM(J5:J10) -> 1283040.5 | ... L11: =SUM(L5:L10) -> 239439
B12: Insurance Contract Liabilites | C12: {='[1]APPENDIX 6 II'!$C12:$L12} -> 0 | D12: 4385749.3 | E12: 5032380.9 | F12: 15417252 | G12: 4798423.2 | H12: 1069750.3 | I12: 7062281.6 | J12: 1420906 | K12: 0 | L12: 8352171.2
B13: Reinsurance Contract Liabilites | C13: {='[1]APPENDIX 6 II'!$C13:$L13} -> 0 | D13: 0 | E13: 0 | F13: 1881843.9 | G13: 0 | H13: 0 | I13: 173054.03 | J13: 0 | K13: 0 | L13: 483056.36
B14: Long-Term Liabilites | C14: {='[1]APPENDIX 6 II'!$C14:$L14} -> 200000 | D14: 0 | E14: 0 | F14: 137686.41 | G14: 0 | H14: 0 | I14: 449102.85 | J14: 39938.269 | K14: 0 | L14: 0
B15: Short-Term Liabilites | C15: {='[1]APPENDIX 6 II'!$C15:$L15} -> 0 | D15: 56414.318 | E15: 295351.61 | F15: 379678.71 | G15: 75442.547 | H15: 103390.62 | I15: 729496.28 | J15: 78467.908 | K15: 0 | L15: 1499759.4
B16: Other Liabilites | C16: {='[1]APPENDIX 6 II'!$C16:$L16} -> 24835.53 | D16: 108931.77 | E16: 551588.57 | F16: 311045.9 | G16: 62102.849 | H16: 1582.5978 | I16: 134665.77 | J16: 45576.614 | K16: 0 | L16: 123209
B17: Total Equity And Liabilities | C17: 880961.62 | D17: 5775529.2 | E17: 7670450.4 | F17: 27679699 | G17: 6739716.9 | H17: 3175982.4 | I17: 16891179 | J17: 2867929.2 | K17: 0 | L17: 10697635
B18: Intangible Assets | C18: {='[1]APPENDIX 6 II'!$C18:$L18} -> 0 | D18: 3643.767 | E18: 31363.194 | F18: 42961.969 | G18: 53175.104 | H18: 2538.883 | I18: 65214.753 | J18: 43031.778 | K18: 0 | L18: 15326
B19: Land and Buildings | C19: {='[1]APPENDIX 6 II'!$C19:$L19} -> 0 | D19: 222528.32 | E19: 443000 | F19: 1170000 | G19: 410000 | H19: 28878.092 | I19: 0 | J19: 0 | K19: 0 | L19: 0
B20: Investment Property | C20: {='[1]APPENDIX 6 II'!$C20:$L20} -> 0 | D20: 1001121.7 | E20: 980000 | F20: 1325380 | G20: 974500 | H20: 0 | I20: 2865000 | J20: 504000 | K20: 0 | L20: 0
B21: Fixed Assets | C21: {='[1]APPENDIX 6 II'!$C21:$L21} -> 0 | D21: 16404.332 | E21: 29695.06 | F21: 49857.265 | G21: 158487.65 | H21: 10635.951 | I21: 56699.452 | J21: 105586.75 | K21: 0 | L21: 62405
B22: Government Securites | C22: {='[1]APPENDIX 6 II'!$C22:$L22} -> 579677.76 | D22: 2271685.2 | E22: 894337.56 | F22: 6952214.2 | G22: 1499057.7 | H22: 1549804 | I22: 5803650.9 | J22: 610675.02 | K22: 0 | L22: 3627473
B23: Other Securites | C23: {='[1]APPENDIX 6 II'!$C23:$L23} -> 0 | D23: 0 | E23: 0 | F23: 0 | G23: 0 | H23: 0 | I23: 83715.186 | J23: 0 | K23: 0 | L23: 0
B24: Investment in Related Parties | C24: {='[1]APPENDIX 6 II'!$C24:$L24} -> 0 | D24: 13707.035 | E24: 0 | F24: 1080779.4 | G24: 0 | H24: 0 | I24: 564243.2 | J24: 0 | K24: 0 | L24: 0
B25: Corporate Bonds | C25: {='[1]APPENDIX 6 II'!$C25:$L25} -> 0 | D25: 4499.2115 | E25: 0 | F25: 0 | G25: 10000 | H25: 0 | I25: 58124.136 | J25: 0 | K25: 0 | L25: 0
B26: Commercial Papers | C26: {='[1]APPENDIX 6 II'!$C26:$L26} -> 0 | D26: 0 | E26: 0 | F26: 0 | G26: 8115.699 | H26: 0 | I26: 0 | J26: 0 | K26: 0 | L26: 0
B27: Debentures | C27: {='[1]APPENDIX 6 II'!$C27:$L27} -> 0 | D27: 0 | E27: 0 | F27: 0 | G27: 0 | H27: 0 | I27: 0 | J27: 0 | K27: 0 | L27: 0
B28: Ordinary Shares Quoted | C28: {='[1]APPENDIX 6 II'!$C28:$L28} -> 0 | D28: 42124 | E28: 0 | F28: 501993.34 | G28: 56237.222 | H28: 0 | I28: 732046.1 | J28: 0 | K28: 0 | L28: 0
B29: Ordinary Shares Unquoted | C29: {='[1]APPENDIX 6 II'!$C29:$L29} -> 0 | D29: 0 | E29: 0 | F29: 507149.1 | G29: 6266.403 | H29: 0 | I29: 0 | J29: 0 | K29: 0 | L29: 0
... B39: Other Assets | C39: {='[1]APPENDIX 6 II'!$C39:$L39} -> 231.49 | D39: 591312.91 | E39: 1046608.4 | F39: 295203.16 | G39: 422161.34 | H39: 259464.9 | I39: 1027535.1 | J39: 56579.098 | K39: 0 | L39: 2204700.8
B40: Total Assets | C40: 880961.62 | D40: 5775529.2 | E40: 7670450.4 | F40: 27679699 | G40: 6739716.9 | H40: 3175982.4 | I40: 16891179 | J40: 2867929.2 | K40: 0 | L40: 10697635
B41: Amounts in thousand Shillings | K41: Continued next page

Sheet APPENDIX 6 III
B2: Continued from previous page
B3: =_xlfn.CONCAT(INDEX(_xlfn.TEXTSPLIT(Contents!E22," III"),1),": ",UPPER(Contents!F22)) -> APPENDIX 6: SUMMARY OF GENERAL INSURANCE BUSINESS BALANCE SHEETS AS AT 31.12.2024
B4: Company | C4: JUBILEE HEALTH INSURANCE | D4: KENINDIA ASSURANCE COMPANY | E4: KENYA ORIENT INSURANCE | F4: KENYA REINSURANCE CORPORATION | G4: MADISON INSURANCE COMPANY | H4: MAYFAIR INSURANCE COMPANY | I4: MUA INSURANCE COMPANY | J4: NCBA INSURANCE COMPANY | K4: OCCIDENTAL INSURANCE COMPANY | L4: OLD MUTUAL GENERAL INSURANCE | M4: PACIS INSURANCE COMPANY
B5: Share Captial | C5: {='[1]APPENDIX 6 III'!$C5:$M5} -> 2763720 | D5: 600000 | E5: 810721.06 | F5: 13498981 | G5: 605000 | H5: 1500000 | I5: 600000 | J5: 600000 | K5: 745831 | L5: 1000000 | M5: 688553.91
B6: Share Premium | C6: {='[1]APPENDIX 6 III'!$C6:$M6} -> 0 | D6: 1198.295 | E6: 0 | F6: 0 | G6: 0 | H6: 0 | I6: 0 | J6: 0 | K6: 100378.9 | L6: 0 | M6: 5712
B7: Revaluation Reserve | C7: {='[1]APPENDIX 6 III'!$C7:$M7} -> -54909.117 | D7: 456053 | E7: 356.34275 | F7: 36911.31 | G7: 0 | H7: -60349.069 | I7: -11645.963 | J7: -15561.17 | K7: 0 | L7: 0 | M7: 0
B8: Other Equity | C8: {='[1]APPENDIX 6 III'!$C8:$M8} -> 0 | D8: 441589.77 | E8: 0 | F8: -109502.9 | G8: 0 | H8: 114391.13 | I8: 1215327.8 | J8: 150000 | K8: 150000 | L8: 0 | M8: -10047.931
B9: Retained Earnings | C9: {='[1]APPENDIX 6 III'!$C9:$M9} -> 2426232.2 | D9: 3191406.6 | E9: -3411709.3 | F9: 22977078 | G9: -588221.76 | H9: 3055804 | I9: -1753388.5 | J9: 1484930 | K9: -397843.32 | L9: 6013678.5 | M9: 275337.38
B10: Other Reserves | C10: {='[1]APPENDIX 6 III'!$C10:$M10} -> 0 | D10: 0 | E10: 1534217.3 | F10: 1523664.8 | G10: 824886.44 | H10: 920001 | I10: 0 | J10: 0 | K10: 0 | L10: 0 | M10: 24798.639
B11: Total Equity_x000D_ | C11: 5135043.1 | D11: 4690247.6 | E11: -1066414.6 | F11: 37927133 | G11: 841664.69 | H11: 5529847 | I11: 50293.321 | J11: 2219368.8 | K11: 598366.58 | L11: 7013678.5 | M11: 984354
B12: Insurance Contract Liabilites | C12: {='[1]APPENDIX 6 III'!$C12:$M12} -> 4564463.6 | D12: 6169771.1 | E12: 2973008.7 | F12: 9053304.5 | G12: 6759771 | H12: 6648412.9 | I12: 2368144.9 | J12: 2151016.2 | K12: 1926199.6 | L12: 10442443 | M12: 2710680.9
B13: Reinsurance Contract Liabilites | C13: {='[1]APPENDIX 6 III'!$C13:$M13} -> 0 | D13: 0 | E13: 0 | F13: 881551.27 | G13: 0 | H13: 0 | I13: 0 | J13: 62469.21 | K13: 0 | L13: 144994.73 | M13: 0
B14: Long-Term Liabilites | C14: {='[1]APPENDIX 6 III'!$C14:$M14} -> 0 | D14: 54306.604 | E14: 0 | F14: 1419534.4 | G14: 0 | H14: 126893.87 | I14: 0 | J14: 0 | K14: 0 | L14: 0 | M14: 37385.016
B15: Short-Term Liabilites | C15: {='[1]APPENDIX 6 III'!$C15:$M15} -> 72000.611 | D15: 186887.6 | E15: 550651.36 | F15: 786700 | G15: 137872.22 | H15: 1944308.8 | I15: 684751.08 | J15: 483025 | K15: 452844.12 | L15: 0 | M15: 185325.01
B16: Other Liabilites | C16: {='[1]APPENDIX 6 III'!$C16:$M16} -> 1594431.4 | D16: 21949.912 | E16: 87565.357 | F16: 292842.6 | G16: 31300.387 | H16: 43632.317 | I16: 66682.38 | J16: 225252 | K16: 135735.31 | L16: 1495962.2 | M16: 51446.53
B17: Total Equity And Liabilities | C17: 11365939 | D17: 11123163 | E17: 2544810.8 | F17: 50361066 | G17: 7770608.3 | H17: 14293095 | I17: 3169871.7 | J17: 5141131.3 | K17: 3113145.6 | L17: 19097079 | M17: 3969191.4
B18: Intangible Assets | C18: {='[1]APPENDIX 6 III'!$C18:$M18} -> 112389.53 | D18: 5120.195 | E18: 3817.8571 | F18: 46280.038 | G18: 91441.691 | H18: 15342.135 | I18: 16124.992 | J18: 335032.02 | K18: 0 | L18: 76543.697 | M18: 344.476
B19: Land and Buildings | C19: {='[1]APPENDIX 6 III'!$C19:$M19} -> 0 | D19: 799971.73 | E19: 108000 | F19: 0 | G19: 0 | H19: 206928.42 | I19: 0 | J19: 0 | K19: 0 | L19: 0 | M19: 112832.2
B20: Investment Property | C20: {='[1]APPENDIX 6 III'!$C20:$M20} -> 0 | D20: 1294600 | E20: 892000 | F20: 11171625 | G20: 703932.3 | H20: 403571.58 | I20: 0 | J20: 0 | K20: 440000 | L20: 3128000 | M20: 712167.8
B21: Fixed Assets | C21: {='[1]APPENDIX 6 III'!$C21:$M21} -> 83399.802 | D21: 48346.59 | E21: 11688.456 | F21: 34087.529 | G21: 32404.845 | H21: 83467.692 | I21: 41517.645 | J21: 104951 | K21: 13694.626 | L21: 91062.479 | M21: 24597.33
B22: Government Securites | C22: {='[1]APPENDIX 6 III'!$C22:$M22} -> 5043371.5 | D22: 3752509.7 | E22: 152792.62 | F22: 17489365 | G22: 2067463.9 | H22: 3820994.4 | I22: 1025480 | J22: 2108508.9 | K22: 700841.37 | L22: 9363919.3 | M22: 289033.03
B23: Other Securites | C23: {='[1]APPENDIX 6 III'!$C23:$M23} -> 0 | D23: 0 | E23: 0 | F23: 0 | G23: 1251.36 | H23: 0 | I23: 0 | J23: 0 | K23: 8364.035 | L23: 0 | M23: 0
B24: Investment in Related Parties | C24: 1844431.4 | D24: 105611.8 | E24: 124000 | F24: 11922932 | G24: 0 | H24: 1693723.4 | I24: 109127.35 | J24: 0 | K24: 0 | L24: 0 | M24: 0
B25: Corporate Bonds | C25: 0 | D25: 0 | E25: 0 | F25: 44819.627 | G25: 0 | H25: 26757.311 | I25: 0 | J25: 0 | K25: 14469.178 | L25: 49997.508 | M25: 0
B26: Commercial Papers | C26: 0 | D26: 0 | E26: 0 | F26: 0 | G26: 0 | H26: 0 | I26: 0 | J26: 0 | K26: 0 | L26: 0 | M26: 0
B27: Debentures | C27: 0 | D27: 0 | E27: 0 | F27: 0 | G27: 0 | H27: 0 | I27: 0 | J27: 0 | K27: 0 | L27: 0 | M27: 0
B28: Ordinary Shares Quoted | C28: 276728.43 | D28: 45819.703 | E28: 5298.9 | F28: 1194186 | G28: 6490.935 | H28: 112941.92 | I28: 61163.217 | J28: 0 | K28: 0 | L28: 26400.642 | M28: 0
B29: Ordinary Shares Unquoted | C29: 747882.02 | D29: 775846.16 | E29: 232339.99 | F29: 603113.15 | G29: 545708.95 | H29: 153358.34 | I29: 0 | J29: 0 | K29: 0 | L29: 159816.12 | M29: 0
B30: Preference Shares Quoted | C30: 402.1 | D30: 0 | E30: 0 | F30: 64.624 | G30: 0 | H30: 0 | I30: 0 | J30: 0 | K30: 0 | L30: 0 | M30: 0
B31: Preference Shares Unquoted | C31: 0 | D31: 0 | E31: 0 | F31: 0 | G31: 0 | H31: 0 | I31: 0 | J31: 0 | K31: 0 | L31: 0 | M31: 0
B32: Loans Secured and Unsecured | C32: 0 | D32: 18309.515 | E32: 0 | F32: 0 | G32: 1230368.6 | H32: 38550.875 | I32: 440.72619 | J32: 5989.1468 | K32: 0 | L32: 0 | M32: 0
B33: Mortgages | C33: 31000 | D33: 0 | E33: 0 | F33: 815526.9 | G33: 0 | H33: 0 | I33: 0 | J33: 0 | K33: 0 | L33: 87673.274 | M33: 0
B34: Term Deposits | C34: 1877338.1 | D34: 347676.16 | E34: 24938.793 | F34: 5397438.2 | G34: 446989.62 | H34: 2371655.5 | I34: 815256.68 | J34: 129020 | K34: 70706.097 | L34: 2382233.6 | M34: 404324.96
B35: Cash and Cash Balances | C35: 99105.749 | D35: 27084.6 | E35: 22346.195 | F35: 173728.33 | G35: 131123.26 | H35: 1620269.2 | I35: 218261.4 | J35: 128583.5 | K35: 117718.45 | L35: 331096.14 | M35: 231493.33
... B40: Total Assets | C40: 11365939 | D40: 11123163 | E40: 2544810.8 | F40: 50361066 | G40: 7770608.3 | H40: 14293095 | I40: 3169871.7 | J40: 5141131.3 | K40: 3113145.6 | L40: 19097079 | M40: 3969191.4
B41: Amounts in thousand Shillings | J41: Continued next page

Sheet APPENDIX 6 IV
B2: Continued from previous page
B3: =_xlfn.CONCAT(INDEX(_xlfn.TEXTSPLIT(Contents!E23," IV"),1),": ",UPPER(Contents!F23)) -> APPENDIX 6: SUMMARY OF GENERAL INSURANCE BUSINESS BALANCE SHEETS AS AT 31.12.2024
B4: Company | C4: PIONEER INSURANCE COMPANY | D4: SANLAM INSURANCE COMPANY | E4: STAR DISCOVER INSURANCE | F4: TAKAFUL INSURANCE OF AFRICA | G4: TAUSI ASSURANCE COMPANY | H4: THE HERITAGE INSURANCE COMPANY | I4: THE KENYAN ALLIANCE INSURANCE | J4: THE MONARCH INSURANCE | K4: TRIDENT INSURANCE COMPANY | L4: WAICA REINSURANCE KENYA LIMITED | M4: TOTAL | P4: Insurers | Q4: Reinsurers
B5: Share Captial | C5: {='[1]APPENDIX 6 IV'!$C5:$M5} -> 700000 | D5: 1028998.1 | E5: 600000 | F5: 566304.27 | G5: 600000 | H5: 1000000 | I5: 600000 | J5: 497024.16 | K5: 0 | L5: 1102550 | M5: 50492396 | P5: =M5-Q5 -> 32890865 | Q5: ='APPENDIX 6 I'!I5+'APPENDIX 6 I'!L5+'APPENDIX 6 II'!H5+'APPENDIX 6 III'!F5+'APPENDIX 6 IV'!L5 -> 17601531
B6: Share Premium | C6: {='[1]APPENDIX 6 IV'!$C6:$M6} -> 0 | D6: 100361.29 | E6: 0 | F6: 146101 | G6: 0 | H6: 0 | I6: 0 | J6: 0 | K6: 0 | L6: 0 | M6: 3320220.8 | P6: =M6-Q6 -> 3309349.5 | Q6: ='APPENDIX 6 I'!I6+'APPENDIX 6 I'!L6+'APPENDIX 6 II'!H6+'APPENDIX 6 III'!F6+'APPENDIX 6 IV'!L6 -> 10871.242
B7: Revaluation Reserve | C7: {='[1]APPENDIX 6 IV'!$C7:$M7} -> 0 | D7: 0 | E7: 0 | F7: 25539.216 | G7: 181909.03 | H7: 0 | I7: 128382 | J7: 0 | K7: 0 | L7: 0 | M7: 2724565.3 | P7: =M7-Q7 -> 2466109 | Q7: ='APPENDIX 6 I'!I7+'APPENDIX 6 I'!L7+'APPENDIX 6 II'!H7+'APPENDIX 6 III'!F7+'APPENDIX 6 IV'!L7 -> 258456.3
B8: Other Equity | C8: {='[1]APPENDIX 6 IV'!$C8:$M8} -> 50015 | D8: 1174527.6 | E8: 0 | F8: 0 | G8: 157850.3 | H8: 0 | I8: 0 | J8: 0 | K8: 0 | L8: 0 | M8: 3611128.4 | P8: =M8-Q8 -> 3719966.6 | Q8: ='APPENDIX 6 I'!I8+'APPENDIX 6 I'!L8+'APPENDIX 6 II'!H8+'APPENDIX 6 III'!F8+'APPENDIX 6 IV'!L8 -> -108838.17
B9: Retained Earnings | C9: {='[1]APPENDIX 6 IV'!$C9:$M9} -> 88882.707 | D9: -598581.08 | E9: -24591.595 | F9: -321233.73 | G9: 1756386.5 | H9: 4923814.4 | I9: -1213509.1 | J9: -1552867.6 | K9: 0 | L9: 1564445.4 | M9: 68937161 | P9: =M9-Q9 -> 37009718 | Q9: ='APPENDIX 6 I'!I9+'APPENDIX 6 I'!L9+'APPENDIX 6 II'!H9+'APPENDIX 6 III'!F9+'APPENDIX 6 IV'!L9 -> 31927443
B10: Other Reserves | C10: {='[1]APPENDIX 6 IV'!$C10:$M10} -> 1031184.4 | D10: 0 | E10: 0 | F10: 0 | G10: 0 | H10: 0 | I10: -15557.495 | J10: 0 | K10: 0 | L10: 0 | M10: 6772522.3 | P10: =M10-Q10 -> 5325049.6 | Q10: ='APPENDIX 6 I'!I10+'APPENDIX 6 I'!L10+'APPENDIX 6 II'!H10+'APPENDIX 6 III'!F10+'APPENDIX 6 IV'!L10 -> 1447472.7
B11: Total Equity_x000D_ | C11: 1870082.1 | D11: 1705306 | E11: 575408.4 | F11: 416710.76 | G11: 2696145.8 | H11: 5923814.4 | I11: -500684.59 | J11: -1055843.9 | K11: 0 | L11: 2666995.4 | M11: =SUM('APPENDIX 6 I'!C11:L11,'APPENDIX 6 II'!C11:L11,'APPENDIX 6 III'!C11:M11,'APPENDIX 6 IV'!C11:L11) -> 1.3585799e+08 | P11: =M11-Q11 -> 84721057 | Q11: ='APPENDIX 6 I'!I11+'APPENDIX 6 I'!L11+'APPENDIX 6 II'!H11+'APPENDIX 6 III'!F11+'APPENDIX 6 IV'!L11 -> 51136937
B12: Insurance Contract Liabilites | C12: {='[1]APPENDIX 6 IV'!$C12:$M12} -> 1623201.3 | D12: 2622807.9 | E12: 481450.64 | F12: 773652.06 | G12: 1368185.3 | H12: 5985121.6 | I12: 1362497.4 | J12: 2070223.9 | K12: 0 | L12: 1718835.2 | M12: 1.8128369e+08 | P12: =M12-Q12 -> 1.6055163e+08 | Q12: ='APPENDIX 6 I'!I12+'APPENDIX 6 I'!L12+'APPENDIX 6 II'!H12+'APPENDIX 6 III'!F12+'APPENDIX 6 IV'!L12 -> 20732061
B13: Reinsurance Contract Liabilites | C13: {='[1]APPENDIX 6 IV'!$C13:$M13} -> 0 | D13: 118797.38 | E13: 0 | F13: 383.72446 | G13: 0 | H13: 186854.49 | I13: 0 | J13: 0 | K13: 0 | L13: 856029.91 | M13: 5345324.3 | P13: =M13-Q13 -> 3444539.6 | Q13: ='APPENDIX 6 I'!I13+'APPENDIX 6 I'!L13+'APPENDIX 6 II'!H13+'APPENDIX 6 III'!F13+'APPENDIX 6 IV'!L13 -> 1900784.7
B14: Long-Term Liabilites | C14: {='[1]APPENDIX 6 IV'!$C14:$M14} -> 0 | D14: 0 | E14: 6698.4815 | F14: 11988 | G14: 79731.373 | H14: 0 | I14: 238649.44 | J14: 532978.82 | K14: 0 | L14: 0 | M14: 3485051.1 | P14: =M14-Q14 -> 2005805.1 | Q14: ='APPENDIX 6 I'!I14+'APPENDIX 6 I'!L14+'APPENDIX 6 II'!H14+'APPENDIX 6 III'!F14+'APPENDIX 6 IV'!L14 -> 1479246
B15: Short-Term Liabilites | C15: {='[1]APPENDIX 6 IV'!$C15:$M15} -> 220421.52 | D15: 172835.68 | E15: 129951.76 | F15: 39013.656 | G15: 72193.015 | H15: 812580.43 | I15: 1511201.5 | J15: 546836.84 | K15: 0 | L15: 88508.313 | M15: 16192984 | P15: =M15-Q15 -> 15214385 | Q15: ='APPENDIX 6 I'!I15+'APPENDIX 6 I'!L15+'APPENDIX 6 II'!H15+'APPENDIX 6 III'!F15+'APPENDIX 6 IV'!L15 -> 978598.94
B16: Other Liabilites | C16: {='[1]APPENDIX 6 IV'!$C16:$M16} -> 31599.614 | D16: 117329.69 | E16: 145663.43 | F16: 64264.682 | G16: 6159.743 | H16: 265628.65 | I16: 67635.994 | J16: 25274.254 | K16: 0 | L16: 183708.3 | M16: 8608464.8 | P16: =M16-Q16 -> 7587291.7 | Q16: ='APPENDIX 6 I'!I16+'APPENDIX 6 I'!L16+'APPENDIX 6 II'!H16+'APPENDIX 6 III'!F16+'APPENDIX 6 IV'!L16 -> 1021173.1
B17: Total Equity And Liabilities | C17: 3745304.6 | D17: 4737076.6 | E17: 1339172.7 | F17: 1306012.9 | G17: 4222415.2 | H17: 13174000 | I17: 2679299.8 | J17: 2119470.4 | K17: 0 | L17: 5514077.1 | M17: =SUM('APPENDIX 6 I'!C17:L17,'APPENDIX 6 II'!C17:L17,'APPENDIX 6 III'!C17:M17,'APPENDIX 6 IV'!C17:L17) -> 3.5077351e+08 | P17: =M17-Q17 -> 2.735247e+08 | Q17: ='APPENDIX 6 I'!I17+'APPENDIX 6 I'!L17+'APPENDIX 6 II'!H17+'APPENDIX 6 III'!F17+'APPENDIX 6 IV'!L17 -> 77248801
B18: Intangible Assets | C18: {='[1]APPENDIX 6 IV'!$C18:$M18} -> 12328.553 | D18: 1087.984 | E18: 34591.034 | F18: 20318 | G18: 26389.014 | H18: 75604.609 | I18: 1984.8631 | J18: 7862.792 | K18: 0 | L18: 176.189 | M18: 1390359.1 | P18: =M18-Q18 -> 1341239.5 | Q18: ='APPENDIX 6 I'!I18+'APPENDIX 6 I'!L18+'APPENDIX 6 II'!H18+'APPENDIX 6 III'!F18+'APPENDIX 6 IV'!L18 -> 49119.567
B19: Land and Buildings | C19: {='[1]APPENDIX 6 IV'!$C19:$M19} -> 0 | D19: 0 | E19: 0 | F19: 0 | G19: 307248.63 | H19: 0 | I19: 218800 | J19: 0 | K19: 0 | L19: 0 | M19: 5643626.7 | P19: =M19-Q19 -> 5227873.1 | Q19: ='APPENDIX 6 I'!I19+'APPENDIX 6 I'!L19+'APPENDIX 6 II'!H19+'APPENDIX 6 III'!F19+'APPENDIX 6 IV'!L19 -> 415753.62
B20: Investment Property | C20: {='[1]APPENDIX 6 IV'!$C20:$M20} -> 446000 | D20: 47000 | E20: 0 | F20: 30000 | G20: 0 | H20: 0 | I20: 461400 | J20: 753279.48 | K20: 0 | L20: 0 | M20: 35945287 | P20: =M20-Q20 -> 24038662 | Q20: ='APPENDIX 6 I'!I20+'APPENDIX 6 I'!L20+'APPENDIX 6 II'!H20+'APPENDIX 6 III'!F20+'APPENDIX 6 IV'!L20 -> 11906625
B21: Fixed Assets | C21: {='[1]APPENDIX 6 IV'!$C21:$M21} -> 15363.485 | D21: 29229.297 | E21: 11309.084 | F21: 23273.651 | G21: 37846.329 | H21: 67431.351 | I21: 110230.65 | J21: 38037.246 | K21: 0 | L21: 44479.522 | M21: 1919521.1 | P21: =M21-Q21 -> 1776124.4 | Q21: ='APPENDIX 6 I'!I21+'APPENDIX 6 I'!L21+'APPENDIX 6 II'!H21+'APPENDIX 6 III'!F21+'APPENDIX 6 IV'!L21 -> 143396.76
B22: Government Securites | C22: {='[1]APPENDIX 6 IV'!$C22:$M22} -> 893844.38 | D22: 2734168.4 | E22: 817160.25 | F22: 51014 | G22: 2250722 | H22: 6458070.7 | I22: 333209 | J22: 56365.779 | K22: 0 | L22: 1100639.8 | M22: 1.2621533e+08 | P22: =M22-Q22 -> 99522549 | Q22: ='APPENDIX 6 I'!I22+'APPENDIX 6 I'!L22+'APPENDIX 6 II'!H22+'APPENDIX 6 III'!F22+'APPENDIX 6 IV'!L22 -> 26692780
B23: Other Securites | C23: {='[1]APPENDIX 6 IV'!$C23:$M23} -> 0 | D23: 0 | E23: 0 | F23: 93080 | G23: 5387.0972 | H23: 0 | I23: 0 | J23: 0 | K23: 0 | L23: 521445.22 | M23: 1296270.1 | P23: =M23-Q23 -> 593416.08 | Q23: ='APPENDIX 6 I'!I23+'APPENDIX 6 I'!L23+'APPENDIX 6 II'!H23+'APPENDIX 6 III'!F23+'APPENDIX 6 IV'!L23 -> 702854.02
B24: Investment in Related Parties | C24: {='[1]APPENDIX 6 IV'!$C24:$M24} -> 0 | D24: 0 | E24: 0 | F24: 0 | G24: 0 | H24: 146556.57 | I24: 0 | J24: 0 | K24: 0 | L24: 0 | M24: 19193022 | P24: =M24-Q24 -> 6625238 | Q24: ='APPENDIX 6 I'!I24+'APPENDIX 6 I'!L24+'APPENDIX 6 II'!H24+'APPENDIX 6 III'!F24+'APPENDIX 6 IV'!L24 -> 12567784
B25: Corporate Bonds | C25: {='[1]APPENDIX 6 IV'!$C25:$M25} -> 0 | D25: 0 | E25: 0 | F25: 0 | G25: 0 | H25: 0 | I25: 0 | J25: 0 | K25: 0 | L25: 0 | M25: 213680.81 | P25: =M25-Q25 -> 168861.19 | Q25: ='APPENDIX 6 I'!I25+'APPENDIX 6 I'!L25+'APPENDIX 6 II'!H25+'APPENDIX 6 III'!F25+'APPENDIX 6 IV'!L25 -> 44819.627
B26: Commercial Papers | C26: {='[1]APPENDIX 6 IV'!$C26:$M26} -> 0 | D26: 0 | E26: 0 | F26: 0 | G26: 0 | H26: 0 | I26: 0 | J26: 0 | K26: 0 | L26: 0 | M26: 8115.699 | P26: =M26-Q26 -> 8115.699 | Q26: ='APPENDIX 6 I'!I26+'APPENDIX 6 I'!L26+'APPENDIX 6 II'!H26+'APPENDIX 6 III'!F26+'APPENDIX 6 IV'!L26 -> 0
B27: Debentures | C27: {='[1]APPENDIX 6 IV'!$C27:$M27} -> 0 | D27: 0 | E27: 0 | F27: 0 | G27: 0 | H27: 0 | I27: 357021.47 | J27: 0 | K27: 0 | L27: 0 | M27: 357021.47 | P27: =M27-Q27 -> 357021.47 | Q27: ='APPENDIX 6 I'!I27+'APPENDIX 6 I'!L27+'APPENDIX 6 II'!H27+'APPENDIX 6 III'!F27+'APPENDIX 6 IV'!L27 -> 0
B28: Ordinary Shares Quoted | C28: {='[1]APPENDIX 6 IV'!$C28:$M28} -> 0 | D28: 0 | E28: 0 | F28: 0 | G28: 191126.6 | H28: 0 | I28: 7999.3864 | J28: 0 | K28: 0 | L28: 0 | M28: 4415831.8 | P28: =M28-Q28 -> 3203340.8 | Q28: ='APPENDIX 6 I'!I28+'APPENDIX 6 I'!L28+'APPENDIX 6 II'!H28+'APPENDIX 6 III'!F28+'APPENDIX 6 IV'!L28 -> 1212491
B29: Ordinary Shares Unquoted | C29: {='[1]APPENDIX 6 IV'!$C29:$M29} -> 1249906.3 | D29: 0 | E29: 0 | F29: 0 | G29: 2176.755 | H29: 0 | I29: 0 | J29: 0 | K29: 0 | L29: 0 | M29: 5023433.8 | P29: =M29-Q29 -> 4420320.6 | Q29: ='APPENDIX 6 I'!I29+'APPENDIX 6 I'!L29+'APPENDIX 6 II'!H29+'APPENDIX 6 III'!F29+'APPENDIX 6 IV'!L29 -> 603113.15
... B39: Other Assets | C39: {='[1]APPENDIX 6 IV'!$C39:$M39} -> 124479.1 | D39: 185158.66 | E39: 6762.993 | F39: 152760.61 | G39: 138294.62 | H39: 53188.129 | I39: 367786.51 | J39: 613396.67 | K39: 0 | L39: 204708.18 | M39: 20794215 | P39: =M39-Q39 -> 19088011 | Q39: ='APPENDIX 6 I'!I39+'APPENDIX 6 I'!L39+'APPENDIX 6 II'!H39+'APPENDIX 6 III'!F39+'APPENDIX 6 IV'!L39 -> 1706203.6
B40: Total Assets | C40: 3745304.6 | D40: 4737076.6 | E40: 1339172.7 | F40: 1306012.9 | G40: 4222415.2 | H40: 13174000 | I40: 2679299.8 | J40: 2119470.4 | K40: 0 | L40: 5514077.1 | M40: =SUM('APPENDIX 6 I'!C40:L40,'APPENDIX 6 II'!C40:L40,'APPENDIX 6 III'!C40:M40,'APPENDIX 6 IV'!C40:L40) -> 3.5077351e+08 | P40: =M40-Q40 -> 2.735247e+08 | Q40: ='APPENDIX 6 I'!I40+'APPENDIX 6 I'!L40+'APPENDIX 6 II'!H40+'APPENDIX 6 III'!F40+'APPENDIX 6 IV'!L40 -> 77248801
B41: Amounts in thousand Shillings
O43: Total Assets | P43: =P40 -> 2.735247e+08 | Q43: =Q40 -> 77248801
N44: =N40-N17 -> 0 | O44: =O40-O17 -> 0 | P44: =P40-P17 -> 0.0005428791 | Q44: =Q40-Q17 -> -0.00050780177

Sheet APPENDIX 7
B3: =_xlfn.CONCAT(Contents!E24,": ",UPPER(Contents!F24)) -> APPENDIX 7: SUMMARY OF MICROINSURANCE BUSINESS BALANCE SHEETS AS AT 31.12.2024
B4: Company | C4: STAR DISCOVER MICRO INSURANCE | D4: TURACO MICROINSURANCE | E4: TOTAL
B5: Share Captial | C5: {='[1]APPENDIX 7'!$C5:$E5} -> 100000 | D5: 50000 | E5: 150000
B6: Share Premium | C6: {='[1]APPENDIX 7'!$C6:$E6} -> 0 | D6: 0 | E6: 0
B7: Revaluation Reserve | C7: {='[1]APPENDIX 7'!$C7:$E7} -> 0 | D7: 0 | E7: 0
B8: Other Equity | C8: {='[1]APPENDIX 7'!$C8:$E8} -> 0 | D8: 0 | E8: 0
B9: Retained Earnings | C9: {='[1]APPENDIX 7'!$C9:$E9} -> -37846.352 | D9: 3153.3695 | E9: -34692.982
B10: Other Reserves | C10: {='[1]APPENDIX 7'!$C10:$E10} -> 0 | D10: 0 | E10: 0
B11: Total Equity | C11: 62153.648 | D11: 53153.369 | E11: 115307.02
B12: Insurance Contract Liabilites | C12: {='[1]APPENDIX 7'!$C12:$E12} -> 17609.185 | D12: 22201.804 | E12: 39810.989
B13: Reinsurance Contract Liabilites | C13: {='[1]APPENDIX 7'!$C13:$E13} -> 0 | D13: 0 | E13: 0
B14: Long-Term Liabilites | C14: {='[1]APPENDIX 7'!$C14:$E14} -> 0 | D14: 3246.755 | E14: 3246.755
B15: Short-Term Liabilites | C15: {='[1]APPENDIX 7'!$C15:$E15} -> 35180.34 | D15: 115572.68 | E15: 150753.02
B16: Other Liabilites | C16: {='[1]APPENDIX 7'!$C16:$E16} -> 28430.751 | D16: 11713.671 | E16: 40144.422
B17: Total Equity and Liabilites | C17: 143373.92 | D17: 205888.28 | E17: 349262.21
B18: Intangible Assets | C18: {='[1]APPENDIX 7'!$C18:$E18} -> 15909 | D18: 0 | E18: 15909
B19: Land and Buildings | C19: {='[1]APPENDIX 7'!$C19:$E19} -> 0 | D19: 0 | E19: 0
B20: Investment Property | C20: {='[1]APPENDIX 7'!$C20:$E20} -> 0 | D20: 0 | E20: 0
B21: Fixed Assets | C21: {='[1]APPENDIX 7'!$C21:$E21} -> 2130.808 | D21: 0 | E21: 2130.808
B22: Government Securites | C22: {='[1]APPENDIX 7'!$C22:$E22} -> 56531.493 | D22: 49139.711 | E22: 105671.2
B23: Other Securites | C23: {='[1]APPENDIX 7'!$C23:$E23} -> 0 | D23: 0 | E23: 0
B24: Investment in Related Parties | C24: {='[1]APPENDIX 7'!$C24:$E24} -> 0 | D24: 0 | E24: 0
B25: Corporate Bonds | C25: {='[1]APPENDIX 7'!$C25:$E25} -> 0 | D25: 0 | E25: 0
B26: Commercial Papers | C26: {='[1]APPENDIX 7'!$C26:$E26} -> 0 | D26: 0 | E26: 0
B27: Debentures | C27: {='[1]APPENDIX 7'!$C27:$E27} -> 0 | D27: 0 | E27: 0
B28: Ordinary Shares Quoted | C28: {='[1]APPENDIX 7'!$C28:$E28} -> 0 | D28: 0 | E28: 0
B29: Ordinary Shares Unquoted | C29: {='[1]APPENDIX 7'!$C29:$E29} -> 0 | D29: 0 | E29: 0
... B39: Other Assets | C39: {='[1]APPENDIX 7'!$C39:$E39} -> 22911.017 | D39: 6227.14 | E39: 29138.157
B40: Total Assets | C40: 143373.92 | D40: 205888.28 | E40: 349262.21
B41: Amounts in thousand Shillings

Sheet APPENDIX 8
B3: =_xlfn.CONCAT(Contents!E25,": ",UPPER(Contents!F25)) -> APPENDIX 8: SUMMARY OF LONG TERM BUSINESS GROSS DIRECT PREMIUMS FOR THE YEAR ENDED 31.12.2024
B4: Company | C4: Life Assurances | D4: Annuities | E4: Deposit Administration | F4: Personal Pensions | G4: Group Life | H4: Group Credit | I4: Permanent Health | J4: Investments | K4: Total | L4: Market Share (%)
B5: INSURERS
B6: ABSA LIFE ASSURANCE | C6: {='[1]APPENDIX 8'!$C6:$J6} -> 4885789.6 | D6: 0 | E6: 0 | F6: 0 | G6: 3056103.8 | H6: 522285.84 | I6: 0 | J6: 0 | K6: =SUM(C6:J6) -> 8464179.2 | L6: =K6/$K$31*100 -> 4.4130536
B7: APA LIFE ASSURANCE COMPANY | C7: {='[1]APPENDIX 8'!$C7:$J7} -> 486359 | D7: 74357.726 | E7: 1474001.5 | F7: 0 | G7: 1831606.7 | H7: 1091794.8 | I7: 0 | J7: 933309.69 | K7: =SUM(C7:J7) -> 5891429.4 | L7: =K7/$K$31*100 -> 3.0716733
B8: BRITAM LIFE ASSURANCE | C8: {='[1]APPENDIX 8'!$C8:$J8} -> 11592507 | D8: 6901846.1 | E8: 7112670.9 | F8: 4922405.8 | G8: 6250268.2 | H8: 299440.25 | I8: 0 | J8: 4947421.3 | K8: =SUM(C8:J8) -> 42026559 | L8: =K8/$K$31*100 -> 21.911806
B9: CANNON LIFE ASSURANCE (K) LIMITED | C9: {='[1]APPENDIX 8'!$C9:$J9} -> 27657.387 | D9: 0 | E9: 0 | F9: 0 | G9: 383545.16 | H9: 9555.2 | I9: 0 | J9: 0 | K9: =SUM(C9:J9) -> 420757.75 | L9: =K9/$K$31*100 -> 0.21937467
B10: CAPEX LIFE ASSURANCE COMPANY | C10: {='[1]APPENDIX 8'!$C10:$J10} -> 5981.2511 | D10: 324925.1 | E10: 0 | F10: 0 | G10: 1198881.9 | H10: 80776.741 | I10: 0 | J10: 0 | K10: =SUM(C10:J10) -> 1610565 | L10: =K10/$K$31*100 -> 0.83971634
B11: CIC LIFE ASSURANCE COMPANY | C11: {='[1]APPENDIX 8'!$C11:$J11} -> 1279963.5 | D11: 354526.11 | E11: 4569003.3 | F11: 0 | G11: 1261374.5 | H11: 5220507.4 | I11: 0 | J11: 0 | K11: =SUM(C11:J11) -> 12685375 | L11: =K11/$K$31*100 -> 6.6139004
B12: CORPORATE INSURANCE COMPANY | C12: {='[1]APPENDIX 8'!$C12:$J12} -> 49368.199 | D12: 0 | E12: 0 | F12: 0 | G12: 0 | H12: 0 | I12: 0 | J12: 0 | K12: =SUM(C12:J12) -> 49368.199 | L12: =K12/$K$31*100 -> 0.025739591
B13: EQUITY LIFE ASSURANCE | C13: {='[1]APPENDIX 8'!$C13:$J13} -> 0 | D13: 0 | E13: 1607623.1 | F13: 297501.74 | G13: 428316.15 | H13: 2310958.7 | I13: 0 | J13: -177476.25 | K13: =SUM(C13:J13) -> 4466923.4 | L13: =K13/$K$31*100 -> 2.3289644
B14: GA LIFE ASSURANCE COMPANY | C14: {='[1]APPENDIX 8'!$C14:$J14} -> 466960.01 | D14: 0 | E14: 5949888.1 | F14: 1124579.5 | G14: 88965.034 | H14: 3367.8619 | I14: 0 | J14: 0 | K14: =SUM(C14:J14) -> 7633760.5 | L14: =K14/$K$31*100 -> 3.9800899
B15: GEMINIA LIFE INSURANCE COMPANY | C15: {='[1]APPENDIX 8'!$C15:$J15} -> 323624.61 | D15: 0 | E15: 743623.7 | F15: 64322.608 | G15: 442017.73 | H15: 222692.69 | I15: 0 | J15: 90519.786 | K15: =SUM(C15:J15) -> 1886801.1 | L15: =K15/$K$31*100 -> 0.98374032
B16: ICEA LION LIFE ASSURANCE | C16: {='[1]APPENDIX 8'!$C16:$J16} -> 6861578.8 | D16: 2298750.9 | E16: 10466116 | F16: 7851350.6 | G16: 579365.75 | H16: 261123.55 | I16: 0 | J16: 7160.1264 | K16: =SUM(C16:J16) -> 28325446 | L16: =K16/$K$31*100 -> 14.76832
B17: JUBILEE LIFE INSURANCE | C17: {='[1]APPENDIX 8'!$C17:$J17} -> 4725879 | D17: 725116.17 | E17: 17575105 | F17: 2545576 | G17: 1332792.2 | H17: 185059.58 | I17: 0 | J17: 71722.042 | K17: =SUM(C17:J17) -> 27161250 | L17: =K17/$K$31*100 -> 14.161332
... B19: KENYA ORIENT LIFE ASSURANCE | C19: {='[1]APPENDIX 8'!$C19:$J19} -> 62639.754 | D19: 217364.6 | E19: 195261.17 | F19: 97576.273 | G19: 122599.13 | H19: 566081.43 | I19: 0 | J19: 0 | K19: =SUM(C19:J19) -> 1261522.4 | L19: =K19/$K$31*100 -> 0.6577325
B20: KUSCCO MUTUAL ASSURANCE LIMITED | C20: {='[1]APPENDIX 8'!$C20:$J20} -> 1478.913 | D20: 58685.82 | E20: 0 | F20: 0 | G20: 19757.017 | H20: 363560.15 | I20: 0 | J20: 0 | K20: 443481.9 | L20: =K20/$K$31*100 -> 0.23122258
B21: LIBERTY LIFE ASSURANCE COMPANY | C21: {='[1]APPENDIX 8'!$C21:$J21} -> 970639.37 | D21: 0 | E21: 243935.88 | F21: 1340316 | G21: 880054.88 | H21: 863630.76 | I21: 0 | J21: 1289128.4 | K21: =SUM(C21:J21) -> 5587705.3 | L21: =K21/$K$31*100 -> 2.9133177
B22: MADISON INSURANCE COMPANY | C22: {='[1]APPENDIX 8'!$C22:$J22} -> 2393360 | D22: 0 | E22: 628180 | F22: 241633 | G22: 749070 | H22: 470264 | I22: 0 | J22: 645 | K22: =SUM(C22:J22) -> 4483152 | L22: =K22/$K$31*100 -> 2.3374257
B23: OLD MUTUAL ASSURANCE COMPANY | C23: {='[1]APPENDIX 8'!$C23:$J23} -> 795486.4 | D23: 0 | E23: 0 | F23: 0 | G23: 0 | H23: 0 | I23: 0 | J23: 267440.84 | K23: =SUM(C23:J23) -> 1062927.2 | L23: =K23/$K$31*100 -> 0.55418898
B24: OLD MUTUAL LIFE ASSURANCE KENYA | C24: {='[1]APPENDIX 8'!$C24:$J24} -> 1025180.8 | D24: 0 | E24: 713703.33 | F24: 0 | G24: 2429214.7 | H24: 914453.01 | I24: 0 | J24: 17061.999 | K24: =SUM(C24:J24) -> 5099613.9 | L24: =K24/$K$31*100 -> 2.6588366
B25: PIONEER ASSURANCE COMPANY | C25: {='[1]APPENDIX 8'!$C25:$J25} -> 1205240.9 | D25: 14853.57 | E25: 5950703 | F25: 0 | G25: 1010493.6 | H25: 344986.81 | I25: 0 | J25: 84024.803 | K25: =SUM(C25:J25) -> 8610302.6 | L25: =K25/$K$31*100 -> 4.4892394
B26: PRUDENTIAL LIFE ASSURANCE | C26: {='[1]APPENDIX 8'!$C26:$J26} -> 714587.57 | D26: 0 | E26: 457697.34 | F26: 668964.66 | G26: 845454.79 | H26: 419244.36 | I26: 0 | J26: 0 | K26: =SUM(C26:J26) -> 3105948.7 | L26: =K26/$K$31*100 -> 1.6193795
B27: SANLAM LIFE ASSURANCE | C27: {='[1]APPENDIX 8'!$C27:$J27} -> 2879253.7 | D27: 938848.18 | E27: 71046.363 | F27: 410324.14 | G27: 984909.33 | H27: 387222.67 | I27: 0 | J27: 241262.77 | K27: =SUM(C27:J27) -> 5912867.2 | L27: =K27/$K$31*100 -> 3.0828506
B28: STAR DISCOVER LIFE INSURANCE | C28: {='[1]APPENDIX 8'!$C28:$J28} -> 0 | D28: 0 | E28: 0 | F28: 0 | G28: 346616.64 | H28: 1003.78 | I28: 0 | J28: 0 | K28: =SUM(C28:J28) -> 347620.42 | L28: =K28/$K$31*100 -> 0.18124233
B29: THE KENYAN ALLIANCE INSURANCE | C29: {='[1]APPENDIX 8'!$C29:$J29} -> 17230.846 | D29: 0 | E29: 444490.32 | F29: 336057.7 | G29: 332860.8 | H29: 15378.246 | I29: 0 | J29: 9197.797 | K29: =SUM(C29:J29) -> 1155215.7 | L29: =K29/$K$31*100 -> 0.60230634
B30: THE MONARCH INSURANCE | C30: {='[1]APPENDIX 8'!$C30:$J30} -> 8957.7761 | D30: 0 | E30: 0 | F30: 0 | G30: 11379.468 | H30: 2886.1699 | I30: 0 | J30: 0 | K30: =SUM(C30:J30) -> 23223.414 | L30: =K30/$K$31*100 -> 0.012108223
B31: TOTAL | C31: =SUM(C6:C30) -> 42457066 | D31: =SUM(D6:D30) -> 12356888 | E31: =SUM(E6:E30) -> 68244152 | F31: =SUM(F6:F30) -> 21729305 | G31: =SUM(G6:G30) -> 24669467 | H31: =SUM(H6:H30) -> 14560401 | I31: =SUM(I6:I30) -> 0 | J31: =SUM(J6:J30) -> 7781418.3 | ... L31: =SUM(L6:L30) -> 100
B32: REINSURERS
B33: CONTINENTAL REINSURANCE | C33: {='[1]APPENDIX 8'!$C33:$L33} -> 0 | D33: 0 | E33: 0 | F33: 0 | G33: 0 | H33: 0 | I33: 0 | J33: 0 | K33: 0 | L33: 0
B34: EAST AFRICA REINSURANCE | C34: {='[1]APPENDIX 8'!$C34:$L34} -> 0 | D34: 0 | E34: 0 | F34: 0 | G34: 0 | H34: 0 | I34: 0 | J34: 0 | K34: 0 | L34: 0
B35: KENYA REINSURANCE CORPORATION | C35: {='[1]APPENDIX 8'!$C35:$L35} -> 0 | D35: 0 | E35: 0 | F35: 0 | G35: 0 | H35: 0 | I35: 0 | J35: 0 | K35: 0 | L35: 0
B36: TOTAL | C36: =SUM(C33:C35) -> 0 | D36: =SUM(D33:D35) -> 0 | E36: =SUM(E33:E35) -> 0 | F36: =SUM(F33:F35) -> 0 | G36: =SUM(G33:G35) -> 0 | H36: =SUM(H33:H35) -> 0 | I36: =SUM(I33:I35) -> 0 | J36: =SUM(J33:J35) -> 0 | ... L36: =SUM(L33:L35) -> 0
B37: Amounts in Thousand Shillings

Sheet APPENDIX 9
B3: =_xlfn.CONCAT(Contents!E26,": ",UPPER(Contents!F26)) -> APPENDIX 9: SUMMARY OF LONG TERM BUSINESS INWARD REINSURANCE PREMIUMS FOR THE YEAR ENDED 31.12.2024
B4: Company | C4: Life Assurances | D4: Annuities | E4: Deposit Administration | F4: Personal Pensions | G4: Group Life | H4: Group Credit | I4: Permanent Health | J4: Investments | K4: Total | L4: Market Share (%)
B5: INSURERS
B6: ABSA LIFE ASSURANCE | C6: {='[1]APPENDIX 9'!$C6:$J6} -> 0 | D6: 0 | E6: 0 | F6: 0 | G6: 0 | H6: 0 | I6: 0 | J6: 0 | K6: 0 | L6: =IFERROR(K6/$K$31*100,0) -> 0
B7: APA LIFE ASSURANCE COMPANY | C7: {='[1]APPENDIX 9'!$C7:$J7} -> 0 | D7: 0 | E7: 0 | F7: 0 | G7: 0 | H7: 0 | I7: 0 | J7: 0 | K7: 0 | L7: =IFERROR(K7/$K$31*100,0) -> 0
B8: BRITAM LIFE ASSURANCE | C8: {='[1]APPENDIX 9'!$C8:$J8} -> 0 | D8: 0 | E8: 0 | F8: 0 | G8: 0 | H8: 0 | I8: 0 | J8: 0 | K8: 0 | L8: =IFERROR(K8/$K$31*100,0) -> 0
B9: CANNON LIFE ASSURANCE (K) LIMITED | C9: {='[1]APPENDIX 9'!$C9:$J9} -> 0 | D9: 0 | E9: 0 | F9: 0 | G9: 0 | H9: 0 | I9: 0 | J9: 0 | K9: 0 | L9: =IFERROR(K9/$K$31*100,0) -> 0
B10: CAPEX LIFE ASSURANCE COMPANY | C10: {='[1]APPENDIX 9'!$C10:$J10} -> 0 | D10: 0 | E10: 0 | F10: 0 | G10: 0 | H10: 0 | I10: 0 | J10: 0 | K10: 0 | L10: =IFERROR(K10/$K$31*100,0) -> 0
B11: CIC LIFE ASSURANCE COMPANY | C11: {='[1]APPENDIX 9'!$C11:$J11} -> 0 | D11: 0 | E11: 0 | F11: 0 | G11: 0 | H11: 0 | I11: 0 | J11: 0 | K11: 0 | L11: =IFERROR(K11/$K$31*100,0) -> 0
B12: CORPORATE INSURANCE COMPANY | C12: {='[1]APPENDIX 9'!$C12:$J12} -> 0 | D12: 0 | E12: 0 | F12: 0 | G12: 0 | H12: 0 | I12: 0 | J12: 0 | K12: 0 | L12: =IFERROR(K12/$K$31*100,0) -> 0
B13: EQUITY LIFE ASSURANCE | C13: {='[1]APPENDIX 9'!$C13:$J13} -> 0 | D13: 0 | E13: 0 | F13: 0 | G13: 0 | H13: 0 | I13: 0 | J13: 0 | K13: 0 | L13: =IFERROR(K13/$K$31*100,0) -> 0
B14: GA LIFE ASSURANCE COMPANY | C14: {='[1]APPENDIX 9'!$C14:$J14} -> 0 | D14: 0 | E14: 0 | F14: 0 | G14: 0 | H14: 0 | I14: 0 | J14: 0 | K14: 0 | L14: =IFERROR(K14/$K$31*100,0) -> 0
B15: GEMINIA LIFE INSURANCE COMPANY | C15: {='[1]APPENDIX 9'!$C15:$J15} -> 0 | D15: 0 | E15: 0 | F15: 0 | G15: 0 | H15: 0 | I15: 0 | J15: 0 | K15: 0 | L15: =IFERROR(K15/$K$31*100,0) -> 0
B16: ICEA LION LIFE ASSURANCE | C16: {='[1]APPENDIX 9'!$C16:$J16} -> 0 | D16: 0 | E16: 0 | F16: 0 | G16: 0 | H16: 0 | I16: 0 | J16: 0 | K16: 0 | L16: =IFERROR(K16/$K$31*100,0) -> 0
B17: JUBILEE LIFE INSURANCE | C17: {='[1]APPENDIX 9'!$C17:$J17} -> 0 | D17: 0 | E17: 0 | F17: 0 | G17: 0 | H17: 0 | I17: 0 | J17: 0 | K17: 0 | L17: =IFERROR(K17/$K$31*100,0) -> 0
... B30: THE MONARCH INSURANCE | C30: {='[1]APPENDIX 9'!$C30:$J30} -> 0 | D30: 0 | E30: 0 | F30: 0 | G30: 0 | H30: 0 | I30: 0 | J30: 0 | K30: 0 | L30: =IFERROR(K30/$K$31*100,0) -> 0
B31: TOTAL | C31: =SUM(C6:C30) -> 0 | D31: =SUM(D6:D30) -> 0 | F31: =SUM(F6:F30) -> 0 | G31: =SUM(G6:G30) -> 0 | H31: =SUM(H6:H30) -> 0 | I31: =SUM(I6:I30) -> 0 | J31: =SUM(J6:J30) -> 0 | K31: =SUM(K6:K30) -> 0
B32: REINSURERS
B33: CONTINENTAL REINSURANCE | C33: {='[1]APPENDIX 9'!$C33:$J33} -> 0 | D33: 0 | E33: 0 | F33: 0 | G33: 17405.962 | H33: 0 | I33: 0 | J33: 0 | K33: =SUM(C33:J33) -> 17405.962 | L33: =IFERROR(K33/$K$36*100,0) -> 0.41044424
B34: EAST AFRICA REINSURANCE | C34: {='[1]APPENDIX 9'!$C34:$J34} -> 115415.98 | D34: 0 | E34: 0 | F34: 0 | G34: 1105358.1 | H34: 0 | I34: 0 | J34: 0 | K34: =SUM(C34:J34) -> 1220774.1 | L34: =IFERROR(K34/$K$36*100,0) -> 28.78667
B35: KENYA REINSURANCE CORPORATION | C35: {='[1]APPENDIX 9'!$C35:$J35} -> 100925.68 | D35: 0 | E35: 0 | F35: 0 | G35: 2901655.9 | H35: 0 | I35: 0 | J35: 0 | K35: =SUM(C35:J35) -> 3002581.6 | L35: =IFERROR(K35/$K$36*100,0) -> 70.802886
B36: TOTAL | C36: =SUM(C33:C35) -> 216341.66 | D36: =SUM(D33:D35) -> 0 | E36: =SUM(E33:E35) -> 0 | F36: =SUM(F33:F35) -> 0 | G36: =SUM(G33:G35) -> 4024420 | H36: =SUM(H33:H35) -> 0 | I36: =SUM(I33:I35) -> 0 | J36: =SUM(J33:J35) -> 0 | ... L36: =SUM(L33:L35) -> 100
B37: Amounts in Thousand Shillings

Sheet APPENDIX 10
B3: =_xlfn.CONCAT(Contents!E27,": ",UPPER(Contents!F27)) -> APPENDIX 10: SUMMARY OF LONG TERM BUSINESS OUTWARD REINSURANCE PREMIUMS FOR THE YEAR ENDED 31.12.2024
B4: Company | C4: Life Assurances | D4: Annuities | E4: Deposit Administration | F4: Personal Pensions | G4: Group Life | H4: Group Credit | I4: Permanent Health | J4: Investments | K4: Total
B5: INSURERS
B6: ABSA LIFE ASSURANCE | C6: {='[1]APPENDIX 10'!$C6:$J6} -> 24683.608 | D6: 0 | E6: 0 | F6: 0 | G6: 1443658.5 | H6: 131433.08 | I6: 0 | J6: 0 | K6: =SUM(C6:J6) -> 1599775.1
B7: APA LIFE ASSURANCE COMPANY | C7: {='[1]APPENDIX 10'!$C7:$J7} -> 10242.721 | D7: 0 | E7: 0 | F7: 0 | G7: 1036110.6 | H7: 90680.466 | I7: 0 | J7: 0 | K7: =SUM(C7:J7) -> 1137033.7
B8: BRITAM LIFE ASSURANCE | C8: {='[1]APPENDIX 10'!$C8:$J8} -> 12916.402 | D8: 0 | E8: 0 | F8: 0 | G8: 5587114.9 | H8: 46343.144 | I8: 0 | J8: 0 | K8: =SUM(C8:J8) -> 5646374.4
B9: CANNON LIFE ASSURANCE (K) LIMITED | C9: {='[1]APPENDIX 10'!$C9:$J9} -> 341.88173 | D9: 0 | E9: 0 | F9: 0 | G9: 165638.73 | H9: 1163.767 | I9: 0 | J9: 0 | K9: =SUM(C9:J9) -> 167144.38
B10: CAPEX LIFE ASSURANCE COMPANY | C10: {='[1]APPENDIX 10'!$C10:$J10} -> 0 | D10: 0 | E10: 0 | F10: 0 | G10: 159165.26 | H10: 13365.011 | I10: 0 | J10: 0 | K10: =SUM(C10:J10) -> 172530.28
B11: CIC LIFE ASSURANCE COMPANY | C11: {='[1]APPENDIX 10'!$C11:$J11} -> 12513.654 | D11: 0 | E11: 0 | F11: 0 | G11: 63488.788 | H11: 381400.83 | I11: 0 | J11: 0 | K11: =SUM(C11:J11) -> 457403.27
B12: CORPORATE INSURANCE COMPANY | C12: {='[1]APPENDIX 10'!$C12:$J12} -> 0 | D12: 0 | E12: 0 | F12: 0 | G12: 0 | H12: 0 | I12: 0 | J12: 0 | K12: =SUM(C12:J12) -> 0
B13: EQUITY LIFE ASSURANCE | C13: {='[1]APPENDIX 10'!$C13:$J13} -> 0 | D13: 0 | E13: 0 | F13: 0 | G13: 280480.78 | H13: 138313.03 | I13: 0 | J13: 0 | K13: =SUM(C13:J13) -> 418793.81
B14: GA LIFE ASSURANCE COMPANY | C14: {='[1]APPENDIX 10'!$C14:$J14} -> 0 | D14: 0 | E14: 0 | F14: 0 | G14: 81782.066 | H14: 2845.506 | I14: 0 | J14: 0 | K14: =SUM(C14:J14) -> 84627.572
B15: GEMINIA LIFE INSURANCE COMPANY | C15: {='[1]APPENDIX 10'!$C15:$J15} -> 0 | D15: 0 | E15: 0 | F15: 0 | G15: 272345.48 | H15: 0 | I15: 0 | J15: 0 | K15: =SUM(C15:J15) -> 272345.48
B16: ICEA LION LIFE ASSURANCE | C16: {='[1]APPENDIX 10'!$C16:$J16} -> 72906.166 | D16: 0 | E16: 0 | F16: 0 | G16: 265777.79 | H16: 129673.73 | I16: 0 | J16: 0 | K16: =SUM(C16:J16) -> 468357.69
B17: JUBILEE LIFE INSURANCE | C17: {='[1]APPENDIX 10'!$C17:$J17} -> 13121.791 | D17: 0 | E17: 0 | F17: 0 | G17: 617286.12 | H17: 27147.277 | I17: 0 | J17: 0 | K17: =SUM(C17:J17) -> 657555.19
... B19: KENYA ORIENT LIFE ASSURANCE | C19: {='[1]APPENDIX 10'!$C19:$J19} -> 154.106 | D19: 0 | E19: 0 | F19: 0 | G19: 28837.487 | H19: 72729.043 | I19: 0 | J19: 0 | K19: =SUM(C19:J19) -> 101720.64
B20: KUSCCO MUTUAL ASSURANCE LIMITED | C20: {='[1]APPENDIX 10'!$C20:$J20} -> 0 | D20: 0 | E20: 0 | F20: 0 | G20: 3951.403 | H20: 72712.03 | I20: 0 | J20: 0 | K20: 76663.433
B21: LIBERTY LIFE ASSURANCE COMPANY | C21: {='[1]APPENDIX 10'!$C21:$J21} -> 32088.345 | D21: 0 | E21: 0 | F21: 0 | G21: 180280.09 | H21: 120884.43 | I21: 0 | J21: 50.12 | K21: =SUM(C21:J21) -> 333302.98
B22: MADISON INSURANCE COMPANY | C22: {='[1]APPENDIX 10'!$C22:$J22} -> 0 | D22: 0 | E22: 0 | F22: 0 | G22: 307865 | H22: 221826 | I22: 0 | J22: 0 | K22: =SUM(C22:J22) -> 529691
B23: OLD MUTUAL ASSURANCE COMPANY | C23: {='[1]APPENDIX 10'!$C23:$J23} -> 71025.902 | D23: 0 | E23: 0 | F23: 0 | G23: 0 | H23: 0 | I23: 0 | J23: 0 | K23: =SUM(C23:J23) -> 71025.902
B24: OLD MUTUAL LIFE ASSURANCE KENYA | C24: {='[1]APPENDIX 10'!$C24:$J24} -> 14326.052 | D24: 0 | E24: 0 | F24: 0 | G24: 946367.88 | H24: 293039.64 | I24: 0 | J24: 0 | K24: =SUM(C24:J24) -> 1253733.6
B25: PIONEER ASSURANCE COMPANY | C25: {='[1]APPENDIX 10'!$C25:$J25} -> 5069.406 | D25: 0 | E25: 0 | F25: 0 | G25: 139585.1 | H25: 89575.607 | I25: 0 | J25: 0 | K25: =SUM(C25:J25) -> 234230.11
B26: PRUDENTIAL LIFE ASSURANCE | C26: {='[1]APPENDIX 10'!$C26:$J26} -> 87779.226 | D26: 0 | E26: 0 | F26: 0 | G26: 322987.89 | H26: 48152.48 | I26: 0 | J26: 0 | K26: =SUM(C26:J26) -> 458919.59
B27: SANLAM LIFE ASSURANCE | C27: {='[1]APPENDIX 10'!$C27:$J27} -> 96906.509 | D27: 18093.089 | E27: 0 | F27: 0 | G27: 477830.6 | H27: 154625.18 | I27: 0 | J27: 0 | K27: =SUM(C27:J27) -> 747455.38
B28: STAR DISCOVER LIFE INSURANCE | C28: {='[1]APPENDIX 10'!$C28:$J28} -> 0 | D28: 0 | E28: 0 | F28: 0 | G28: 861.05 | H28: 336.434 | I28: 0 | J28: 0 | K28: =SUM(C28:J28) -> 1197.484
B29: THE KENYAN ALLIANCE INSURANCE | C29: {='[1]APPENDIX 10'!$C29:$J29} -> 0 | D29: 0 | E29: 0 | F29: 0 | G29: 23083.11 | H29: 0 | I29: 0 | J29: 0 | K29: =SUM(C29:J29) -> 23083.11
B30: THE MONARCH INSURANCE | C30: {='[1]APPENDIX 10'!$C30:$J30} -> 0 | D30: 0 | E30: 0 | F30: 0 | G30: 3514.839 | H30: 1506.359 | I30: 0 | J30: 0 | K30: =SUM(C30:J30) -> 5021.198
B31: TOTAL | C31: =SUM(C6:C30) -> 460149.52 | D31: =SUM(D6:D30) -> 18093.089 | E31: =SUM(E6:E30) -> 0 | F31: =SUM(F6:F30) -> 0 | G31: =SUM(G6:G30) -> 12471166 | H31: =SUM(H6:H30) -> 2037753 | I31: =SUM(I6:I30) -> 0 | J31: =SUM(J6:J30) -> 50.12 | K31: =SUM(K6:K30) -> 14987211
B32: REINSURERS
B33: CONTINENTAL REINSURANCE | C33: {='[1]APPENDIX 10'!$C33:$J33} -> 0 | D33: 0 | E33: 0 | F33: 0 | G33: -52.837 | H33: 0 | I33: 0 | J33: 0 | K33: =SUM(C33:J33) -> -52.837
B34: EAST AFRICA REINSURANCE | C34: {='[1]APPENDIX 10'!$C34:$J34} -> 27316.379 | D34: 0 | E34: 0 | F34: 0 | G34: 261613.5 | H34: 0 | I34: 0 | J34: 0 | K34: =SUM(C34:J34) -> 288929.88
B35: KENYA REINSURANCE CORPORATION | C35: {='[1]APPENDIX 10'!$C35:$J35} -> 0 | D35: 0 | E35: 0 | F35: 0 | G35: 147837.42 | H35: 0 | I35: 0 | J35: 0 | K35: =SUM(C35:J35) -> 147837.42
B36: TOTAL | C36: =SUM(C33:C35) -> 27316.379 | D36: =SUM(D33:D35) -> 0 | E36: =SUM(E33:E35) -> 0 | F36: =SUM(F33:F35) -> 0 | G36: =SUM(G33:G35) -> 409398.08 | H36: =SUM(H33:H35) -> 0 | I36: =SUM(I33:I35) -> 0 | J36: =SUM(J33:J35) -> 0 | K36: =SUM(K33:K35) -> 436714.46
B37: Amounts in Thousand Shillings

Sheet APPENDIX 11
B3: =_xlfn.CONCAT(Contents!E28,": ",UPPER(Contents!F28)) -> APPENDIX 11: SUMMARY OF LIFE ASSURANCES BUSINESS REVENUE ACCOUNTS FOR THE YEAR ENDED 31.12.2024
B4: Company | C4: Life Fund BF | D4: Gross Premium | E4: Net Premium | F4: Other (Fee) Income | G4: Total Benefits | H4: Claims | I4: Surrenders_x000D_ | J4: Bonuses Paid | K4: Annuities Paid | L4: Net Commisions | M4: Expense of Management | N4: Investment Income | O4: Investment Expenses | P4: Transfer To (From) P & L | Q4: Life Fund CF
B5: INSURERS
B6: ABSA LIFE ASSURANCE | C6: {='[1]APPENDIX 11'!$C6:$Q6} -> 7146925.1 | D6: 4885789.6 | E6: 4861106 | F6: 0 | G6: 1790635.3 | H6: 1790635.3 | I6: 0 | J6: 0 | K6: 0 | L6: 622692.75 | M6: 344885.12 | N6: 1386791.2 | O6: 0 | P6: 0 | Q6: 10636609
B7: APA LIFE ASSURANCE COMPANY | C7: {='[1]APPENDIX 11'!$C7:$Q7} -> 716591.72 | D7: 486359 | E7: 476116.28 | F7: 0 | G7: 179474.16 | H7: 179474.16 | I7: 0 | J7: 0 | K7: 0 | L7: 176023.81 | M7: 117338.64 | N7: 193156.19 | O7: 2948.969 | P7: 85000 | Q7: 995078.63
B8: BRITAM LIFE ASSURANCE | C8: {='[1]APPENDIX 11'!$C8:$Q8} -> 37651992 | D8: 11592507 | E8: 11579590 | F8: -26087.15 | G8: 6729363.5 | H8: 6729363.5 | I8: 0 | J8: 0 | K8: 0 | L8: 1443684.9 | M8: 2674177.5 | N8: 9750324.7 | O8: 204858.95 | P8: 4017551.4 | Q8: 43886184
B9: CANNON LIFE ASSURANCE (K) LIMITED | C9: {='[1]APPENDIX 11'!$C9:$Q9} -> 634162.08 | D9: 27657.387 | E9: 27315.505 | F9: 0 | G9: 110743.57 | H9: 110743.57 | I9: 0 | J9: 0 | K9: 0 | L9: -3075.4641 | M9: 54369.61 | N9: 28366.919 | O9: 0 | P9: 0 | Q9: 527806.79
B10: CAPEX LIFE ASSURANCE COMPANY | C10: {='[1]APPENDIX 11'!$C10:$Q10} -> 37873.837 | D10: 5981.2511 | E10: 5981.2511 | F10: 0 | G10: 8457.8835 | H10: 8457.8835 | I10: 0 | J10: 0 | K10: 0 | L10: 827.82 | M10: 1496.4127 | N10: 153.74309 | O10: 0 | P10: 0 | Q10: 33226.715
B11: CIC LIFE ASSURANCE COMPANY | C11: {='[1]APPENDIX 11'!$C11:$Q11} -> 4860801.5 | D11: 1279963.5 | E11: 1267449.8 | F11: 0 | G11: 903449.73 | H11: 903449.73 | I11: 0 | J11: 0 | K11: 0 | L11: 140099.95 | M11: 372676.56 | N11: 427387.1 | O11: 0 | P11: 0 | Q11: 5139412.2
B12: CORPORATE INSURANCE COMPANY | C12: {='[1]APPENDIX 11'!$C12:$Q12} -> 73832.62 | D12: 49368.199 | E12: 49368.199 | F12: 0 | G12: 58502.7 | H12: 58502.7 | I12: 0 | J12: 0 | K12: 0 | L12: 0 | M12: 12856.517 | N12: 12939.548 | O12: 1766.569 | P12: 0 | Q12: 63014.581
B13: EQUITY LIFE ASSURANCE | C13: {='[1]APPENDIX 11'!$C13:$Q13} -> 0 | D13: 0 | E13: 0 | F13: 0 | G13: 0 | H13: 0 | I13: 0 | J13: 0 | K13: 0 | L13: 0 | M13: 0 | N13: 0 | O13: 0 | P13: 0 | Q13: 0
B14: GA LIFE ASSURANCE COMPANY | C14: {='[1]APPENDIX 11'!$C14:$Q14} -> 3320238.7 | D14: 466960.01 | E14: 466960.01 | F14: 0 | G14: 633824.31 | H14: 633824.31 | I14: 0 | J14: 0 | K14: 0 | L14: 529.427 | M14: 684.42527 | N14: 1013898.1 | O14: 0 | P14: 71484.691 | Q14: 4094574
B15: GEMINIA LIFE INSURANCE COMPANY | C15: {='[1]APPENDIX 11'!$C15:$Q15} -> 796180.98 | D15: 323624.61 | E15: 323624.61 | F15: 0 | G15: 675175.37 | H15: 29807.393 | I15: 645367.97 | J15: 0 | K15: 0 | L15: 10932.626 | M15: 15094.984 | N15: 5022 | O15: 0 | P15: 0 | Q15: 423624.61
B16: ICEA LION LIFE ASSURANCE | C16: {='[1]APPENDIX 11'!$C16:$Q16} -> 18152706 | D16: 6861578.8 | E16: 6788672.6 | F16: 0 | G16: 3279848 | H16: 2720675.2 | I16: 559172.83 | J16: 0 | K16: 0 | L16: 1300357.6 | M16: 1255458.3 | N16: 3292624.2 | O16: 0 | P16: 0 | Q16: 22398339
B17: JUBILEE LIFE INSURANCE | C17: {='[1]APPENDIX 11'!$C17:$Q17} -> 11593836 | D17: 4725879 | E17: 4712757.2 | F17: 0 | G17: 4378243.6 | H17: 4378243.6 | I17: 0 | J17: 0 | K17: 0 | L17: 837692.57 | M17: 645162.77 | N17: 2623477.1 | O17: 24463.496 | P17: -426031.81 | Q17: 13470539
... B30: THE MONARCH INSURANCE | C30: {='[1]APPENDIX 11'!$C30:$Q30} -> 67157.661 | D30: 8957.7761 | E30: 8957.7761 | F30: 0 | G30: 2414.314 | H30: 2414.314 | I30: 0 | J30: 0 | K30: 0 | L30: 0 | M30: 9482.1126 | N30: 1786.1017 | O30: 0 | P30: 0 | Q30: 66005.112
B31: TOTAL | C31: =SUM(C6:C30) -> 1.3388076e+08 | D31: =SUM(D6:D30) -> 42457066 | E31: =SUM(E6:E30) -> 41996916 | F31: =SUM(F6:F30) -> 344796.43 | G31: =SUM(G6:G30) -> 28586823 | H31: =SUM(H6:H30) -> 27363192 | I31: =SUM(I6:I30) -> 1204540.8 | J31: =SUM(J6:J30) -> 19090.284 | ... Q31: =SUM(Q6:Q30) -> 1.5500846e+08
B32: REINSURERS
B33: CONTINENTAL REINSURANCE | C33: {='[1]APPENDIX 11'!$C33:$Q33} -> 0 | D33: 0 | E33: 0 | F33: 0 | G33: 0 | H33: 0 | I33: 0 | J33: 0 | K33: 0 | L33: 0 | M33: 0 | N33: 0 | O33: 0 | P33: 0 | Q33: 0
B34: EAST AFRICA REINSURANCE | C34: {='[1]APPENDIX 11'!$C34:$Q34} -> 79585.893 | D34: 115415.98 | E34: 88099.606 | F34: 0 | G34: 14777.5 | H34: 14777.5 | I34: 0 | J34: 0 | K34: 0 | L34: 23419.794 | M34: 14234.983 | N34: 25660.171 | O34: 1053.0599 | P34: 0 | Q34: 139860.33
B35: KENYA REINSURANCE CORPORATION | C35: {='[1]APPENDIX 11'!$C35:$Q35} -> 352997.75 | D35: 100925.68 | E35: 100925.68 | F35: 0 | G35: 10450.848 | H35: 10450.848 | I35: 0 | J35: 0 | K35: 0 | L35: 36761.067 | M35: 6637.772 | N35: 30309.59 | O35: 0 | P35: 0 | Q35: 430383.33
B36: TOTAL | C36: =SUM(C33:C35) -> 432583.64 | D36: =SUM(D33:D35) -> 216341.66 | E36: =SUM(E33:E35) -> 189025.28 | F36: =SUM(F33:F35) -> 0 | G36: =SUM(G33:G35) -> 25228.348 | H36: =SUM(H33:H35) -> 25228.348 | I36: =SUM(I33:I35) -> 0 | J36: =SUM(J33:J35) -> 0 | ... Q36: =SUM(Q33:Q35) -> 570243.66
B37: Amounts in Thousand Shillings

Sheet APPENDIX 12
B3: =_xlfn.CONCAT(Contents!E29,": ",UPPER(Contents!F29)) -> APPENDIX 12: SUMMARY OF ANNUITIES BUSINESS REVENUE ACCOUNTS FOR THE YEAR ENDED 31.12.2024
B4: Company | C4: Life Fund BF | D4: Gross Premium | E4: Net Premium | F4: Other (Fee) Income | G4: Total Benefits | H4: Claims | I4: Surrenders_x000D_ | J4: Bonuses Paid | K4: Annuities Paid | L4: Net Commisions | M4: Expense of Management | N4: Investment Income | O4: Investment Expenses | P4: Transfer To (From) P & L | Q4: Life Fund CF
B5: INSURERS
B6: ABSA LIFE ASSURANCE | C6: {='[1]APPENDIX 12'!$C6:$Q6} -> 0 | D6: 0 | E6: 0 | F6: 0 | G6: 0 | H6: 0 | I6: 0 | J6: 0 | K6: 0 | L6: 0 | M6: 0 | N6: 0 | O6: 0 | P6: 0 | Q6: 0
B7: APA LIFE ASSURANCE COMPANY | C7: {='[1]APPENDIX 12'!$C7:$Q7} -> 869199.94 | D7: 74357.726 | E7: 74357.726 | F7: 0 | G7: 107270.79 | H7: 107270.79 | I7: 0 | J7: 0 | K7: 0 | L7: 0 | M7: 2921.171 | N7: 186629.58 | O7: 4955.2185 | P7: 0 | Q7: 1015040.1
B8: BRITAM LIFE ASSURANCE | C8: {='[1]APPENDIX 12'!$C8:$Q8} -> 14833456 | D8: 6901846.1 | E8: 6901846.1 | F8: 0 | G8: 2645201.6 | H8: 2645201.6 | I8: 0 | J8: 0 | K8: 0 | L8: 138131.49 | M8: 93805.928 | N8: 4833237.7 | O8: 33506.686 | P8: -401722.19 | Q8: 24059616
B9: CANNON LIFE ASSURANCE (K) LIMITED | C9: {='[1]APPENDIX 12'!$C9:$Q9} -> 12842.232 | D9: 0 | E9: 0 | F9: 0 | G9: 1309.509 | H9: 1309.509 | I9: 0 | J9: 0 | K9: 0 | L9: 0 | M9: 0 | N9: 0 | O9: 0 | P9: 0 | Q9: 11532.723
B10: CAPEX LIFE ASSURANCE COMPANY | C10: {='[1]APPENDIX 12'!$C10:$Q10} -> 1016949.2 | D10: 324925.1 | E10: 324925.1 | F10: 0 | G10: 386423.06 | H10: 386423.06 | I10: 0 | J10: 0 | K10: 0 | L10: 19546.54 | M10: 81291.029 | N10: 8351.93 | O10: 0 | P10: 0 | Q10: 862965.63
B11: CIC LIFE ASSURANCE COMPANY | C11: {='[1]APPENDIX 12'!$C11:$Q11} -> 1534571.1 | D11: 354526.11 | E11: 354526.11 | F11: 0 | G11: 302435.66 | H11: 302435.66 | I11: 0 | J11: 0 | K11: 0 | L11: 6787.6644 | M11: 25574.188 | N11: 274977.86 | O11: 0 | P11: 0 | Q11: 1829277.5
B12: CORPORATE INSURANCE COMPANY | C12: {='[1]APPENDIX 12'!$C12:$Q12} -> 0 | D12: 0 | E12: 0 | F12: 0 | G12: 0 | H12: 0 | I12: 0 | J12: 0 | K12: 0 | L12: 0 | M12: 0 | N12: 0 | O12: 0 | P12: 0 | Q12: 0
B13: EQUITY LIFE ASSURANCE | C13: {='[1]APPENDIX 12'!$C13:$Q13} -> 0 | D13: 0 | E13: 0 | F13: 0 | G13: 0 | H13: 0 | I13: 0 | J13: 0 | K13: 0 | L13: 0 | M13: 0 | N13: 0 | O13: 0 | P13: 0 | Q13: 0
B14: GA LIFE ASSURANCE COMPANY | C14: {='[1]APPENDIX 12'!$C14:$Q14} -> 0 | D14: 0 | E14: 0 | F14: 0 | G14: 0 | H14: 0 | I14: 0 | J14: 0 | K14: 0 | L14: 0 | M14: 0 | N14: 0 | O14: 0 | P14: 0 | Q14: 0
B15: GEMINIA LIFE INSURANCE COMPANY | C15: {='[1]APPENDIX 12'!$C15:$Q15} -> 0 | D15: 0 | E15: 0 | F15: 0 | G15: 0 | H15: 0 | I15: 0 | J15: 0 | K15: 0 | L15: 0 | M15: 0 | N15: 0 | O15: 0 | P15: 0 | Q15: 0
B16: ICEA LION LIFE ASSURANCE | C16: {='[1]APPENDIX 12'!$C16:$Q16} -> 17678914 | D16: 2298750.9 | E16: 2298750.9 | F16: 0 | G16: 2432050 | H16: 42207.388 | I16: 0 | J16: 0 | K16: 2389842.7 | L16: 39131.672 | M16: 41682.638 | N16: 5186500.9 | O16: 0 | P16: 0 | Q16: 22651302
B17: JUBILEE LIFE INSURANCE | C17: {='[1]APPENDIX 12'!$C17:$Q17} -> 11271713 | D17: 725116.17 | E17: 725116.17 | F17: 0 | G17: 1578767.1 | H17: 1578767.1 | I17: 0 | J17: 0 | K17: 0 | L17: 11240.019 | M17: 23710.496 | N17: 2626649.9 | O17: 12161.476 | P17: 143143.15 | Q17: 12854457
... B30: THE MONARCH INSURANCE | C30: {='[1]APPENDIX 12'!$C30:$Q30} -> 0 | D30: 0 | E30: 0 | F30: 0 | G30: 0 | H30: 0 | I30: 0 | J30: 0 | K30: 0 | L30: 0 | M30: 0 | N30: 0 | O30: 0 | P30: 0 | Q30: 0
B31: TOTAL | C31: =SUM(C6:C30) -> 77613757 | D31: =SUM(D6:D30) -> 12356888 | E31: =SUM(E6:E30) -> 12338795 | F31: =SUM(F6:F30) -> 0 | G31: =SUM(G6:G30) -> 11510784 | H31: =SUM(H6:H30) -> 9196301.4 | I31: =SUM(I6:I30) -> 0 | J31: =SUM(J6:J30) -> -75359.831 | ... Q31: =SUM(Q6:Q30) -> 95670085
B32: REINSURERS
B33: CONTINENTAL REINSURANCE | C33: {='[1]APPENDIX 12'!$C33:$Q33} -> 0 | D33: 0 | E33: 0 | F33: 0 | G33: 0 | H33: 0 | I33: 0 | J33: 0 | K33: 0 | L33: 0 | M33: 0 | N33: 0 | O33: 0 | P33: 0 | Q33: 0
B34: EAST AFRICA REINSURANCE | C34: {='[1]APPENDIX 12'!$C34:$Q34} -> 0 | D34: 0 | E34: 0 | F34: 0 | G34: 0 | H34: 0 | I34: 0 | J34: 0 | K34: 0 | L34: 0 | M34: 0 | N34: 0 | O34: 0 | P34: 0 | Q34: 0
B35: KENYA REINSURANCE CORPORATION | C35: {='[1]APPENDIX 12'!$C35:$Q35} -> 0 | D35: 0 | E35: 0 | F35: 0 | G35: 0 | H35: 0 | I35: 0 | J35: 0 | K35: 0 | L35: 0 | M35: 0 | N35: 0 | O35: 0 | P35: 0 | Q35: 0
B36: TOTAL | C36: =SUM(C33:C35) -> 0 | D36: =SUM(D33:D35) -> 0 | E36: =SUM(E33:E35) -> 0 | F36: =SUM(F33:F35) -> 0 | G36: =SUM(G33:G35) -> 0 | H36: =SUM(H33:H35) -> 0 | I36: =SUM(I33:I35) -> 0 | J36: =SUM(J33:J35) -> 0 | ... Q36: =SUM(Q33:Q35) -> 0
B37: Amounts in Thousand Shillings

Sheet APPENDIX 13
B3: =_xlfn.CONCAT(Contents!E30,": ",UPPER(Contents!F30)) -> APPENDIX 13: SUMMARY OF GROUP LIFE BUSINESS REVENUE ACCOUNTS FOR THE YEAR ENDED 31.12.2024
B4: Company | C4: Life Fund BF | D4: Gross Premium | E4: Net Premium | F4: Other (Fee) Income | G4: Total Benefits | H4: Claims | I4: Surrenders_x000D_ | J4: Bonuses Paid | K4: Annuities Paid | L4: Net Commisions | M4: Expense of Management | N4: Investment Income | O4: Investment Expenses | P4: Transfer To (From) P & L | Q4: Life Fund CF
B5: INSURERS
B6: ABSA LIFE ASSURANCE | C6: {='[1]APPENDIX 13'!$C6:$Q6} -> 117830.52 | D6: 3056103.8 | E6: 1612445.4 | F6: 0 | G6: 871554.97 | H6: 871554.97 | I6: 0 | J6: 0 | K6: 0 | L6: 116844.29 | M6: 417359.95 | N6: 129512.06 | O6: 0 | P6: 0 | Q6: 454028.71
B7: APA LIFE ASSURANCE COMPANY | C7: {='[1]APPENDIX 13'!$C7:$Q7} -> 52580.685 | D7: 1831606.7 | E7: 795496.14 | F7: 0 | G7: 300050.03 | H7: 300050.03 | I7: 0 | J7: 0 | K7: 0 | L7: -283615.39 | M7: 219755.74 | N7: 29572.066 | O7: 2295.0395 | P7: 0 | Q7: 639163.48
B8: BRITAM LIFE ASSURANCE | C8: {='[1]APPENDIX 13'!$C8:$Q8} -> 2736825.9 | D8: 6250268.2 | E8: 663153.35 | F8: 0 | G8: 515518.69 | H8: 515518.69 | I8: 0 | J8: 0 | K8: 0 | L8: -195000.71 | M8: 390390.15 | N8: 497203.96 | O8: -7849.2 | P8: 421357.3 | Q8: 2772767
B9: CANNON LIFE ASSURANCE (K) LIMITED | C9: {='[1]APPENDIX 13'!$C9:$Q9} -> 94519.407 | D9: 383545.16 | E9: 217906.43 | F9: 0 | G9: 84859.725 | H9: 84859.725 | I9: 0 | J9: 0 | K9: 0 | L9: 7868.5269 | M9: 104705.44 | N9: 53213.463 | O9: 0 | P9: 0 | Q9: 168205.61
B10: CAPEX LIFE ASSURANCE COMPANY | C10: {='[1]APPENDIX 13'!$C10:$Q10} -> -104354.75 | D10: 1198881.9 | E10: 1039716.6 | F10: 0 | G10: 255681.38 | H10: 255681.38 | I10: 0 | J10: 0 | K10: 0 | L10: 75222.702 | M10: 299940.94 | N10: 30816.264 | O10: 0 | P10: 0 | Q10: 335333.11
B11: CIC LIFE ASSURANCE COMPANY | C11: {='[1]APPENDIX 13'!$C11:$Q11} -> 960794.28 | D11: 1261374.5 | E11: 1197885.7 | F11: 0 | G11: 497944.14 | H11: 497944.14 | I11: 0 | J11: 0 | K11: 0 | L11: 68439.085 | M11: 268759 | N11: 330614.47 | O11: 0 | P11: 0 | Q11: 1654152.2
B12: CORPORATE INSURANCE COMPANY | C12: {='[1]APPENDIX 13'!$C12:$Q12} -> 0 | D12: 0 | E12: 0 | F12: 0 | G12: 0 | H12: 0 | I12: 0 | J12: 0 | K12: 0 | L12: 0 | M12: 0 | N12: 0 | O12: 0 | P12: 0 | Q12: 0
B13: EQUITY LIFE ASSURANCE | C13: {='[1]APPENDIX 13'!$C13:$Q13} -> 288146.31 | D13: 428316.15 | E13: 147835.37 | F13: 0 | G13: 129620.36 | H13: 129620.36 | I13: 0 | J13: 0 | K13: 0 | L13: -47771.703 | M13: 50325.314 | N13: 283821 | O13: 0 | P13: 0 | Q13: 587628.71
B14: GA LIFE ASSURANCE COMPANY | C14: {='[1]APPENDIX 13'!$C14:$Q14} -> 19822.486 | D14: 88965.034 | E14: 7182.968 | F14: 0 | G14: 1856.0242 | H14: 1856.0242 | I14: 0 | J14: 0 | K14: 0 | L14: -14232.606 | M14: 17283.809 | N14: 8641.199 | O14: 0 | P14: 3890.821 | Q14: 26848.605
B15: GEMINIA LIFE INSURANCE COMPANY | C15: {='[1]APPENDIX 13'!$C15:$Q15} -> 535930.34 | D15: 442017.73 | E15: 169672.25 | F15: 0 | G15: 349028.48 | H15: 349028.48 | I15: 0 | J15: 0 | K15: 0 | L15: 113991.19 | M15: 97431.26 | N15: 272294.62 | O15: 0 | P15: 589825.86 | Q15: 1007272.1
B16: ICEA LION LIFE ASSURANCE | C16: {='[1]APPENDIX 13'!$C16:$Q16} -> 250174.67 | D16: 579365.75 | E16: 313587.96 | F16: 0 | G16: 128182.69 | H16: 128182.69 | I16: 0 | J16: 0 | K16: 0 | L16: -85245.874 | M16: 142814.5 | N16: 55355.713 | O16: 0 | P16: 0 | Q16: 433367.02
B17: JUBILEE LIFE INSURANCE | C17: {='[1]APPENDIX 13'!$C17:$Q17} -> 474015.98 | D17: 1332792.2 | E17: 715506.09 | F17: 0 | G17: 355591.77 | H17: 355591.77 | I17: 0 | J17: 0 | K17: 0 | L17: 10760.404 | M17: 194833.24 | N17: 123014.67 | O17: 3717.7833 | P17: 273017.19 | Q17: 474616.36
... B30: THE MONARCH INSURANCE | C30: {='[1]APPENDIX 13'!$C30:$Q30} -> 656.47116 | D30: 11379.468 | E30: 7864.629 | F30: 0 | G30: 21663.003 | H30: 21663.003 | I30: 0 | J30: 0 | K30: 0 | L30: -79.833 | M30: 8569.2054 | N30: 2060.803 | O30: 0 | P30: 0 | Q30: -19570.472
B31: TOTAL | C31: =SUM(C6:C30) -> 10201114 | D31: =SUM(D6:D30) -> 24669467 | E31: =SUM(E6:E30) -> 12198302 | F31: =SUM(F6:F30) -> -113480.05 | G31: =SUM(G6:G30) -> 6712824.5 | H31: =SUM(H6:H30) -> 6587851.2 | I31: =SUM(I6:I30) -> 0 | J31: =SUM(J6:J30) -> 124973.33 | ... Q31: =SUM(Q6:Q30) -> 14491587
B32: REINSURERS
B33: CONTINENTAL REINSURANCE | C33: {='[1]APPENDIX 13'!$C33:$Q33} -> 0 | D33: 17405.962 | E33: 17458.799 | F33: 0 | G33: 22022.256 | H33: 22022.256 | I33: 0 | J33: 0 | K33: 0 | L33: 5479.831 | M33: 8610.053 | N33: 51161.547 | O33: 0 | P33: 0 | Q33: 32508.206
B34: EAST AFRICA REINSURANCE | C34: {='[1]APPENDIX 13'!$C34:$Q34} -> 762207.32 | D34: 1105358.1 | E34: 843744.57 | F34: 0 | G34: 406236.23 | H34: 406236.23 | I34: 0 | J34: 0 | K34: 0 | L34: 224295.26 | M34: 184750.04 | N34: 259452.84 | O34: 10647.606 | P34: 0 | Q34: 1039475.6
B35: KENYA REINSURANCE CORPORATION | C35: {='[1]APPENDIX 13'!$C35:$Q35} -> 6497502.4 | D35: 2901655.9 | E35: 2753818.5 | F35: 0 | G35: 1250557.7 | H35: 1250557.7 | I35: 0 | J35: 0 | K35: 0 | L35: 860925.18 | M35: 59739.938 | N35: 871413.57 | O35: 0 | P35: 0 | Q35: 7951511.7
B36: TOTAL | C36: =SUM(C33:C35) -> 7259709.7 | D36: =SUM(D33:D35) -> 4024420 | E36: =SUM(E33:E35) -> 3615021.9 | F36: =SUM(F33:F35) -> 0 | G36: =SUM(G33:G35) -> 1678816.2 | H36: =SUM(H33:H35) -> 1678816.2 | I36: =SUM(I33:I35) -> 0 | J36: =SUM(J33:J35) -> 0 | ... Q36: =SUM(Q33:Q35) -> 9023495.5
B37: Amounts in Thousand Shillings

Sheet APPENDIX 14
B3: =_xlfn.CONCAT(Contents!E31,": ",UPPER(Contents!F31)) -> APPENDIX 14: SUMMARY OF PERSONAL PENSIONS BUSINESS REVENUE ACCOUNTS FOR THE YEAR ENDED 31.12.2024
B4: Company | C4: Life Fund BF | D4: Gross Premium | E4: Net Premium | F4: Other (Fee) Income | G4: Total Benefits | H4: Claims | I4: Surrenders_x000D_ | J4: Bonuses Paid | K4: Annuities Paid | L4: Net Commisions | M4: Expense of Management | N4: Investment Income | O4: Investment Expenses | P4: Transfer To (From) P & L | Q4: Life Fund CF
B5: INSURERS
B6: ABSA LIFE ASSURANCE | C6: {='[1]APPENDIX 14'!$C6:$Q6} -> 0 | D6: 0 | E6: 0 | F6: 0 | G6: 0 | H6: 0 | I6: 0 | J6: 0 | K6: 0 | L6: 0 | M6: 0 | N6: 0 | O6: 0 | P6: 0 | Q6: 0
B7: APA LIFE ASSURANCE COMPANY | C7: {='[1]APPENDIX 14'!$C7:$Q7} -> 0 | D7: 0 | E7: 0 | F7: 0 | G7: 0 | H7: 0 | I7: 0 | J7: 0 | K7: 0 | L7: 0 | M7: 0 | N7: 0 | O7: 0 | P7: 0 | Q7: 0
B8: BRITAM LIFE ASSURANCE | C8: {='[1]APPENDIX 14'!$C8:$Q8} -> 27848271 | D8: 4922405.8 | E8: 4922405.8 | F8: 0 | G8: 3569499 | H8: 3569499 | I8: 0 | J8: 0 | K8: 0 | L8: 36286.458 | M8: 413359.7 | N8: 4744839.4 | O8: 12360.281 | P8: 190308.82 | Q8: 33293702
B9: CANNON LIFE ASSURANCE (K) LIMITED | C9: {='[1]APPENDIX 14'!$C9:$Q9} -> 0 | D9: 0 | E9: 0 | F9: 0 | G9: 0 | H9: 0 | I9: 0 | J9: 0 | K9: 0 | L9: 0 | M9: 0 | N9: 0 | O9: 0 | P9: 0 | Q9: 0
B10: CAPEX LIFE ASSURANCE COMPANY | C10: {='[1]APPENDIX 14'!$C10:$Q10} -> 0 | D10: 0 | E10: 0 | F10: 0 | G10: 0 | H10: 0 | I10: 0 | J10: 0 | K10: 0 | L10: 0 | M10: 0 | N10: 0 | O10: 0 | P10: 0 | Q10: 0
B11: CIC LIFE ASSURANCE COMPANY | C11: {='[1]APPENDIX 14'!$C11:$Q11} -> 0 | D11: 0 | E11: 0 | F11: 0 | G11: 0 | H11: 0 | I11: 0 | J11: 0 | K11: 0 | L11: 0 | M11: 0 | N11: 0 | O11: 0 | P11: 0 | Q11: 0
B12: CORPORATE INSURANCE COMPANY | C12: {='[1]APPENDIX 14'!$C12:$Q12} -> 0 | D12: 0 | E12: 0 | F12: 0 | G12: 0 | H12: 0 | I12: 0 | J12: 0 | K12: 0 | L12: 0 | M12: 0 | N12: 0 | O12: 0 | P12: 0 | Q12: 0
B13: EQUITY LIFE ASSURANCE | C13: {='[1]APPENDIX 14'!$C13:$Q13} -> 77385.645 | D13: 297501.74 | E13: 297501.74 | F13: 0 | G13: 0 | H13: 0 | I13: 0 | J13: 0 | K13: 0 | L13: 0 | M13: 0 | N13: 0 | O13: 0 | P13: 0 | Q13: 374887.39
B14: GA LIFE ASSURANCE COMPANY | C14: {='[1]APPENDIX 14'!$C14:$Q14} -> 4616086.6 | D14: 1124579.5 | E14: 1124579.5 | F14: 0 | G14: 609405.11 | H14: 609405.11 | I14: 0 | J14: 0 | K14: 0 | L14: 5998.369 | M14: 16878.123 | N14: 777105.29 | O14: 0 | P14: 25619.062 | Q14: 5859870.8
B15: GEMINIA LIFE INSURANCE COMPANY | C15: {='[1]APPENDIX 14'!$C15:$Q15} -> 66038.844 | D15: 64322.608 | E15: 64322.608 | F15: 0 | G15: 0 | H15: 0 | I15: 0 | J15: 0 | K15: 0 | L15: 1331.703 | M15: 0 | N15: 0 | O15: 0 | P15: 0 | Q15: 129029.75
B16: ICEA LION LIFE ASSURANCE | C16: {='[1]APPENDIX 14'!$C16:$Q16} -> 38845423 | D16: 7851350.6 | E16: 7851350.6 | F16: 0 | G16: 4049576.8 | H16: 4049576.8 | I16: 0 | J16: 0 | K16: 0 | L16: 82573.375 | M16: 270105.83 | N16: 6156443.6 | O16: 0 | P16: 0 | Q16: 48450961
B17: JUBILEE LIFE INSURANCE | C17: {='[1]APPENDIX 14'!$C17:$Q17} -> 8987123.4 | D17: 2545576 | E17: 2545576 | F17: 0 | G17: 1421413.6 | H17: 1421413.6 | I17: 0 | J17: 0 | K17: 0 | L17: 0 | M17: 128797.2 | N17: 436477.02 | O17: 4053.57 | P17: 0 | Q17: 10414912
... B30: THE MONARCH INSURANCE | C30: {='[1]APPENDIX 14'!$C30:$Q30} -> 0 | D30: 0 | E30: 0 | F30: 0 | G30: 0 | H30: 0 | I30: 0 | J30: 0 | K30: 0 | L30: 0 | M30: 0 | N30: 0 | O30: 0 | P30: 0 | Q30: 0
B31: TOTAL | C31: =SUM(C6:C30) -> 83930763 | D31: =SUM(D6:D30) -> 21729305 | E31: =SUM(E6:E30) -> 21729305 | F31: =SUM(F6:F30) -> 0 | G31: =SUM(G6:G30) -> 12343212 | H31: =SUM(H6:H30) -> 12383505 | I31: =SUM(I6:I30) -> 0 | J31: =SUM(J6:J30) -> -40292.717 | ... Q31: =SUM(Q6:Q30) -> 1.057317e+08
B32: REINSURERS
B33: CONTINENTAL REINSURANCE | C33: {='[1]APPENDIX 14'!$C33:$Q33} -> 0 | D33: 0 | E33: 0 | F33: 0 | G33: 0 | H33: 0 | I33: 0 | J33: 0 | K33: 0 | L33: 0 | M33: 0 | N33: 0 | O33: 0 | P33: 0 | Q33: 0
B34: EAST AFRICA REINSURANCE | C34: {='[1]APPENDIX 14'!$C34:$Q34} -> 0 | D34: 0 | E34: 0 | F34: 0 | G34: 0 | H34: 0 | I34: 0 | J34: 0 | K34: 0 | L34: 0 | M34: 0 | N34: 0 | O34: 0 | P34: 0 | Q34: 0
B35: KENYA REINSURANCE CORPORATION | C35: {='[1]APPENDIX 14'!$C35:$Q35} -> 0 | D35: 0 | E35: 0 | F35: 0 | G35: 0 | H35: 0 | I35: 0 | J35: 0 | K35: 0 | L35: 0 | M35: 0 | N35: 0 | O35: 0 | P35: 0 | Q35: 0
B36: TOTAL | C36: =SUM(C33:C35) -> 0 | D36: =SUM(D33:D35) -> 0 | E36: =SUM(E33:E35) -> 0 | F36: =SUM(F33:F35) -> 0 | G36: =SUM(G33:G35) -> 0 | H36: =SUM(H33:H35) -> 0 | I36: =SUM(I33:I35) -> 0 | J36: =SUM(J33:J35) -> 0 | ... Q36: =SUM(Q33:Q35) -> 0
B37: Amounts in Thousand Shillings

Sheet APPENDIX 15
B3: =_xlfn.CONCAT(Contents!E32,": ",UPPER(Contents!F32)) -> APPENDIX 15: SUMMARY OF DEPOSIT ADMINISTRATION BUSINESS REVENUE ACCOUNTS FOR THE YEAR ENDED 31.12.2024
B4: Company | C4: Life Fund BF | D4: Gross Premium | E4: Net Premium | F4: Other (Fee) Income | G4: Total Benefits | H4: Claims | I4: Surrenders_x000D_ | J4: Bonuses Paid | K4: Annuities Paid | L4: Net Commisions | M4: Expense of Management | N4: Investment Income | O4: Investment Expenses | P4: Transfer To (From) P & L | Q4: Life Fund CF
B5: INSURERS
B6: ABSA LIFE ASSURANCE | C6: {='[1]APPENDIX 15'!$C6:$Q6} -> 0 | D6: 0 | E6: 0 | F6: 0 | G6: 0 | H6: 0 | I6: 0 | J6: 0 | K6: 0 | L6: 0 | M6: 0 | N6: 0 | O6: 0 | P6: 0 | Q6: 0
B7: APA LIFE ASSURANCE COMPANY | C7: {='[1]APPENDIX 15'!$C7:$Q7} -> 8088731.4 | D7: 1474001.5 | E7: 1474001.5 | F7: 0 | G7: 901952.77 | H7: 901952.77 | I7: 0 | J7: 0 | K7: 0 | L7: 28004.86 | M7: 117308.7 | N7: 1292614.8 | O7: 23031.108 | P7: 51823.546 | Q7: 9733226.8
B8: BRITAM LIFE ASSURANCE | C8: {='[1]APPENDIX 15'!$C8:$Q8} -> 36844759 | D8: 7112670.9 | E8: 7112670.9 | F8: 0 | G8: 5694566 | H8: 5694566 | I8: 0 | J8: 0 | K8: 0 | L8: 48342.204 | M8: 597287.51 | N8: 6941928.6 | O8: 18083.686 | P8: 204509.08 | Q8: 44336570
B9: CANNON LIFE ASSURANCE (K) LIMITED | C9: {='[1]APPENDIX 15'!$C9:$Q9} -> 0 | D9: 0 | E9: 0 | F9: 0 | G9: 0 | H9: 0 | I9: 0 | J9: 0 | K9: 0 | L9: 0 | M9: 0 | N9: 0 | O9: 0 | P9: 0 | Q9: 0
B10: CAPEX LIFE ASSURANCE COMPANY | C10: {='[1]APPENDIX 15'!$C10:$Q10} -> 0 | D10: 0 | E10: 0 | F10: 0 | G10: 0 | H10: 0 | I10: 0 | J10: 0 | K10: 0 | L10: 0 | M10: 0 | N10: 0 | O10: 0 | P10: 0 | Q10: 0
B11: CIC LIFE ASSURANCE COMPANY | C11: {='[1]APPENDIX 15'!$C11:$Q11} -> 8380349 | D11: 4569003.3 | E11: 4569003.3 | F11: 0 | G11: 1926768.4 | H11: 1926768.4 | I11: 0 | J11: 0 | K11: 0 | L11: 87319.652 | M11: 92692.752 | N11: 2650197.9 | O11: 0 | P11: 0 | Q11: 13492770
B12: CORPORATE INSURANCE COMPANY | C12: {='[1]APPENDIX 15'!$C12:$Q12} -> 0 | D12: 0 | E12: 0 | F12: 0 | G12: 0 | H12: 0 | I12: 0 | J12: 0 | K12: 0 | L12: 0 | M12: 0 | N12: 0 | O12: 0 | P12: 0 | Q12: 0
B13: EQUITY LIFE ASSURANCE | C13: {='[1]APPENDIX 15'!$C13:$Q13} -> 11655864 | D13: 1607623.1 | E13: 1607623.1 | F13: 0 | G13: 0 | H13: 0 | I13: 0 | J13: 0 | K13: 0 | L13: 0 | M13: 5589.8243 | N13: 2084363.8 | O13: 1888171.3 | P13: 0 | Q13: 13454089
B14: GA LIFE ASSURANCE COMPANY | C14: {='[1]APPENDIX 15'!$C14:$Q14} -> 27881295 | D14: 5949888.1 | E14: 5949888.1 | F14: 0 | G14: 2639506.1 | H14: 2639506.1 | I14: 0 | J14: 0 | K14: 0 | L14: 51333.902 | M14: 101890.19 | N14: 4691244.4 | O14: 0 | P14: 149818.65 | Q14: 35579878
B15: GEMINIA LIFE INSURANCE COMPANY | C15: {='[1]APPENDIX 15'!$C15:$Q15} -> 567258.02 | D15: 743623.7 | E15: 743623.7 | F15: 0 | G15: 18479.858 | H15: 18479.858 | I15: 0 | J15: 0 | K15: 0 | L15: 0 | M15: 1241.9179 | N15: 0 | O15: 0 | P15: -547536.25 | Q15: 743623.7
B16: ICEA LION LIFE ASSURANCE | C16: {='[1]APPENDIX 15'!$C16:$Q16} -> 68286474 | D16: 10466116 | E16: 10466116 | F16: 0 | G16: 8001615.2 | H16: 8001615.2 | I16: 0 | J16: 0 | K16: 0 | L16: 242434.93 | M16: 489315.09 | N16: 11022180 | O16: 0 | P16: 0 | Q16: 81041405
B17: JUBILEE LIFE INSURANCE | C17: {='[1]APPENDIX 15'!$C17:$Q17} -> 75993889 | D17: 17575105 | E17: 17575105 | F17: 0 | G17: 7053962.1 | H17: 7053962.1 | I17: 0 | J17: 0 | K17: 0 | L17: 318054.92 | M17: 447219.01 | N17: 12209073 | O17: 91708.247 | P17: 728709.78 | Q17: 97138413
... B30: THE MONARCH INSURANCE | C30: {='[1]APPENDIX 15'!$C30:$Q30} -> 0 | D30: 0 | E30: 0 | F30: 0 | G30: 0 | H30: 0 | I30: 0 | J30: 0 | K30: 0 | L30: 0 | M30: 0 | N30: 0 | O30: 0 | P30: 0 | Q30: 0
B31: TOTAL | C31: =SUM(C6:C30) -> 3.1720103e+08 | D31: =SUM(D6:D30) -> 68244152 | E31: =SUM(E6:E30) -> 68244152 | F31: =SUM(F6:F30) -> 0 | G31: =SUM(G6:G30) -> 35160065 | H31: =SUM(H6:H30) -> 35169075 | I31: =SUM(I6:I30) -> 0 | J31: =SUM(J6:J30) -> -9010.3089 | ... Q31: =SUM(Q6:Q30) -> 3.9439235e+08
B32: REINSURERS
B33: CONTINENTAL REINSURANCE | C33: {='[1]APPENDIX 15'!$C33:$Q33} -> 0 | D33: 0 | E33: 0 | F33: 0 | G33: 0 | H33: 0 | I33: 0 | J33: 0 | K33: 0 | L33: 0 | M33: 0 | N33: 0 | O33: 0 | P33: 0 | Q33: 0
B34: EAST AFRICA REINSURANCE | C34: {='[1]APPENDIX 15'!$C34:$Q34} -> 0 | D34: 0 | E34: 0 | F34: 0 | G34: 0 | H34: 0 | I34: 0 | J34: 0 | K34: 0 | L34: 0 | M34: 0 | N34: 0 | O34: 0 | P34: 0 | Q34: 0
B35: KENYA REINSURANCE CORPORATION | C35: {='[1]APPENDIX 15'!$C35:$Q35} -> 0 | D35: 0 | E35: 0 | F35: 0 | G35: 0 | H35: 0 | I35: 0 | J35: 0 | K35: 0 | L35: 0 | M35: 0 | N35: 0 | O35: 0 | P35: 0 | Q35: 0
B36: TOTAL | C36: =SUM(C33:C35) -> 0 | D36: =SUM(D33:D35) -> 0 | E36: =SUM(E33:E35) -> 0 | F36: =SUM(F33:F35) -> 0 | G36: =SUM(G33:G35) -> 0 | H36: =SUM(H33:H35) -> 0 | I36: =SUM(I33:I35) -> 0 | J36: =SUM(J33:J35) -> 0 | ... Q36: =SUM(Q33:Q35) -> 0
B37: Amounts in Thousand Shillings

Sheet PERSONAL PENSIONS
B3: APPENDIX 16: SUMMARY OF PENSIONS BUSINESS REVENUE ACCOUNTS FOR THE YEAR ENDED 31.12.2022
B4: Company | C4: Life Fund BF | D4: Gross Premium | E4: Net Premium | F4: Other (Fee) Income | G4: Total Benefits | H4: Claims | I4: Surrenders_x000D_ | J4: Bonuses Paid | K4: Annuities Paid | L4: Net Commisions | M4: Expense of Management | N4: Investment Income | O4: Investment Expenses | P4: Transfer To (From) P & L | Q4: Life Fund CF
B5: INSURERS
B6: ABSA LIFE ASSURANCE | C6: =+'APPENDIX 14'!C6+'APPENDIX 15'!C6 -> 0 | D6: =+'APPENDIX 14'!D6+'APPENDIX 15'!D6 -> 0 | E6: =+'APPENDIX 14'!E6+'APPENDIX 15'!E6 -> 0 | F6: =+'APPENDIX 14'!F6+'APPENDIX 15'!F6 -> 0 | G6: =+'APPENDIX 14'!G6+'APPENDIX 15'!G6 -> 0 | H6: =+'APPENDIX 14'!H6+'APPENDIX 15'!H6 -> 0 | I6: =+'APPENDIX 14'!I6+'APPENDIX 15'!I6 -> 0 | J6: =+'APPENDIX 14'!J6+'APPENDIX 15'!J6 -> 0 | ... Q6: =+'APPENDIX 14'!Q6+'APPENDIX 15'!Q6 -> 0
B7: APA LIFE ASSURANCE COMPANY | C7: =+'APPENDIX 14'!C7+'APPENDIX 15'!C7 -> 8088731.4 | D7: =+'APPENDIX 14'!D7+'APPENDIX 15'!D7 -> 1474001.5 | E7: =+'APPENDIX 14'!E7+'APPENDIX 15'!E7 -> 1474001.5 | F7: =+'APPENDIX 14'!F7+'APPENDIX 15'!F7 -> 0 | G7: =+'APPENDIX 14'!G7+'APPENDIX 15'!G7 -> 901952.77 | H7: =+'APPENDIX 14'!H7+'APPENDIX 15'!H7 -> 901952.77 | I7: =+'APPENDIX 14'!I7+'APPENDIX 15'!I7 -> 0 | J7: =+'APPENDIX 14'!J7+'APPENDIX 15'!J7 -> 0 | ... Q7: =+'APPENDIX 14'!Q7+'APPENDIX 15'!Q7 -> 9733226.8
B8: BRITAM LIFE ASSURANCE | C8: =+'APPENDIX 14'!C8+'APPENDIX 15'!C8 -> 64693030 | D8: =+'APPENDIX 14'!D8+'APPENDIX 15'!D8 -> 12035077 | E8: =+'APPENDIX 14'!E8+'APPENDIX 15'!E8 -> 12035077 | F8: =+'APPENDIX 14'!F8+'APPENDIX 15'!F8 -> 0 | G8: =+'APPENDIX 14'!G8+'APPENDIX 15'!G8 -> 9264065 | H8: =+'APPENDIX 14'!H8+'APPENDIX 15'!H8 -> 9264065 | I8: =+'APPENDIX 14'!I8+'APPENDIX 15'!I8 -> 0 | J8: =+'APPENDIX 14'!J8+'APPENDIX 15'!J8 -> 0 | ... Q8: =+'APPENDIX 14'!Q8+'APPENDIX 15'!Q8 -> 77630272
B9: CANNON LIFE ASSURANCE (K) LIMITED | C9: =+'APPENDIX 14'!C9+'APPENDIX 15'!C9 -> 0 | D9: =+'APPENDIX 14'!D9+'APPENDIX 15'!D9 -> 0 | E9: =+'APPENDIX 14'!E9+'APPENDIX 15'!E9 -> 0 | F9: =+'APPENDIX 14'!F9+'APPENDIX 15'!F9 -> 0 | G9: =+'APPENDIX 14'!G9+'APPENDIX 15'!G9 -> 0 | H9: =+'APPENDIX 14'!H9+'APPENDIX 15'!H9 -> 0 | I9: =+'APPENDIX 14'!I9+'APPENDIX 15'!I9 -> 0 | J9: =+'APPENDIX 14'!J9+'APPENDIX 15'!J9 -> 0 | ... Q9: =+'APPENDIX 14'!Q9+'APPENDIX 15'!Q9 -> 0
B10: CAPEX LIFE ASSURANCE COMPANY | C10: =+'APPENDIX 14'!C10+'APPENDIX 15'!C10 -> 0 | D10: =+'APPENDIX 14'!D10+'APPENDIX 15'!D10 -> 0 | E10: =+'APPENDIX 14'!E10+'APPENDIX 15'!E10 -> 0 | F10: =+'APPENDIX 14'!F10+'APPENDIX 15'!F10 -> 0 | G10: =+'APPENDIX 14'!G10+'APPENDIX 15'!G10 -> 0 | H10: =+'APPENDIX 14'!H10+'APPENDIX 15'!H10 -> 0 | I10: =+'APPENDIX 14'!I10+'APPENDIX 15'!I10 -> 0 | J10: =+'APPENDIX 14'!J10+'APPENDIX 15'!J10 -> 0 | ... Q10: =+'APPENDIX 14'!Q10+'APPENDIX 15'!Q10 -> 0
B11: CIC LIFE ASSURANCE COMPANY | C11: =+'APPENDIX 14'!C11+'APPENDIX 15'!C11 -> 8380349 | D11: =+'APPENDIX 14'!D11+'APPENDIX 15'!D11 -> 4569003.3 | E11: =+'APPENDIX 14'!E11+'APPENDIX 15'!E11 -> 4569003.3 | F11: =+'APPENDIX 14'!F11+'APPENDIX 15'!F11 -> 0 | G11: =+'APPENDIX 14'!G11+'APPENDIX 15'!G11 -> 1926768.4 | H11: =+'APPENDIX 14'!H11+'APPENDIX 15'!H11 -> 1926768.4 | I11: =+'APPENDIX 14'!I11+'APPENDIX 15'!I11 -> 0 | J11: =+'APPENDIX 14'!J11+'APPENDIX 15'!J11 -> 0 | ... Q11: =+'APPENDIX 14'!Q11+'APPENDIX 15'!Q11 -> 13492770
B12: CORPORATE INSURANCE COMPANY | C12: =+'APPENDIX 14'!C12+'APPENDIX 15'!C12 -> 0 | D12: =+'APPENDIX 14'!D12+'APPENDIX 15'!D12 -> 0 | E12: =+'APPENDIX 14'!E12+'APPENDIX 15'!E12 -> 0 | F12: =+'APPENDIX 14'!F12+'APPENDIX 15'!F12 -> 0 | G12: =+'APPENDIX 14'!G12+'APPENDIX 15'!G12 -> 0 | H12: =+'APPENDIX 14'!H12+'APPENDIX 15'!H12 -> 0 | I12: =+'APPENDIX 14'!I12+'APPENDIX 15'!I12 -> 0 | J12: =+'APPENDIX 14'!J12+'APPENDIX 15'!J12 -> 0 | ... Q12: =+'APPENDIX 14'!Q12+'APPENDIX 15'!Q12 -> 0
B13: EQUITY LIFE ASSURANCE | C13: =+'APPENDIX 14'!C13+'APPENDIX 15'!C13 -> 11733249 | D13: =+'APPENDIX 14'!D13+'APPENDIX 15'!D13 -> 1905124.8 | E13: =+'APPENDIX 14'!E13+'APPENDIX 15'!E13 -> 1905124.8 | F13: =+'APPENDIX 14'!F13+'APPENDIX 15'!F13 -> 0 | G13: =+'APPENDIX 14'!G13+'APPENDIX 15'!G13 -> 0 | H13: =+'APPENDIX 14'!H13+'APPENDIX 15'!H13 -> 0 | I13: =+'APPENDIX 14'!I13+'APPENDIX 15'!I13 -> 0 | J13: =+'APPENDIX 14'!J13+'APPENDIX 15'!J13 -> 0 | ... Q13: =+'APPENDIX 14'!Q13+'APPENDIX 15'!Q13 -> 13828977
B14: GA LIFE ASSURANCE COMPANY | C14: =+'APPENDIX 14'!C14+'APPENDIX 15'!C14 -> 32497381 | D14: =+'APPENDIX 14'!D14+'APPENDIX 15'!D14 -> 7074467.6 | E14: =+'APPENDIX 14'!E14+'APPENDIX 15'!E14 -> 7074467.6 | F14: =+'APPENDIX 14'!F14+'APPENDIX 15'!F14 -> 0 | G14: =+'APPENDIX 14'!G14+'APPENDIX 15'!G14 -> 3248911.2 | H14: =+'APPENDIX 14'!H14+'APPENDIX 15'!H14 -> 3248911.2 | I14: =+'APPENDIX 14'!I14+'APPENDIX 15'!I14 -> 0 | J14: =+'APPENDIX 14'!J14+'APPENDIX 15'!J14 -> 0 | ... Q14: =+'APPENDIX 14'!Q14+'APPENDIX 15'!Q14 -> 41439749
B15: GEMINIA LIFE INSURANCE COMPANY | C15: =+'APPENDIX 14'!C15+'APPENDIX 15'!C15 -> 633296.86 | D15: =+'APPENDIX 14'!D15+'APPENDIX 15'!D15 -> 807946.31 | E15: =+'APPENDIX 14'!E15+'APPENDIX 15'!E15 -> 807946.31 | F15: =+'APPENDIX 14'!F15+'APPENDIX 15'!F15 -> 0 | G15: =+'APPENDIX 14'!G15+'APPENDIX 15'!G15 -> 18479.858 | H15: =+'APPENDIX 14'!H15+'APPENDIX 15'!H15 -> 18479.858 | I15: =+'APPENDIX 14'!I15+'APPENDIX 15'!I15 -> 0 | J15: =+'APPENDIX 14'!J15+'APPENDIX 15'!J15 -> 0 | ... Q15: =+'APPENDIX 14'!Q15+'APPENDIX 15'!Q15 -> 872653.45
B16: ICEA LION LIFE ASSURANCE | C16: =+'APPENDIX 14'!C16+'APPENDIX 15'!C16 -> 1.071319e+08 | D16: =+'APPENDIX 14'!D16+'APPENDIX 15'!D16 -> 18317466 | E16: =+'APPENDIX 14'!E16+'APPENDIX 15'!E16 -> 18317466 | F16: =+'APPENDIX 14'!F16+'APPENDIX 15'!F16 -> 0 | G16: =+'APPENDIX 14'!G16+'APPENDIX 15'!G16 -> 12051192 | H16: =+'APPENDIX 14'!H16+'APPENDIX 15'!H16 -> 12051192 | I16: =+'APPENDIX 14'!I16+'APPENDIX 15'!I16 -> 0 | J16: =+'APPENDIX 14'!J16+'APPENDIX 15'!J16 -> 0 | ... Q16: =+'APPENDIX 14'!Q16+'APPENDIX 15'!Q16 -> 1.2949237e+08
B17: JUBILEE INSURANCE COMPANY | C17: =+'APPENDIX 14'!C17+'APPENDIX 15'!C17 -> 84981013 | D17: =+'APPENDIX 14'!D17+'APPENDIX 15'!D17 -> 20120681 | E17: =+'APPENDIX 14'!E17+'APPENDIX 15'!E17 -> 20120681 | F17: =+'APPENDIX 14'!F17+'APPENDIX 15'!F17 -> 0 | G17: =+'APPENDIX 14'!G17+'APPENDIX 15'!G17 -> 8475375.8 | H17: =+'APPENDIX 14'!H17+'APPENDIX 15'!H17 -> 8475375.8 | I17: =+'APPENDIX 14'!I17+'APPENDIX 15'!I17 -> 0 | J17: =+'APPENDIX 14'!J17+'APPENDIX 15'!J17 -> 0 | ... Q17: =+'APPENDIX 14'!Q17+'APPENDIX 15'!Q17 -> 1.0755333e+08
... B30: THE MONARCH INSURANCE | C30: =+'APPENDIX 14'!C30+'APPENDIX 15'!C30 -> 0 | D30: =+'APPENDIX 14'!D30+'APPENDIX 15'!D30 -> 0 | E30: =+'APPENDIX 14'!E30+'APPENDIX 15'!E30 -> 0 | F30: =+'APPENDIX 14'!F30+'APPENDIX 15'!F30 -> 0 | G30: =+'APPENDIX 14'!G30+'APPENDIX 15'!G30 -> 0 | H30: =+'APPENDIX 14'!H30+'APPENDIX 15'!H30 -> 0 | I30: =+'APPENDIX 14'!I30+'APPENDIX 15'!I30 -> 0 | J30: =+'APPENDIX 14'!J30+'APPENDIX 15'!J30 -> 0 | ... Q30: =+'APPENDIX 14'!Q30+'APPENDIX 15'!Q30 -> 0
B31: TOTAL | C31: =SUM(C6:C30) -> 4.0113179e+08 | D31: =SUM(D6:D30) -> 89973456 | E31: =SUM(E6:E30) -> 89973456 | F31: =SUM(F6:F30) -> 0 | G31: =SUM(G6:G30) -> 47503277 | H31: =SUM(H6:H30) -> 47552580 | I31: =SUM(I6:I30) -> 0 | J31: =SUM(J6:J30) -> -49303.026 | ... Q31: =SUM(Q6:Q30) -> 5.0012404e+08
B32: REINSURERS
B33: CONTINENTAL REINSURANCE | C33: =+'APPENDIX 14'!C33+'APPENDIX 15'!C33 -> 0 | D33: =+'APPENDIX 14'!D33+'APPENDIX 15'!D33 -> 0 | E33: =+'APPENDIX 14'!E33+'APPENDIX 15'!E33 -> 0 | F33: =+'APPENDIX 14'!F33+'APPENDIX 15'!F33 -> 0 | G33: =+'APPENDIX 14'!G33+'APPENDIX 15'!G33 -> 0 | H33: =+'APPENDIX 14'!H33+'APPENDIX 15'!H33 -> 0 | I33: =+'APPENDIX 14'!I33+'APPENDIX 15'!I33 -> 0 | J33: =+'APPENDIX 14'!J33+'APPENDIX 15'!J33 -> 0 | ... Q33: =+'APPENDIX 14'!Q33+'APPENDIX 15'!Q33 -> 0
B34: EAST AFRICA REINSURANCE | C34: =+'APPENDIX 14'!C34+'APPENDIX 15'!C34 -> 0 | D34: =+'APPENDIX 14'!D34+'APPENDIX 15'!D34 -> 0 | E34: =+'APPENDIX 14'!E34+'APPENDIX 15'!E34 -> 0 | F34: =+'APPENDIX 14'!F34+'APPENDIX 15'!F34 -> 0 | G34: =+'APPENDIX 14'!G34+'APPENDIX 15'!G34 -> 0 | H34: =+'APPENDIX 14'!H34+'APPENDIX 15'!H34 -> 0 | I34: =+'APPENDIX 14'!I34+'APPENDIX 15'!I34 -> 0 | J34: =+'APPENDIX 14'!J34+'APPENDIX 15'!J34 -> 0 | ... Q34: =+'APPENDIX 14'!Q34+'APPENDIX 15'!Q34 -> 0
B35: KENYA REINSURANCE CORPORATION | C35: =+'APPENDIX 14'!C35+'APPENDIX 15'!C35 -> 0 | D35: =+'APPENDIX 14'!D35+'APPENDIX 15'!D35 -> 0 | E35: =+'APPENDIX 14'!E35+'APPENDIX 15'!E35 -> 0 | F35: =+'APPENDIX 14'!F35+'APPENDIX 15'!F35 -> 0 | G35: =+'APPENDIX 14'!G35+'APPENDIX 15'!G35 -> 0 | H35: =+'APPENDIX 14'!H35+'APPENDIX 15'!H35 -> 0 | I35: =+'APPENDIX 14'!I35+'APPENDIX 15'!I35 -> 0 | J35: =+'APPENDIX 14'!J35+'APPENDIX 15'!J35 -> 0 | ... Q35: =+'APPENDIX 14'!Q35+'APPENDIX 15'!Q35 -> 0
B36: TOTAL | C36: =SUM(C33:C35) -> 0 | D36: =SUM(D33:D35) -> 0 | E36: =SUM(E33:E35) -> 0 | F36: =SUM(F33:F35) -> 0 | G36: =SUM(G33:G35) -> 0 | H36: =SUM(H33:H35) -> 0 | I36: =SUM(I33:I35) -> 0 | J36: =SUM(J33:J35) -> 0 | ... Q36: =SUM(Q33:Q35) -> 0
B37: Amounts in Thousand Shillings

Sheet UNIT LINKED AND LINKED
B3: APPENDIX 16: SUMMARY OF PENSIONS BUSINESS REVENUE ACCOUNTS FOR THE YEAR ENDED 31.12.2022
B4: Company | C4: Life Fund BF | D4: Gross Premium | E4: Net Premium | F4: Other (Fee) Income | G4: Total Benefits | H4: Claims | I4: Surrenders_x000D_ | J4: Bonuses Paid | K4: Annuities Paid | L4: Net Commisions | M4: Expense of Management | N4: Investment Income | O4: Investment Expenses | P4: Transfer To (From) P & L | Q4: Life Fund CF
B5: INSURERS
B6: ABSA LIFE ASSURANCE | C6: 0 | D6: 0 | E6: 0 | F6: 0 | G6: 0 | H6: 0 | I6: 0 | J6: 0 | K6: 0 | L6: 0 | M6: 0 | N6: 0 | O6: 0 | P6: 0 | Q6: 0
B7: APA LIFE ASSURANCE COMPANY | C7: 0 | D7: 0 | E7: 0 | F7: 0 | G7: 0 | H7: 0 | I7: 0 | J7: 0 | K7: 0 | L7: 0 | M7: 0 | N7: 0 | O7: 0 | P7: 0 | Q7: 0
B8: BRITAM LIFE ASSURANCE | C8: 4537873.7 | D8: 4947421.3 | E8: 4947421.3 | F8: 0 | G8: 2906826.7 | H8: 2906826.7 | I8: 0 | J8: 0 | K8: 0 | L8: 24112.414 | M8: 140170.69 | N8: 1343216.9 | O8: 13295.842 | P8: 224430.37 | Q8: 7519675.8
B9: CANNON LIFE ASSURANCE (K) LIMITED | C9: 134570.41 | D9: 0 | E9: 0 | F9: 0 | G9: 0 | H9: 0 | I9: 0 | J9: 0 | K9: 0 | L9: 0 | M9: 34086.434 | N9: 17784.33 | O9: 0 | P9: 0 | Q9: 118268.31
B10: CAPEX LIFE ASSURANCE COMPANY | C10: 0 | D10: 0 | E10: 0 | F10: 0 | G10: 0 | H10: 0 | I10: 0 | J10: 0 | K10: 0 | L10: 0 | M10: 0 | N10: 0 | O10: 0 | P10: 0 | Q10: 0
B11: CIC LIFE ASSURANCE COMPANY | C11: 0 | D11: 0 | E11: 0 | F11: 0 | G11: 0 | H11: 0 | I11: 0 | J11: 0 | K11: 0 | L11: 0 | M11: 0 | N11: 0 | O11: 0 | P11: 0 | Q11: 0
B12: CORPORATE INSURANCE COMPANY | C12: 0 | D12: 0 | E12: 0 | F12: 0 | G12: 0 | H12: 0 | I12: 0 | J12: 0 | K12: 0 | L12: 0 | M12: 0 | N12: 0 | O12: 0 | P12: 0 | Q12: 0
B13: EQUITY LIFE ASSURANCE | C13: 0 | D13: 0 | E13: 0 | F13: 0 | G13: 0 | H13: 0 | I13: 0 | J13: 0 | K13: 0 | L13: 0 | M13: 0 | N13: 0 | O13: 0 | P13: 0 | Q13: 0
B14: GA LIFE ASSURANCE COMPANY | C14: 0 | D14: 0 | E14: 0 | F14: 0 | G14: 0 | H14: 0 | I14: 0 | J14: 0 | K14: 0 | L14: 0 | M14: 0 | N14: 0 | O14: 0 | P14: 0 | Q14: 0
B15: GEMINIA LIFE INSURANCE COMPANY | C15: 0 | D15: 0 | E15: 0 | F15: 0 | G15: 0 | H15: 0 | I15: 0 | J15: 0 | K15: 0 | L15: 0 | M15: 0 | N15: 0 | O15: 0 | P15: 0 | Q15: 0
B16: ICEA LION LIFE ASSURANCE | C16: 206055.61 | D16: 7160.1264 | E16: 7160.1264 | F16: 0 | G16: 41425.796 | H16: 35534.765 | I16: 5891.0306 | J16: 0 | K16: 0 | L16: 0 | M16: 71.601264 | N16: 268545.14 | O16: 0 | P16: 0 | Q16: 440263.48
B17: JUBILEE INSURANCE COMPANY | C17: 0 | D17: 71722.042 | E17: 71722.042 | F17: 0 | G17: 0 | H17: 0 | I17: 0 | J17: 0 | K17: 0 | L17: 0 | M17: 1375.3737 | N17: 0 | O17: 0 | P17: 0 | Q17: 70346.668
... B30: THE MONARCH INSURANCE | C30: 0 | D30: 0 | E30: 0 | F30: 0 | G30: 0 | H30: 0 | I30: 0 | J30: 0 | K30: 0 | L30: 0 | M30: 0 | N30: 0 | O30: 0 | P30: 0 | Q30: 0
B31: TOTAL | C31: =SUM(C6:C30) -> 12657494 | D31: =SUM(D6:D30) -> 6848834.5 | E31: =SUM(E6:E30) -> 6848784.4 | F31: =SUM(F6:F30) -> 0 | G31: =SUM(G6:G30) -> 6311499.5 | H31: =SUM(H6:H30) -> 6305608.5 | I31: =SUM(I6:I30) -> 5891.0306 | J31: =SUM(J6:J30) -> 0 | ... Q31: =SUM(Q6:Q30) -> 15720233
B32: REINSURERS
B33: CONTINENTAL REINSURANCE | C33: 0 | D33: 0 | E33: 0 | F33: 0 | G33: 0 | H33: 0 | I33: 0 | J33: 0 | K33: 0 | L33: 0 | M33: 0 | N33: 0 | O33: 0 | P33: 0 | Q33: 0
B34: EAST AFRICA REINSURANCE | C34: 0 | D34: 0 | E34: 0 | F34: 0 | G34: 0 | H34: 0 | I34: 0 | J34: 0 | K34: 0 | L34: 0 | M34: 0 | N34: 0 | O34: 0 | P34: 0 | Q34: 0
B35: KENYA REINSURANCE CORPORATION | C35: 0 | D35: 0 | E35: 0 | F35: 0 | G35: 0 | H35: 0 | I35: 0 | J35: 0 | K35: 0 | L35: 0 | M35: 0 | N35: 0 | O35: 0 | P35: 0 | Q35: 0
B36: TOTAL | C36: =SUM(C33:C35) -> 0 | D36: =SUM(D33:D35) -> 0 | E36: =SUM(E33:E35) -> 0 | F36: =SUM(F33:F35) -> 0 | G36: =SUM(G33:G35) -> 0 | H36: =SUM(H33:H35) -> 0 | I36: =SUM(I33:I35) -> 0 | J36: =SUM(J33:J35) -> 0 | ... Q36: =SUM(Q33:Q35) -> 0
B37: Amounts in Thousand Shillings

Sheet NON-LINKED
B3: APPENDIX 16: SUMMARY OF PENSIONS BUSINESS REVENUE ACCOUNTS FOR THE YEAR ENDED 31.12.2022
B4: Company | C4: Life Fund BF | D4: Gross Premium | E4: Net Premium | F4: Other (Fee) Income | G4: Total Benefits | H4: Claims | I4: Surrenders_x000D_ | J4: Bonuses Paid | K4: Annuities Paid | L4: Net Commisions | M4: Expense of Management | N4: Investment Income | O4: Investment Expenses | P4: Transfer To (From) P & L | Q4: Life Fund CF
B5: INSURERS
B6: ABSA LIFE ASSURANCE | C6: 0 | D6: 0 | E6: 0 | F6: 0 | G6: 0 | H6: 0 | I6: 0 | J6: 0 | K6: 0 | L6: 0 | M6: 0 | N6: 0 | O6: 0 | P6: 0 | Q6: 0
B7: APA LIFE ASSURANCE COMPANY | C7: 899994.11 | D7: 933309.69 | E7: 933309.69 | F7: 0 | G7: 195366.2 | H7: 195366.2 | I7: 0 | J7: 0 | K7: 0 | L7: 46665.485 | M7: 0 | N7: 222742.81 | O7: 5724.469 | P7: 0 | Q7: 1808290.5
B8: BRITAM LIFE ASSURANCE | C8: 0 | D8: 0 | E8: 0 | F8: 0 | G8: 0 | H8: 0 | I8: 0 | J8: 0 | K8: 0 | L8: 0 | M8: 0 | N8: 0 | O8: 0 | P8: 0 | Q8: 0
B9: CANNON LIFE ASSURANCE (K) LIMITED | C9: 0 | D9: 0 | E9: 0 | F9: 0 | G9: 0 | H9: 0 | I9: 0 | J9: 0 | K9: 0 | L9: 0 | M9: 0 | N9: 0 | O9: 0 | P9: 0 | Q9: 0
B10: CAPEX LIFE ASSURANCE COMPANY | C10: 0 | D10: 0 | E10: 0 | F10: 0 | G10: 0 | H10: 0 | I10: 0 | J10: 0 | K10: 0 | L10: 0 | M10: 0 | N10: 0 | O10: 0 | P10: 0 | Q10: 0
B11: CIC LIFE ASSURANCE COMPANY | C11: 0 | D11: 0 | E11: 0 | F11: 0 | G11: 0 | H11: 0 | I11: 0 | J11: 0 | K11: 0 | L11: 0 | M11: 0 | N11: 0 | O11: 0 | P11: 0 | Q11: 0
B12: CORPORATE INSURANCE COMPANY | C12: 0 | D12: 0 | E12: 0 | F12: 0 | G12: 0 | H12: 0 | I12: 0 | J12: 0 | K12: 0 | L12: 0 | M12: 0 | N12: 0 | O12: 0 | P12: 0 | Q12: 0
B13: EQUITY LIFE ASSURANCE | C13: 494765.08 | D13: -177476.25 | E13: -177476.25 | F13: 0 | G13: 0 | H13: 0 | I13: 0 | J13: 0 | K13: 0 | L13: 0 | M13: 0 | N13: 0 | O13: 0 | P13: 0 | Q13: 317288.83
B14: GA LIFE ASSURANCE COMPANY | C14: 0 | D14: 0 | E14: 0 | F14: 0 | G14: 0 | H14: 0 | I14: 0 | J14: 0 | K14: 0 | L14: 0 | M14: 0 | N14: 0 | O14: 0 | P14: 0 | Q14: 0
B15: GEMINIA LIFE INSURANCE COMPANY | C15: 18404.926 | D15: 90519.786 | E15: 90519.786 | F15: 0 | G15: 15660.383 | H15: 23928.934 | I15: -8268.5505 | J15: 0 | K15: 0 | L15: 0 | M15: 2744.5425 | N15: 0 | O15: 0 | P15: 0 | Q15: 90519.786
B16: ICEA LION LIFE ASSURANCE | C16: 0 | D16: 0 | E16: 0 | F16: 0 | G16: 0 | H16: 0 | I16: 0 | J16: 0 | K16: 0 | L16: 0 | M16: 0 | N16: 0 | O16: 0 | P16: 0 | Q16: 0
B17: JUBILEE INSURANCE COMPANY | C17: 0 | D17: 0 | E17: 0 | F17: 0 | G17: 0 | H17: 0 | I17: 0 | J17: 0 | K17: 0 | L17: 0 | M17: 0 | N17: 0 | O17: 0 | P17: 0 | Q17: 0
... B30: THE MONARCH INSURANCE | C30: 0 | D30: 0 | E30: 0 | F30: 0 | G30: 0 | H30: 0 | I30: 0 | J30: 0 | K30: 0 | L30: 0 | M30: 0 | N30: 0 | O30: 0 | P30: 0 | Q30: 0
B31: TOTAL | C31: =SUM(C6:C30) -> 2148120.7 | D31: =SUM(D6:D30) -> 932583.8 | E31: =SUM(E6:E30) -> 932583.8 | F31: =SUM(F6:F30) -> 0 | G31: =SUM(G6:G30) -> 337143.35 | H31: =SUM(H6:H30) -> 309552.98 | I31: =SUM(I6:I30) -> -8268.5505 | J31: =SUM(J6:J30) -> 35858.923 | ... Q31: =SUM(Q6:Q30) -> 3341530.2
B32: REINSURERS
B33: CONTINENTAL REINSURANCE | C33: 0 | D33: 0 | E33: 0 | F33: 0 | G33: 0 | H33: 0 | I33: 0 | J33: 0 | K33: 0 | L33: 0 | M33: 0 | N33: 0 | O33: 0 | P33: 0 | Q33: 0
B34: EAST AFRICA REINSURANCE | C34: 0 | D34: 0 | E34: 0 | F34: 0 | G34: 0 | H34: 0 | I34: 0 | J34: 0 | K34: 0 | L34: 0 | M34: 0 | N34: 0 | O34: 0 | P34: 0 | Q34: 0
B35: KENYA REINSURANCE CORPORATION | C35: 0 | D35: 0 | E35: 0 | F35: 0 | G35: 0 | H35: 0 | I35: 0 | J35: 0 | K35: 0 | L35: 0 | M35: 0 | N35: 0 | O35: 0 | P35: 0 | Q35: 0
B36: TOTAL | C36: =SUM(C33:C35) -> 0 | D36: =SUM(D33:D35) -> 0 | E36: =SUM(E33:E35) -> 0 | F36: =SUM(F33:F35) -> 0 | G36: =SUM(G33:G35) -> 0 | H36: =SUM(H33:H35) -> 0 | I36: =SUM(I33:I35) -> 0 | J36: =SUM(J33:J35) -> 0 | ... Q36: =SUM(Q33:Q35) -> 0
B37: Amounts in Thousand Shillings

Sheet PERSONAL PERMANENT HEALTH
B3: APPENDIX 16: SUMMARY OF PENSIONS BUSINESS REVENUE ACCOUNTS FOR THE YEAR ENDED 31.12.2022
B4: Company | C4: Life Fund BF | D4: Gross Premium | E4: Net Premium | F4: Other (Fee) Income | G4: Total Benefits | H4: Claims | I4: Surrenders_x000D_ | J4: Bonuses Paid | K4: Annuities Paid | L4: Net Commisions | M4: Expense of Management | N4: Investment Income | O4: Investment Expenses | P4: Transfer To (From) P & L | Q4: Life Fund CF
B5: INSURERS
B6: ABSA LIFE ASSURANCE | C6: 0 | D6: 0 | E6: 0 | F6: 0 | G6: 0 | H6: 0 | I6: 0 | J6: 0 | K6: 0 | L6: 0 | M6: 0 | N6: 0 | O6: 0 | P6: 0 | Q6: 0
B7: APA LIFE ASSURANCE COMPANY | C7: 0 | D7: 0 | E7: 0 | F7: 0 | G7: 0 | H7: 0 | I7: 0 | J7: 0 | K7: 0 | L7: 0 | M7: 0 | N7: 0 | O7: 0 | P7: 0 | Q7: 0
B8: BRITAM LIFE ASSURANCE | C8: 0 | D8: 0 | E8: 0 | F8: 0 | G8: 0 | H8: 0 | I8: 0 | J8: 0 | K8: 0 | L8: 0 | M8: 0 | N8: 0 | O8: 0 | P8: 0 | Q8: 0
B9: CANNON LIFE ASSURANCE (K) LIMITED | C9: 0 | D9: 0 | E9: 0 | F9: 0 | G9: 0 | H9: 0 | I9: 0 | J9: 0 | K9: 0 | L9: 0 | M9: 0 | N9: 0 | O9: 0 | P9: 0 | Q9: 0
B10: CAPEX LIFE ASSURANCE COMPANY | C10: 0 | D10: 0 | E10: 0 | F10: 0 | G10: 0 | H10: 0 | I10: 0 | J10: 0 | K10: 0 | L10: 0 | M10: 0 | N10: 0 | O10: 0 | P10: 0 | Q10: 0
B11: CIC LIFE ASSURANCE COMPANY | C11: 0 | D11: 0 | E11: 0 | F11: 0 | G11: 0 | H11: 0 | I11: 0 | J11: 0 | K11: 0 | L11: 0 | M11: 0 | N11: 0 | O11: 0 | P11: 0 | Q11: 0
B12: CORPORATE INSURANCE COMPANY | C12: 0 | D12: 0 | E12: 0 | F12: 0 | G12: 0 | H12: 0 | I12: 0 | J12: 0 | K12: 0 | L12: 0 | M12: 0 | N12: 0 | O12: 0 | P12: 0 | Q12: 0
B13: EQUITY LIFE ASSURANCE | C13: 0 | D13: 0 | E13: 0 | F13: 0 | G13: 0 | H13: 0 | I13: 0 | J13: 0 | K13: 0 | L13: 0 | M13: 0 | N13: 0 | O13: 0 | P13: 0 | Q13: 0
B14: GA LIFE ASSURANCE COMPANY | C14: 0 | D14: 0 | E14: 0 | F14: 0 | G14: 0 | H14: 0 | I14: 0 | J14: 0 | K14: 0 | L14: 0 | M14: 0 | N14: 0 | O14: 0 | P14: 0 | Q14: 0
B15: GEMINIA LIFE INSURANCE COMPANY | C15: 0 | D15: 0 | E15: 0 | F15: 0 | G15: 0 | H15: 0 | I15: 0 | J15: 0 | K15: 0 | L15: 0 | M15: 0 | N15: 0 | O15: 0 | P15: 0 | Q15: 0
B16: ICEA LION LIFE ASSURANCE | C16: 0 | D16: 0 | E16: 0 | F16: 0 | G16: 0 | H16: 0 | I16: 0 | J16: 0 | K16: 0 | L16: 0 | M16: 0 | N16: 0 | O16: 0 | P16: 0 | Q16: 0
B17: JUBILEE INSURANCE COMPANY | C17: 0 | D17: 0 | E17: 0 | F17: 0 | G17: 0 | H17: 0 | I17: 0 | J17: 0 | K17: 0 | L17: 0 | M17: 0 | N17: 0 | O17: 0 | P17: 0 | Q17: 0
... B30: THE MONARCH INSURANCE | C30: 0 | D30: 0 | E30: 0 | F30: 0 | G30: 0 | H30: 0 | I30: 0 | J30: 0 | K30: 0 | L30: 0 | M30: 0 | N30: 0 | O30: 0 | P30: 0 | Q30: 0
B31: TOTAL | C31: =SUM(C6:C30) -> 0 | D31: =SUM(D6:D30) -> 0 | E31: =SUM(E6:E30) -> 0 | F31: =SUM(F6:F30) -> 0 | G31: =SUM(G6:G30) -> 0 | H31: =SUM(H6:H30) -> 0 | I31: =SUM(I6:I30) -> 0 | J31: =SUM(J6:J30) -> 0 | ... Q31: =SUM(Q6:Q30) -> 0
B32: REINSURERS
B33: CONTINENTAL REINSURANCE | C33: 0 | D33: 0 | E33: 0 | F33: 0 | G33: 0 | H33: 0 | I33: 0 | J33: 0 | K33: 0 | L33: 0 | M33: 0 | N33: 0 | O33: 0 | P33: 0 | Q33: 0
B34: EAST AFRICA REINSURANCE | C34: 0 | D34: 0 | E34: 0 | F34: 0 | G34: 0 | H34: 0 | I34: 0 | J34: 0 | K34: 0 | L34: 0 | M34: 0 | N34: 0 | O34: 0 | P34: 0 | Q34: 0
B35: KENYA REINSURANCE CORPORATION | C35: 0 | D35: 0 | E35: 0 | F35: 0 | G35: 0 | H35: 0 | I35: 0 | J35: 0 | K35: 0 | L35: 0 | M35: 0 | N35: 0 | O35: 0 | P35: 0 | Q35: 0
B36: TOTAL | C36: =SUM(C33:C35) -> 0 | D36: =SUM(D33:D35) -> 0 | E36: =SUM(E33:E35) -> 0 | F36: =SUM(F33:F35) -> 0 | G36: =SUM(G33:G35) -> 0 | H36: =SUM(H33:H35) -> 0 | I36: =SUM(I33:I35) -> 0 | J36: =SUM(J33:J35) -> 0 | ... Q36: =SUM(Q33:Q35) -> 0
B37: Amounts in Thousand Shillings

Sheet GROUP PERMANENT HEALTH
B3: APPENDIX 16: SUMMARY OF PENSIONS BUSINESS REVENUE ACCOUNTS FOR THE YEAR ENDED 31.12.2022
B4: Company | C4: Life Fund BF | D4: Gross Premium | E4: Net Premium | F4: Other (Fee) Income | G4: Total Benefits | H4: Claims | I4: Surrenders_x000D_ | J4: Bonuses Paid | K4: Annuities Paid | L4: Net Commisions | M4: Expense of Management | N4: Investment Income | O4: Investment Expenses | P4: Transfer To (From) P & L | Q4: Life Fund CF
B5: INSURERS
B6: ABSA LIFE ASSURANCE | C6: 0 | D6: 0 | E6: 0 | F6: 0 | G6: 0 | H6: 0 | I6: 0 | J6: 0 | K6: 0 | L6: 0 | M6: 0 | N6: 0 | O6: 0 | P6: 0 | Q6: 0
B7: APA LIFE ASSURANCE COMPANY | C7: 0 | D7: 0 | E7: 0 | F7: 0 | G7: 0 | H7: 0 | I7: 0 | J7: 0 | K7: 0 | L7: 0 | M7: 0 | N7: 0 | O7: 0 | P7: 0 | Q7: 0
B8: BRITAM LIFE ASSURANCE | C8: 0 | D8: 0 | E8: 0 | F8: 0 | G8: 0 | H8: 0 | I8: 0 | J8: 0 | K8: 0 | L8: 0 | M8: 0 | N8: 0 | O8: 0 | P8: 0 | Q8: 0
B9: CANNON LIFE ASSURANCE (K) LIMITED | C9: 0 | D9: 0 | E9: 0 | F9: 0 | G9: 0 | H9: 0 | I9: 0 | J9: 0 | K9: 0 | L9: 0 | M9: 0 | N9: 0 | O9: 0 | P9: 0 | Q9: 0
B10: CAPEX LIFE ASSURANCE COMPANY | C10: 0 | D10: 0 | E10: 0 | F10: 0 | G10: 0 | H10: 0 | I10: 0 | J10: 0 | K10: 0 | L10: 0 | M10: 0 | N10: 0 | O10: 0 | P10: 0 | Q10: 0
B11: CIC LIFE ASSURANCE COMPANY | C11: 0 | D11: 0 | E11: 0 | F11: 0 | G11: 0 | H11: 0 | I11: 0 | J11: 0 | K11: 0 | L11: 0 | M11: 0 | N11: 0 | O11: 0 | P11: 0 | Q11: 0
B12: CORPORATE INSURANCE COMPANY | C12: 0 | D12: 0 | E12: 0 | F12: 0 | G12: 0 | H12: 0 | I12: 0 | J12: 0 | K12: 0 | L12: 0 | M12: 0 | N12: 0 | O12: 0 | P12: 0 | Q12: 0
B13: EQUITY LIFE ASSURANCE | C13: 0 | D13: 0 | E13: 0 | F13: 0 | G13: 0 | H13: 0 | I13: 0 | J13: 0 | K13: 0 | L13: 0 | M13: 0 | N13: 0 | O13: 0 | P13: 0 | Q13: 0
B14: GA LIFE ASSURANCE COMPANY | C14: 0 | D14: 0 | E14: 0 | F14: 0 | G14: 0 | H14: 0 | I14: 0 | J14: 0 | K14: 0 | L14: 0 | M14: 0 | N14: 0 | O14: 0 | P14: 0 | Q14: 0
B15: GEMINIA LIFE INSURANCE COMPANY | C15: 0 | D15: 0 | E15: 0 | F15: 0 | G15: 0 | H15: 0 | I15: 0 | J15: 0 | K15: 0 | L15: 0 | M15: 0 | N15: 0 | O15: 0 | P15: 0 | Q15: 0
B16: ICEA LION LIFE ASSURANCE | C16: 0 | D16: 0 | E16: 0 | F16: 0 | G16: 0 | H16: 0 | I16: 0 | J16: 0 | K16: 0 | L16: 0 | M16: 0 | N16: 0 | O16: 0 | P16: 0 | Q16: 0
B17: JUBILEE INSURANCE COMPANY | C17: 0 | D17: 0 | E17: 0 | F17: 0 | G17: 0 | H17: 0 | I17: 0 | J17: 0 | K17: 0 | L17: 0 | M17: 0 | N17: 0 | O17: 0 | P17: 0 | Q17: 0
... B30: THE MONARCH INSURANCE | C30: 0 | D30: 0 | E30: 0 | F30: 0 | G30: 0 | H30: 0 | I30: 0 | J30: 0 | K30: 0 | L30: 0 | M30: 0 | N30: 0 | O30: 0 | P30: 0 | Q30: 0
B31: TOTAL | C31: =SUM(C6:C30) -> 0 | D31: =SUM(D6:D30) -> 0 | E31: =SUM(E6:E30) -> 0 | F31: =SUM(F6:F30) -> 0 | G31: =SUM(G6:G30) -> 0 | H31: =SUM(H6:H30) -> 0 | I31: =SUM(I6:I30) -> 0 | J31: =SUM(J6:J30) -> 0 | ... Q31: =SUM(Q6:Q30) -> 0
B32: REINSURERS
B33: CONTINENTAL REINSURANCE | C33: 0 | D33: 0 | E33: 0 | F33: 0 | G33: 0 | H33: 0 | I33: 0 | J33: 0 | K33: 0 | L33: 0 | M33: 0 | N33: 0 | O33: 0 | P33: 0 | Q33: 0
B34: EAST AFRICA REINSURANCE | C34: 0 | D34: 0 | E34: 0 | F34: 0 | G34: 0 | H34: 0 | I34: 0 | J34: 0 | K34: 0 | L34: 0 | M34: 0 | N34: 0 | O34: 0 | P34: 0 | Q34: 0
